Workbook
Name SDBase: ScenarioDefinition!$J$8:$J$526
Name SDParam: ScenarioDefinition!$H$8:$H$526
Name DPCHG: _xlfn.LAMBDA(_xlpm.p_new,_xlpm.p_ref,_xlpm.p_new/_xlpm.p_ref-1)
Name DFAC: _xlfn.LAMBDA(_xlpm.peds,_xlpm.dp,_xlpm.eps,_xlpm.dp*IF(LEFT(_xlpm.peds,3)="Yes",(1+_xlpm.dp)^_xlpm.eps,1))
Name DTARGET: _xlfn.LAMBDA(_xlpm.share,_xlpm.cum,_xlpm.pct,MAX(0,MIN(_xlpm.share,_xlpm.pct-_xlpm.cum+_xlpm.share)))
Name DPITPICK: _xlfn.LAMBDA(_xlpm.method,_xlpm.pa,_xlpm.prop,_xlpm.te,IF(_xlpm.method="Personal Allowance",_xlpm.pa,IF(_xlpm.method="Proportional Compensation",_xlpm.prop,_xlpm.te)))
Name DPOST: _xlfn.LAMBDA(_xlpm.cons,_xlpm.loss_pct,_xlpm.cons*(1+_xlpm.loss_pct/PctPerUnit))
Name DGINI: _xlfn.LAMBDA(_xlpm.cons,_xlpm.weights,1-SUMPRODUCT(_xlpm.cons,_xlpm.weights)/SUM(_xlpm.cons))
Name WEOVal: 'Constants and Mappings'!$F$1969:$AG$2005
Name WEOKey: 'Constants and Mappings'!$A$1969:$A$2005
Name WEOYear: 'Constants and Mappings'!$F$1968:$AG$1968
Name WEOCode: WEO!$D$4:$D$9003
Name WEOLast: WEO!$A$4:$A$9003
Name WEOData: WEO!$G$4:$AU$9003
Name WEOYr: WEO!$G$3:$AU$3
Name ElaSelKey: 'Constants and Mappings'!$A$1805:$A$1924
Name ElaSel: 'Constants and Mappings'!$M$1805:$M$1924
Name EFSelKey: 'Constants and Mappings'!$A$1751:$A$1787
Name EFSel: 'Constants and Mappings'!$K$1751:$K$1787
Name NCEfKey: 'Constants and Mappings'!$A$2411:$A$2946
Name NCEfIn: 'Constants and Mappings'!$I$2411:$I$2946
Name NCEfFin: 'Constants and Mappings'!$J$2411:$J$2946
Name CtryReg: 'Constants and Mappings'!$C$43
Name PIntVal: 'Constants and Mappings'!$J$2014:$AH$2069
Name PIntKey: 'Constants and Mappings'!$A$2014:$A$2069
Name PIntYear: 'Constants and Mappings'!$J$2012:$AH$2012
Name PTechVal: 'Constants and Mappings'!$A$2269:$AU$2277
Name PTechKey: 'Constants and Mappings'!$A$2269:$A$2277
Name PTechHdr: 'Constants and Mappings'!$A$2268:$AU$2268
Name PParVal: 'Constants and Mappings'!$D$2359:$D$2403
Name PParKey: 'Constants and Mappings'!$A$2359:$A$2403
Name PsMinTE: 'Constants and Mappings'!$B$2222
Name PsHydNoRet: 'Constants and Mappings'!$B$2223
Name PsScNonVRE: 'Constants and Mappings'!$B$2224
Name PsScNonNuc: 'Constants and Mappings'!$B$2225
Name PsScCat: 'Constants and Mappings'!$B$2226
Name PsScUser: 'Constants and Mappings'!$B$2227
Name PsWaccSrc: 'Constants and Mappings'!$B$2228
Name PsWaccUser: 'Constants and Mappings'!$B$2229
Name PsWaccMin: 'Constants and Mappings'!$B$2230
Name PsReDecline: 'Constants and Mappings'!$B$2231
Name PsLTHours: 'Constants and Mappings'!$B$2232
Name PsIncElAdj: 'Constants and Mappings'!$B$2233
Name PsPass: 'Constants and Mappings'!$B$2234
Name PsSTAlloc: 'Constants and Mappings'!$B$2235
Name PsSTHours: 'Constants and Mappings'!$B$2236
Name PsSTRatio: 'Constants and Mappings'!$B$2237
Name PsLTAlloc: 'Constants and Mappings'!$B$2238
Name PsLTStart: 'Constants and Mappings'!$B$2239
Name PsAddEff: 'Constants and Mappings'!$B$2240
Name PsMaxCoalCF: 'Constants and Mappings'!$B$2241
Name PsKDisp: 'Constants and Mappings'!$B$2242
Name PsKInv: 'Constants and Mappings'!$B$2243
Name PsMinCost: 'Constants and Mappings'!$B$2244
Name PsEarlyMax: 'Constants and Mappings'!$B$2245
Name PsEarlyBL: 'Constants and Mappings'!$B$2246
Name PsCFMinVRE: 'Constants and Mappings'!$B$2247
Name PsCFMinOth: 'Constants and Mappings'!$B$2248
Name PsCFMax: 'Constants and Mappings'!$B$2249
Name PsCtryWacc: 'Constants and Mappings'!$B$2253

Sheet Cover
A2: CPAT-AI-Distribution v1.2.0: Cover page
A3: The distribution module of the Climate Policy Assessment Tool (CPAT): the effect of the scenarios of the mitigation prototype on households, by decile, in one analysis year.
A5: How to use it (one scenario at a time)
A6: 1. | B6: In the mitigation workbook: define the scenario, recalculate (F9), save.
A7: 2. | B7: In the Master workbook (CPAT-AI-Master_UserGuide.xlsm, active_workbooks): Update Distribution from Mitigation. It copies section 19a of the mitigation workbook into FromMitigation here and recalculates.
A8: 3. | B8: Read the results on Distribution (one column group per scenario, deciles across).
A9: 4. | B9: Distribution settings of a scenario (analysis year, revenue recycling, targeting): ScenarioDefinition, then recalculate (F9).
A11: Link to the mitigation workbook
A12: Mitigation workbook (input) | B12: CPAT-AI-Mitigation_latest.xlsx
B13: The Master workbook copies section 19a of this mitigation workbook into FromMitigation (the activated .xlsb in active_workbooks, else the .xlsx in excel_ai\mitigation)
A14: File used by the last update | B14: none (shipped values)
A15: Last update | B15: shipped: values of CPAT-AI-Mitigation_latest.xlsx v1.2.0
A16: Country (Settings C4) | B16: =CtryCode -> EGY
A17: Calculation | B17: Shipped with its values, manual calculation: F9 recalculates; the Master workbook activates it
A19: Contents
A20: Tab | B20: Content
A21: Cover | B21: This page: what the module is, the link to the mitigation workbook
A22: ScenarioDefinition | B22: The distribution settings of each scenario (the other rows, set in the mitigation workbook, are hidden)
A23: FromMaster | B23: What the Master workbook wrote here (activation, data source): values
A24: FromMitigation | B24: The inputs from Mitigation (section 19a of the mitigation workbook): values, refreshed by the Master workbook (Update Distribution from Mitigation)
A25: Distribution | B25: The model: household incidence by decile in the analysis year, one column group per scenario
A26: Constants and Mappings | B26: Settings, constants, mappings and the data step of the mitigation workbook (those Mitigation reads are values here)
A27: DistMapping ... WEO | B27: The data tabs: mappings, input-output table, household survey, elasticities, ASPIRE, cooking fuels, GDP ratios, WEO
A29: Limits
B30: The data tabs and the Settings lookups are those of the prototype v1.2.0 (Egypt). Another country needs its own data tabs; its Mitigation inputs come from the mitigation workbook of that country.
B31: The scenario columns of ScenarioDefinition must carry the scenario numbers of the mitigation workbook (FromMitigation row 5).
A33: Version log
A34: Version | B34: Change | C34: Date
A35: 0.1.0 | B35: First standalone module, cut from the mitigation prototype v1.2.0: its Distribution and FromMitigation tabs, the distribution data tabs, the distribution rows of ScenarioDefinition and Settings. Inputs from Mitigation by the button Update from Mitigation (section 19a, defined name ExportDistn). | C35: 2026-10-22
A36: 0.1.1 | B36: Cut from the mitigation prototype v1.2.0: ScenarioDefinition on the rows of legacy 465 with a complete set of names (bug L137, issue I87); the mitigation workbook is looked for in permalink/ too; file named _v0.1.1 at the top of excel_ai/ (NORMS 5a). | C36: 2026-10-28
A37: 0.1.2 | B37: Cut from the mitigation prototype v1.2.0 (combustion emission factors as legacy, issue I98; data problems as issues). | C37: 2026-10-29
A38: 0.1.3 | B38: Cut from the mitigation prototype v1.2.0 (remaining functionality, reverts to legacy, data from legacy 465, last historical price year 2024); the Distribution method unchanged. | C38: 2026-10-29
A39: 0.1.4 | B39: Cut from the mitigation prototype v1.2.0: bug M22 fixed (found by Coded CPAT): the 25th/75th percentile recycling rows (hrec) add the public investment amount per person (pui of the sample, LCU), not its % row. | C39: 2026-10-29
A40: 1.0.0 | B40: First full release (user 2026-10-29), cut from the mitigation prototype v1.2.0: Distribution 0.1.4 as released. Replicated number for number by Coded CPAT 1.0.0p1.0. | C40: 2026-10-29
A41: 1.0.2 | B41: Cut from the mitigation prototype v1.2.0 (version aligned with Mitigation and Coded CPAT; ScenarioDefinition has the input row ModelForm). The Distribution method unchanged. | C41: 2026-10-29
A42: 1.0.3 | B42: Cut from the mitigation prototype v1.2.0. Update from Mitigation also looks in permalink_countryeditable\ (next to this workbook and one folder up) before permalink\. The Distribution method unchanged. | C42: 2026-10-29
A43: 1.0.4 | B43: Cut from the mitigation prototype v1.2.0 (outputs tab MTOutputs in the legacy layout); versions aligned. The Distribution method unchanged. | C43: 2026-10-29
A44: 1.1.0 | B44: Cut from the mitigation prototype v1.2.0: data edition Public01 (perturbed proprietary tables); Update from Mitigation looks next to this workbook, then in active_workbooks\ (one or two folders up). The Distribution method unchanged. | C44: 2026-10-30
A45: 1.2.0 | B45: Renamed CPAT-AI-Distribution (user 2026-10-31); cut from a full build of the mitigation workbook v1.2.0 (which no longer holds Distribution); .xlsx without macros: the Master workbook activates it and updates FromMitigation; tab FromMaster. The Distribution method and values unchanged. | C45: 2026-10-31

Sheet ScenarioDefinition
B1: MTInputs template - row structure copied exactly from legacy CPAT MTInputs (CPAT 1.0pre_465) | J1: Distribution module: only the distribution rows are shown (the other rows are set in the mitigation workbook). Scenario numbers (row 5) as in the mitigation workbook.
B2: Do not insert/delete rows. Columns D:E are hidden placeholders (MT values, Dashboard values). | H2: Short name (chart legends) | J2: Base | K2: CP20 | L2: CP20-b | M2: PkgA | N2: PkgB | O2: CP50
B3: Rows must match legacy 465 exactly. Column H: the names of the codes map (tab Inputs; legacy name kept there). See NORMS.md section 4. | J3: Scenario columns: short name in row 2, number in row 5, name in row 6; red = changed from the template value. J = baseline, K = live policy scenario (Mitigation group 2). | L3: Scenario definitions: row 4 Run? = Yes for the batch run (the Master workbook copies each into column K, runs it and stores the results). Copy the last definition one column to the right to add one.
J4: Baseline (stored once) | K4: Live (batch target) | L4: Yes | M4: Yes | N4: Yes | O4: Yes
C5: FALSE | D5: <-- Should normally be "FALSE"! | J5: 1 | K5: =J5+1 -> 2 | L5: =K5+1 -> 3 | M5: =L5+1 -> 4 | N5: =M5+1 -> 5 | O5: =N5+1 -> 6
D6: 6 | J6: Baseline (no carbon price) | K6: Carbon price $20/tCO2 from 2027 | L6: Carbon price $20/tCO2 from 2027 | M6: Package A: carbon tax to $50 by 2030 + feebates (transport, industry) | N6: Package B: ETS on power and industry (cap -5% 2027 to -20% 2035) + carbon tax $25 elsewhere | O6: Carbon price $50/tCO2 from 2027
B7: Parameters | C7: unit | D7: MT values | E7: "Dashboard" values | F7: Used for calculation | G7: Defaults | H7: NameOfParameter | J7: Used for calculation | K7: Used for calculation | L7: Used for calculation | M7: Used for calculation | N7: Used for calculation | O7: Used for calculation
B8: Country | F8: Egypt | G8: Egypt | H8: Countryname | J8: Egypt | K8: Egypt | L8: Egypt | M8: Egypt | N8: Egypt | O8: Egypt
B9: Scenario identification
B10: Scenario ID | C10: # | F10: N/A | G10: N/A | H10: MSTScenarioID | J10: =J$5 -> 1 | K10: =K$5 -> 2 | L10: =L$5 -> 3 | M10: =M$5 -> 4 | N10: =N$5 -> 5 | O10: =O$5 -> 6
B11: Scenario status | C11: switch | F11: N/A | G11: N/A | H11: ScenarioStatus | J11: N/A | K11: N/A | L11: N/A | M11: N/A | N11: N/A | O11: N/A
B12: Scenario name | C12: name | F12: N/A | G12: N/A | H12: ScenarioName | J12: =J$6 -> Baseline (no carbon price) | K12: =K$6 -> Carbon price $20/tCO2 from 2027 | L12: =L$6 -> Carbon price $20/tCO2 from 2027 | M12: =M$6 -> Package A: carbon tax to $50 by 2030 + feebates (transport, industry) | N12: =N$6 -> Package B: ETS on power and industry (cap -5% 2027 to -20% 2035) + carbon tax $25 elsewhere | O12: =O$6 -> Carbon price $50/tCO2 from 2027
B13: Chosen policy | C13: switch | F13: - Carbon tax | G13: - Carbon tax | H13: ScenarioSelected | J13: - Carbon tax | K13: - Carbon tax | L13: - Carbon tax | M13: - Carbon tax | N13: - Carbon tax | O13: - Carbon tax
B14: Scenario status for macro | C14: # | F14: N/A | G14: N/A | H14: ScenarioStatusMacro | J14: N/A | K14: N/A | L14: N/A | M14: N/A | N14: N/A | O14: N/A
B15: Scenario parameters override? | C15: # | F15: N/A | G15: N/A | H15: ScenarioParamOverride | J15: N/A | K15: N/A | L15: N/A | M15: N/A | N15: N/A | O15: N/A
B16: CPAT-side parameters override? | C16: switch | F16: Manual* | G16: Manual* | H16: CPATDefaultsOrUserDefined | J16: Manual* | K16: Manual* | L16: Manual* | M16: Manual* | N16: Manual* | O16: Manual*
B17: Carbon pricing: main inputs
A18: X | B18: Carbon pricing start year | C18: year | F18: 2026 | G18: 2027 | H18: CPIntro | J18: 2027 | K18: 2027 | L18: 2027 | M18: 2027 | N18: 2027 | O18: 2027
A19: X | B19: Starting carbon price | C19: nom. USD/tCO2 | F19: 0 | G19: 20 | H19: CPLevelStart | J19: 0 | K19: 20 | L19: 20 | M19: 10 | N19: 25 | O19: 50
B20: Target level of carbon price | C20: nom. USD/tCO2 | F20: 50 | G20: 50 | H20: CPLevelTarget | J20: 0 | K20: 20 | L20: 20 | M20: 50 | N20: 25 | O20: 50
A21: X | B21: Year to reach target level | C21: year | F21: 2030 | G21: 2035 | H21: CPOutro | J21: 2030 | K21: 2030 | L21: 2030 | M21: 2030 | N21: 2030 | O21: 2030
B22: Carbon pricing: fuel coverage
B23: Apply tax to coal? | C23: switch | F23: TRUE | G23: TRUE | H23: MCovCoa | J23: TRUE | K23: TRUE | L23: TRUE | M23: TRUE | N23: TRUE | O23: TRUE
B24: Apply tax to natural gas? | C24: switch | F24: TRUE | G24: TRUE | H24: MCovNga | J24: TRUE | K24: TRUE | L24: TRUE | M24: TRUE | N24: TRUE | O24: TRUE
B25: Apply tax to gasoline? | C25: switch | F25: TRUE | G25: TRUE | H25: MCovGso | J25: TRUE | K25: TRUE | L25: TRUE | M25: TRUE | N25: TRUE | O25: TRUE
B26: Apply tax to diesel? | C26: switch | F26: TRUE | G26: TRUE | H26: MCovDie | J26: TRUE | K26: TRUE | L26: TRUE | M26: TRUE | N26: TRUE | O26: TRUE
B27: Apply tax to LPG? | C27: switch | F27: TRUE | G27: TRUE | H27: MCovLpg | J27: TRUE | K27: TRUE | L27: TRUE | M27: TRUE | N27: TRUE | O27: TRUE
B28: Apply tax to kerosene? | C28: switch | F28: TRUE | G28: TRUE | H28: MCovKer | J28: TRUE | K28: TRUE | L28: TRUE | M28: TRUE | N28: TRUE | O28: TRUE
B29: Apply tax to non-road oil products? | C29: switch | F29: TRUE | G29: TRUE | H29: MCovOop | J29: TRUE | K29: TRUE | L29: TRUE | M29: TRUE | N29: TRUE | O29: TRUE
B30: Carbon pricing: sector coverage
B31: Apply tax to power sector? | C31: switch | F31: TRUE | G31: TRUE | H31: MCovPow | J31: TRUE | K31: TRUE | L31: TRUE | M31: TRUE | N31: TRUE | O31: TRUE
B32: Apply tax to road transportation? | C32: switch | F32: TRUE | G32: TRUE | H32: MCovRod | J32: TRUE | K32: TRUE | L32: TRUE | M32: TRUE | N32: TRUE | O32: TRUE
B33: Apply tax to rail transportation? | C33: switch | F33: TRUE | G33: TRUE | H33: MCovRal | J33: TRUE | K33: TRUE | L33: TRUE | M33: TRUE | N33: TRUE | O33: TRUE
B34: Apply tax to domestic aviation? | C34: switch | F34: TRUE | G34: TRUE | H34: MCovAvi | J34: TRUE | K34: TRUE | L34: TRUE | M34: TRUE | N34: TRUE | O34: TRUE
B35: Apply tax to domestic shipping? | C35: switch | F35: TRUE | G35: TRUE | H35: MCovNav | J35: TRUE | K35: TRUE | L35: TRUE | M35: TRUE | N35: TRUE | O35: TRUE
B36: Apply tax to residential sector? | C36: switch | F36: TRUE | G36: TRUE | H36: MCovRes | J36: TRUE | K36: TRUE | L36: TRUE | M36: TRUE | N36: TRUE | O36: TRUE
B37: Apply tax to food & forestry? | C37: switch | F37: TRUE | G37: TRUE | H37: MCovFoo | J37: TRUE | K37: TRUE | L37: TRUE | M37: TRUE | N37: TRUE | O37: TRUE
B38: Apply tax to services (private / public)? | C38: switch | F38: TRUE | G38: TRUE | H38: MCovSrv | J38: TRUE | K38: TRUE | L38: TRUE | M38: TRUE | N38: TRUE | O38: TRUE
B39: Apply tax to mining & chemicals? | C39: switch | F39: TRUE | G39: TRUE | H39: MCovMch | J39: TRUE | K39: TRUE | L39: TRUE | M39: TRUE | N39: TRUE | O39: TRUE
B40: Apply tax to iron and steel? | C40: switch | F40: TRUE | G40: TRUE | H40: MCovIrn | J40: TRUE | K40: TRUE | L40: TRUE | M40: TRUE | N40: TRUE | O40: TRUE
B41: Apply tax to non-ferrous metals? | C41: switch | F41: TRUE | G41: TRUE | H41: MCovNfm | J41: TRUE | K41: TRUE | L41: TRUE | M41: TRUE | N41: TRUE | O41: TRUE
B42: Apply tax to machinery? | C42: switch | F42: TRUE | G42: TRUE | H42: MCovMac | J42: TRUE | K42: TRUE | L42: TRUE | M42: TRUE | N42: TRUE | O42: TRUE
... B47: Apply tax to other energy use? | C47: switch | F47: TRUE | G47: TRUE | H47: MCovOen | J47: FALSE | K47: FALSE | L47: FALSE | M47: FALSE | N47: FALSE | O47: FALSE
B48: Exemptions phaseout
B49: Apply exemption phaseout? | C49: switch | F49: FALSE | G49: FALSE | H49: ExemptPhaseout | J49: FALSE | K49: FALSE | L49: FALSE | M49: FALSE | N49: FALSE | O49: FALSE
B50: Year to start exemption phaseout (if applicable) | C50: year | F50: 2027 | G50: 2027 | H50: YearPha | J50: 2027 | K50: 2027 | L50: 2027 | M50: 2027 | N50: 2027 | O50: 2027
B51: Period to reach full exemption phaseout (if applicable) | C51: year | F51: 5 | G51: 5 | H51: ExemptPhaseoutPeriod | J51: 5 | K51: 5 | L51: 5 | M51: 5 | N51: 5 | O51: 5
B52: Feebates: Starting and End Date
B53: Start date | F53: 2027 | G53: 2027 | H53: FeebateIntro | J53: 2027 | K53: 2027 | L53: 2027 | M53: 2027 | N53: 2027 | O53: 2027
B54: Target date | F54: 2035 | G54: 2035 | H54: FeebateOutro | J54: 2035 | K54: 2035 | L54: 2035 | M54: 2030 | N54: 2035 | O54: 2035
B55: Feebates: Feebate starting rate
B56: Power sector | C56: USD/tCO2 | F56: 0 | G56: 0 | H56: Feb_Level_Start_Pow | J56: 0 | K56: 0 | L56: 0 | M56: 0 | N56: 0 | O56: 0
B57: Transport | C57: USD/tCO2 | F57: 0 | G57: 0 | H57: Feb_Level_Start_Trans | J57: 0 | K57: 0 | L57: 0 | M57: 10 | N57: 0 | O57: 0
B58: Residential | C58: USD/tCO2 | F58: 0 | G58: 0 | H58: Feb_Level_Start_Res | J58: 0 | K58: 0 | L58: 0 | M58: 0 | N58: 0 | O58: 0
B59: Industry | C59: USD/tCO2 | F59: 0 | G59: 0 | H59: Feb_Level_Start_Ind | J59: 0 | K59: 0 | L59: 0 | M59: 5 | N59: 0 | O59: 0
B60: Feebates: Feebate target rate
B61: Power sector | C61: USD/tCO2 | F61: 0 | G61: 0 | H61: Feb_Level_Target_Pow | J61: 0 | K61: 0 | L61: 0 | M61: 0 | N61: 0 | O61: 0
B62: Transport | C62: USD/tCO2 | F62: 0 | G62: 0 | H62: Feb_Level_Target_Trans | J62: 0 | K62: 0 | L62: 0 | M62: 50 | N62: 0 | O62: 0
B63: Residential | C63: USD/tCO2 | F63: 0 | G63: 0 | H63: Feb_Level_Target_Res | J63: 0 | K63: 0 | L63: 0 | M63: 0 | N63: 0 | O63: 0
B64: Industry | C64: USD/tCO2 | F64: 0 | G64: 0 | H64: Feb_Level_Target_Ind | J64: 0 | K64: 0 | L64: 0 | M64: 25 | N64: 0 | O64: 0
B65: Feebates sector coverage
B66: Apply tax to power sector? | C66: switch | F66: FALSE | G66: TRUE | H66: FbCovPow | J66: FALSE | K66: FALSE | L66: FALSE | M66: FALSE | N66: FALSE | O66: FALSE
B67: Apply tax to road transportation? | F67: FALSE | G67: FALSE | H67: FbCovRod | J67: FALSE | K67: FALSE | L67: FALSE | M67: TRUE | N67: FALSE | O67: FALSE
B68: Apply tax to rail transportation? | F68: FALSE | G68: FALSE | H68: FbCovRal | J68: FALSE | K68: FALSE | L68: FALSE | M68: FALSE | N68: FALSE | O68: FALSE
B69: Apply tax to domestic aviation? | F69: FALSE | G69: FALSE | H69: FbCovAvi | J69: FALSE | K69: FALSE | L69: FALSE | M69: FALSE | N69: FALSE | O69: FALSE
B70: Apply tax to domestic shipping? | F70: FALSE | G70: FALSE | H70: FbCovNav | J70: FALSE | K70: FALSE | L70: FALSE | M70: FALSE | N70: FALSE | O70: FALSE
B71: Apply tax to residential sector? | C71: switch | F71: FALSE | G71: TRUE | H71: FbCovRes | J71: FALSE | K71: FALSE | L71: FALSE | M71: FALSE | N71: FALSE | O71: FALSE
B72: Apply tax to food & forestry? | F72: FALSE | G72: TRUE | H72: FbCovFoo | J72: FALSE | K72: FALSE | L72: FALSE | M72: FALSE | N72: FALSE | O72: FALSE
B73: Apply tax to services (private / public)? | F73: FALSE | G73: TRUE | H73: FbCovSrv | J73: FALSE | K73: FALSE | L73: FALSE | M73: FALSE | N73: FALSE | O73: FALSE
B74: Apply tax to mining & chemicals? | F74: TRUE | G74: TRUE | H74: FbCovMch | J74: TRUE | K74: TRUE | L74: TRUE | M74: TRUE | N74: TRUE | O74: TRUE
B75: Apply tax to iron and steel? | F75: FALSE | G75: TRUE | H75: FbCovIrn | J75: FALSE | K75: FALSE | L75: FALSE | M75: TRUE | N75: FALSE | O75: FALSE
B76: Apply tax to non-ferrous metals? | F76: TRUE | G76: TRUE | H76: FbCovNfm | J76: TRUE | K76: TRUE | L76: TRUE | M76: TRUE | N76: TRUE | O76: TRUE
B77: Apply tax to machinery? | F77: TRUE | G77: TRUE | H77: FbCovMac | J77: TRUE | K77: TRUE | L77: TRUE | M77: TRUE | N77: TRUE | O77: TRUE
B78: Apply tax to cement? | F78: TRUE | G78: TRUE | H78: FbCovCem | J78: TRUE | K78: TRUE | L78: TRUE | M78: TRUE | N78: TRUE | O78: TRUE
B79: Apply tax to other manucfacturing? | F79: TRUE | G79: TRUE | H79: FbCovOmn | J79: TRUE | K79: TRUE | L79: TRUE | M79: TRUE | N79: TRUE | O79: TRUE
B80: Apply tax to construction? | F80: TRUE | G80: TRUE | H80: FbCovCst | J80: TRUE | K80: TRUE | L80: TRUE | M80: TRUE | N80: TRUE | O80: TRUE
B81: Apply tax to fuel transformation? | F81: TRUE | G81: TRUE | H81: FbCovFtr | J81: TRUE | K81: TRUE | L81: TRUE | M81: TRUE | N81: TRUE | O81: TRUE
B82: Apply tax to other energy use? | F82: TRUE | G82: TRUE | H82: FbCovOen | J82: TRUE | K82: TRUE | L82: TRUE | M82: TRUE | N82: TRUE | O82: TRUE
B83: ETS Main Characteristics
B84: Apply new ETS? | F84: No | G84: No | H84: NewETS | J84: No | K84: No | L84: No | M84: No | N84: Yes | O84: No
B85: Change Relative to Baseline in Start Year | F85: 0 | G85: 0 | H85: ETSChangeRelStart | J85: 0 | K85: 0 | L85: 0 | M85: 0 | N85: -0.05 | O85: 0
B86: Change Relative to Baseline in Target Year | F86: 0 | G86: 0 | H86: ETSChangeRelTarget | J86: 0 | K86: 0 | L86: 0 | M86: 0 | N86: -0.2 | O86: 0
B87: Cap continuation after target year? | F87: Constant | G87: KeepRelativeCapConstant | H87: ETSCapCont | J87: Constant | K87: Constant | L87: Constant | M87: Constant | N87: Constant | O87: Constant
B88: ETS Start Year | F88: 2027 | G88: 2026 | H88: ETSIntro | J88: 2027 | K88: 2027 | L88: 2027 | M88: 2027 | N88: 2027 | O88: 2027
B89: ETS Target Year | F89: 2035 | G89: 2035 | H89: ETSOutro | J89: 2035 | K89: 2035 | L89: 2035 | M89: 2035 | N89: 2035 | O89: 2035
B90: Proportion Auctioned in Starting Year | F90: 0 | G90: 0 | H90: ETSAuctStart | J90: 0 | K90: 0 | L90: 0 | M90: 0 | N90: 0 | O90: 0
B91: Proportion Auctioned in Target Year | F91: 0 | G91: 1 | H91: ETSAuctTarget | J91: 0 | K91: 0 | L91: 0 | M91: 0 | N91: 0 | O91: 0
B92: Auction proportion continuation after target year? | F92: Constant | G92: Constant | H92: ETSAuctCont | J92: Constant | K92: Constant | L92: Constant | M92: Constant | N92: Constant | O92: Constant
B93: Override ETS price | F93: No | G93: No | H93: ETSPriceOverride | J93: No | K93: No | L93: No | M93: No | N93: No | O93: No
B94: ETS: modelling assumptions
B95: ETS Volatility | F95: Medium* | G95: Medium* | H95: ETSVolatility | J95: Medium* | K95: Medium* | L95: Medium* | M95: Medium* | N95: Medium* | O95: Medium*
B96: Impact of Volatility on Abatement Costs | F96: Medium* | G96: Medium* | H96: ETSVolImpact | J96: Medium* | K96: Medium* | L96: Medium* | M96: Medium* | N96: Medium* | O96: Medium*
B97: Carbon Tax Policy Risk | F97: 0.2 | G97: 0.2 | H97: ETSCTRisk | J97: 0.2 | K97: 0.2 | L97: 0.2 | M97: 0.2 | N97: 0.2 | O97: 0.2
B98: ETS: sector coverage
B99: power sector | C99: switch | F99: TRUE | G99: TRUE | H99: ETSCovPow | J99: TRUE | K99: TRUE | L99: TRUE | M99: TRUE | N99: TRUE | O99: TRUE
B100: road transportation | F100: FALSE | G100: TRUE | H100: ETSCovRod | J100: FALSE | K100: FALSE | L100: FALSE | M100: FALSE | N100: FALSE | O100: FALSE
B101: rail transportation | F101: FALSE | G101: TRUE | H101: ETSCovRal | J101: FALSE | K101: FALSE | L101: FALSE | M101: FALSE | N101: FALSE | O101: FALSE
B102: domestic aviation | F102: FALSE | G102: TRUE | H102: ETSCovAvi | J102: FALSE | K102: FALSE | L102: FALSE | M102: FALSE | N102: FALSE | O102: FALSE
B103: domestic shipping | F103: FALSE | G103: TRUE | H103: ETSCovNav | J103: FALSE | K103: FALSE | L103: FALSE | M103: FALSE | N103: FALSE | O103: FALSE
B104: residential | C104: switch | F104: FALSE | G104: TRUE | H104: ETSCovRes | J104: FALSE | K104: FALSE | L104: FALSE | M104: FALSE | N104: FALSE | O104: FALSE
...

Sheet FromMaster
A2: FromMaster - what the Master workbook wrote here (activation, data source); values
A3: Written by the macros of the Master workbook (CPAT-AI-Master_UserGuide.xlsm, active_workbooks); read by the Cover. Values only: the module has no macros and no link to another file.
A5: Name | B5: Item | C5: Value
A6: FMMaster | B6: Master workbook (writes this tab) | C6: CPAT-AI-Master_UserGuide.xlsm
A7: FMVersion | B7: Version of the Master that last wrote here | C7: none (shipped)
A8: FMActivated | B8: Activated (formulas to the last year, recalculated, saved as .xlsb) | C8: not activated: formulas to 2035
A9: FMSource | B9: Data source of the linked tables | C9: Embedded (shipped data, no update)
A10: FMRows | B10: Rows loaded (Country = the country of MTInputs; All countries) | C10: Country
A11: FMPath | B11: File or URL of the data source

Sheet FromMitigation
H1: Year | K1: Scenario: output code | L1: 2022 | M1: 2023 | N1: 2024 | O1: 2025 | P1: 2026 | Q1: 2027 | R1: 2028 | S1: 2029 | T1: 2030 | U1: 2031 | V1: 2032 | W1: 2033 | X1: 2034 | Y1: 2035 | Z1: 2036 | AA1: 2037 | AB1: 2038 | AC1: 2039 | AD1: 2040 | AE1: 2041 | AG1: Scenario: output code | AH1: 2022 | AI1: 2023 | AJ1: 2024 | AK1: 2025 | AL1: 2026 | AM1: 2027 | AN1: 2028 | AO1: 2029 | AP1: 2030 | AQ1: 2031 | AR1: 2032 | AS1: 2033 | AT1: 2034 | AU1: 2035 | AV1: 2036 | AW1: 2037 | AX1: 2038 | AY1: 2039 | AZ1: 2040 | BA1: 2041
A2: FromMitigation - the inputs of the distribution module from Mitigation (section 19a)
H5: Scenario number | K5: 1 | L5: 1 | M5: 1 | N5: 1 | O5: 1 | P5: 1 | Q5: 1 | R5: 1 | S5: 1 | T5: 1 | U5: 1 | V5: 1 | W5: 1 | X5: 1 | Y5: 1 | Z5: 1 | AA5: 1 | AB5: 1 | AC5: 1 | AD5: 1 | AE5: 1 | AG5: 2 | AH5: 2 | AI5: 2 | AJ5: 2 | AK5: 2 | AL5: 2 | AM5: 2 | AN5: 2 | AO5: 2 | AP5: 2 | AQ5: 2 | AR5: 2 | AS5: 2 | AT5: 2 | AU5: 2 | AV5: 2 | AW5: 2 | AX5: 2 | AY5: 2 | AZ5: 2 | BA5: 2
A7: Variable | B7: Fuel | C7: Sector | D7: Scale to base unit | E7: Base unit | H7: Description | I7: Unit (Mitigation) | J7: Source
A8: gdp.lcu | B8: all | C8: all | D8: 1000000000 | E8: LCU | H8: Real GDP, baseline (local currency bn, sheet WEO; legacy row 464; v0.3.13) | I8: LCU bn | J8: Mitigation section 19a | K8: egy.mit.gdp.lcu.all.all.1 | L8: 7842.5 | M8: 8137.4 | N8: 8332.6 | O8: 8698.6 | P8: 9067.395 | Q8: 9505.2793 | R8: 10031.427 | S8: 10555.73 | T8: 11066.825 | U8: 11596.786 | V8: 12145.963 | W8: 12714.692 | X8: 13303.295 | Y8: 13912.077 | Z8: 14541.324 | AA8: 15191.305 | AB8: 15862.267 | AC8: 16554.434 | AD8: 17268.008 | AE8: 18003.163 | AG8: egy.mit.gdp.lcu.all.all.2 | AH8: 7842.5 | AI8: 8137.4 | AJ8: 8332.6 | AK8: 8698.6 | AL8: 9067.395 | AM8: 9505.2793 | AN8: 10031.427 | AO8: 10555.73 | AP8: 11066.825 | AQ8: 11596.786 | AR8: 12145.963 | AS8: 12714.692 | AT8: 13303.295 | AU8: 13912.077 | AV8: 14541.324 | AW8: 15191.305 | AX8: 15862.267 | AY8: 16554.434 | AZ8: 17268.008 | BA8: 18003.163
A9: xr | B9: all | C9: all | D9: 1 | H9: Exchange rate implied by real GDP: local currency per USD, constant in real terms (v0.3.13) | I9: LCU/USD | J9: Mitigation section 19a | K9: egy.mit.xr.all.all.1 | L9: 14.338056 | M9: 14.338056 | N9: 14.338056 | O9: 14.338056 | P9: 14.338056 | Q9: 14.338056 | R9: 14.338056 | S9: 14.338056 | T9: 14.338056 | U9: 14.338056 | V9: 14.338056 | W9: 14.338056 | X9: 14.338056 | Y9: 14.338056 | Z9: 14.338056 | AA9: 14.338056 | AB9: 14.338056 | AC9: 14.338056 | AD9: 14.338056 | AE9: 14.338056 | AG9: egy.mit.xr.all.all.2 | AH9: 14.338056 | AI9: 14.338056 | AJ9: 14.338056 | AK9: 14.338056 | AL9: 14.338056 | AM9: 14.338056 | AN9: 14.338056 | AO9: 14.338056 | AP9: 14.338056 | AQ9: 14.338056 | AR9: 14.338056 | AS9: 14.338056 | AT9: 14.338056 | AU9: 14.338056 | AV9: 14.338056 | AW9: 14.338056 | AX9: 14.338056 | AY9: 14.338056 | AZ9: 14.338056 | BA9: 14.338056
A10: pop | B10: all | C10: all | D10: 1000 | E10: persons | H10: Population | All sectors | All fuels | I10: thousand | J10: Mitigation section 19a | K10: egy.mit.pop.all.all.1 | L10: 111743.37 | M10: 113493.13 | N10: 116538.26 | O10: 118365.99 | P10: 120101.18 | Q10: 121847.62 | R10: 123608.46 | S10: 125373.05 | T10: 127139.32 | U10: 128912.25 | V10: 130695.08 | W10: 132485.61 | X10: 134287.84 | Y10: 136097.22 | Z10: 137913.26 | AA10: 139738.7 | AB10: 141565.83 | AC10: 143393.26 | AD10: 145213.65 | AE10: 147018.56 | AG10: egy.mit.pop.all.all.2 | AH10: 111743.37 | AI10: 113493.13 | AJ10: 116538.26 | AK10: 118365.99 | AL10: 120101.18 | AM10: 121847.62 | AN10: 123608.46 | AO10: 125373.05 | AP10: 127139.32 | AQ10: 128912.25 | AR10: 130695.08 | AS10: 132485.61 | AT10: 134287.84 | AU10: 136097.22 | AV10: 137913.26 | AW10: 139738.7 | AX10: 141565.83 | AY10: 143393.26 | AZ10: 145213.65 | BA10: 147018.56
A11: rnew | B11: all | C11: all | D11: 1000000 | E11: USD | H11: Revenue from new policies (carbon tax, excise, auctioned ETS, VAT on them) | All sectors | All fuels | I11: USD m real | J11: Mitigation section 19a | K11: egy.mit.rnew.tot.tot.1 | L11: 0 | M11: 0 | N11: 0 | O11: 0 | P11: 0 | Q11: 0 | R11: 0 | S11: 0 | T11: 0 | U11: 0 | V11: 0 | W11: 0 | X11: 0 | Y11: 0 | Z11: 0 | AA11: 0 | AB11: 0 | AC11: 0 | AD11: 0 | AE11: 0 | AG11: egy.mit.rnew.tot.tot.2 | AH11: 0 | AI11: 0 | AJ11: 0 | AK11: 0 | AL11: 0 | AM11: 4963.4827 | AN11: 4909.8102 | AO11: 5096.3675 | AP11: 5190.4642 | AQ11: 5272.9227 | AR11: 5320.241 | AS11: 5439.2411 | AT11: 5531.8505 | AU11: 5641.1717 | AV11: 5752.113 | AW11: 5867.3621 | AX11: 5981.4069 | AY11: 6096.0896 | AZ11: 6209.0057 | BA11: 6323.0646
A12: atp | B12: coa | C12: res | D12: 1 | H12: After-tax price | Residential | Coal | I12: USD/GJ real | J12: Mitigation section 19a | K12: egy.mit.atp.res.coa.1 | L12: 23.57658 | M12: 15.452973 | N12: 14.483227 | O12: 13.293239 | P12: 13.948916 | Q12: 14.09682 | R12: 14.026689 | S12: 13.951483 | T12: 13.870992 | U12: 13.793315 | V12: 13.793315 | W12: 13.793315 | X12: 13.793315 | Y12: 13.793315 | Z12: 13.793315 | AA12: 13.793315 | AB12: 13.793315 | AC12: 13.793315 | AD12: 13.793315 | AE12: 13.793315 | AG12: egy.mit.atp.res.coa.2 | AH12: 23.57658 | AI12: 15.452973 | AJ12: 14.483227 | AK12: 13.293239 | AL12: 13.948916 | AM12: 16.237272 | AN12: 16.167141 | AO12: 16.091935 | AP12: 16.011444 | AQ12: 15.933767 | AR12: 15.933767 | AS12: 15.933767 | AT12: 15.933767 | AU12: 15.933767 | AV12: 15.933767 | AW12: 15.933767 | AX12: 15.933767 | AY12: 15.933767 | AZ12: 15.933767 | BA12: 15.933767
A13: atp | B13: nga | C13: res | D13: 1 | H13: After-tax price | Residential | Natural gas | I13: USD/GJ real | J13: Mitigation section 19a | K13: egy.mit.atp.res.nga.1 | L13: 4.9564885 | M13: 2.7348469 | N13: 1.7971601 | O13: 1.7971601 | P13: 1.7971601 | Q13: 1.7971601 | R13: 1.7971601 | S13: 1.7971601 | T13: 1.7971601 | U13: 1.7971601 | V13: 1.7971601 | W13: 1.7971601 | X13: 1.7971601 | Y13: 1.7971601 | Z13: 1.7971601 | AA13: 1.7971601 | AB13: 1.7971601 | AC13: 1.7971601 | AD13: 1.7971601 | AE13: 1.7971601 | AG13: egy.mit.atp.res.nga.2 | AH13: 4.9564885 | AI13: 2.7348469 | AJ13: 1.7971601 | AK13: 1.7971601 | AL13: 1.7971601 | AM13: 2.9081833 | AN13: 2.9081833 | AO13: 2.9081833 | AP13: 2.9081833 | AQ13: 2.9081833 | AR13: 2.9081833 | AS13: 2.9081833 | AT13: 2.9081833 | AU13: 2.9081833 | AV13: 2.9081833 | AW13: 2.9081833 | AX13: 2.9081833 | AY13: 2.9081833 | AZ13: 2.9081833 | BA13: 2.9081833
A14: atp | B14: oop | C14: res | D14: 1 | H14: After-tax price | Residential | Other oil products | I14: USD/GJ real | J14: Mitigation section 19a | K14: egy.mit.atp.res.oop.1 | L14: 4.8634416 | M14: 4.3984443 | N14: 4.185618 | O14: 4.185618 | P14: 4.185618 | Q14: 4.185618 | R14: 4.185618 | S14: 4.185618 | T14: 4.185618 | U14: 4.185618 | V14: 4.185618 | W14: 4.185618 | X14: 4.185618 | Y14: 4.185618 | Z14: 4.185618 | AA14: 4.185618 | AB14: 4.185618 | AC14: 4.185618 | AD14: 4.185618 | AE14: 4.185618 | AG14: egy.mit.atp.res.oop.2 | AH14: 4.8634416 | AI14: 4.3984443 | AJ14: 4.185618 | AK14: 4.185618 | AL14: 4.185618 | AM14: 5.7127771 | AN14: 5.7127771 | AO14: 5.7127771 | AP14: 5.7127771 | AQ14: 5.7127771 | AR14: 5.7127771 | AS14: 5.7127771 | AT14: 5.7127771 | AU14: 5.7127771 | AV14: 5.7127771 | AW14: 5.7127771 | AX14: 5.7127771 | AY14: 5.7127771 | AZ14: 5.7127771 | BA14: 5.7127771
A15: atp | B15: gso | C15: res | D15: 1 | H15: After-tax price | Residential | Gasoline | I15: USD/GJ real | J15: Mitigation section 19a | K15: egy.mit.atp.res.gso.1 | L15: 18.107131 | M15: 11.328675 | N15: 9.1450408 | O15: 9.1450408 | P15: 9.1450408 | Q15: 9.1450408 | R15: 9.1450408 | S15: 9.1450408 | T15: 9.1450408 | U15: 9.1450408 | V15: 9.1450408 | W15: 9.1450408 | X15: 9.1450408 | Y15: 9.1450408 | Z15: 9.1450408 | AA15: 9.1450408 | AB15: 9.1450408 | AC15: 9.1450408 | AD15: 9.1450408 | AE15: 9.1450408 | AG15: egy.mit.atp.res.gso.2 | AH15: 18.107131 | AI15: 11.328675 | AJ15: 9.1450408 | AK15: 9.1450408 | AL15: 9.1450408 | AM15: 10.510026 | AN15: 10.510026 | AO15: 10.510026 | AP15: 10.510026 | AQ15: 10.510026 | AR15: 10.510026 | AS15: 10.510026 | AT15: 10.510026 | AU15: 10.510026 | AV15: 10.510026 | AW15: 10.510026 | AX15: 10.510026 | AY15: 10.510026 | AZ15: 10.510026 | BA15: 10.510026
A16: atp | B16: die | C16: res | D16: 1 | H16: After-tax price | Residential | Diesel | I16: USD/GJ real | J16: Mitigation section 19a | K16: egy.mit.atp.res.die.1 | L16: 11.228295 | M16: 7.7491704 | N16: 6.8266892 | O16: 6.8266892 | P16: 6.8266892 | Q16: 6.8266892 | R16: 6.8266892 | S16: 6.8266892 | T16: 6.8266892 | U16: 6.8266892 | V16: 6.8266892 | W16: 6.8266892 | X16: 6.8266892 | Y16: 6.8266892 | Z16: 6.8266892 | AA16: 6.8266892 | AB16: 6.8266892 | AC16: 6.8266892 | AD16: 6.8266892 | AE16: 6.8266892 | AG16: egy.mit.atp.res.die.2 | AH16: 11.228295 | AI16: 7.7491704 | AJ16: 6.8266892 | AK16: 6.8266892 | AL16: 6.8266892 | AM16: 8.2881426 | AN16: 8.2881426 | AO16: 8.2881426 | AP16: 8.2881426 | AQ16: 8.2881426 | AR16: 8.2881426 | AS16: 8.2881426 | AT16: 8.2881426 | AU16: 8.2881426 | AV16: 8.2881426 | AW16: 8.2881426 | AX16: 8.2881426 | AY16: 8.2881426 | AZ16: 8.2881426 | BA16: 8.2881426
A17: atp | B17: ker | C17: res | D17: 1 | H17: After-tax price | Residential | Kerosene | I17: USD/GJ real | J17: Mitigation section 19a | K17: egy.mit.atp.res.ker.1 | L17: 10.553589 | M17: 6.8465155 | N17: 7.0761974 | O17: 7.0761974 | P17: 7.0761974 | Q17: 7.0761974 | R17: 7.0761974 | S17: 7.0761974 | T17: 7.0761974 | U17: 7.0761974 | V17: 7.0761974 | W17: 7.0761974 | X17: 7.0761974 | Y17: 7.0761974 | Z17: 7.0761974 | AA17: 7.0761974 | AB17: 7.0761974 | AC17: 7.0761974 | AD17: 7.0761974 | AE17: 7.0761974 | AG17: egy.mit.atp.res.ker.2 | AH17: 10.553589 | AI17: 6.8465155 | AJ17: 7.0761974 | AK17: 7.0761974 | AL17: 7.0761974 | AM17: 8.4411829 | AN17: 8.4411829 | AO17: 8.4411829 | AP17: 8.4411829 | AQ17: 8.4411829 | AR17: 8.4411829 | AS17: 8.4411829 | AT17: 8.4411829 | AU17: 8.4411829 | AV17: 8.4411829 | AW17: 8.4411829 | AX17: 8.4411829 | AY17: 8.4411829 | AZ17: 8.4411829 | BA17: 8.4411829
A18: atp | B18: lpg | C18: res | D18: 1 | H18: After-tax price | Residential | LPG | I18: USD/GJ real | J18: Mitigation section 19a | K18: egy.mit.atp.res.lpg.1 | L18: 5.9267651 | M18: 3.4733342 | N18: 4.0682684 | O18: 4.0682684 | P18: 4.0682684 | Q18: 4.0682684 | R18: 4.0682684 | S18: 4.0682684 | T18: 4.0682684 | U18: 4.0682684 | V18: 4.0682684 | W18: 4.0682684 | X18: 4.0682684 | Y18: 4.0682684 | Z18: 4.0682684 | AA18: 4.0682684 | AB18: 4.0682684 | AC18: 4.0682684 | AD18: 4.0682684 | AE18: 4.0682684 | AG18: egy.mit.atp.res.lpg.2 | AH18: 5.9267651 | AI18: 3.4733342 | AJ18: 4.0682684 | AK18: 4.0682684 | AL18: 4.0682684 | AM18: 5.4341499 | AN18: 5.4341499 | AO18: 5.4341499 | AP18: 5.4341499 | AQ18: 5.4341499 | AR18: 5.4341499 | AS18: 5.4341499 | AT18: 5.4341499 | AU18: 5.4341499 | AV18: 5.4341499 | AW18: 5.4341499 | AX18: 5.4341499 | AY18: 5.4341499 | AZ18: 5.4341499 | BA18: 5.4341499
A19: rp | B19: ecy | C19: res | D19: 1 | H19: End-user electricity price | Residential | Electricity | I19: USD/kWh real | J19: Mitigation section 19a | K19: egy.mit.rp.res.ecy.1 | L19: 0.061135555 | M19: 0.053218541 | N19: 0.045128065 | O19: 0.043973478 | P19: 0.043981 | Q19: 0.044425438 | R19: 0.04456749 | S19: 0.045253725 | T19: 0.045925822 | U19: 0.046681109 | V19: 0.045438885 | W19: 0.044415971 | X19: 0.043400832 | Y19: 0.042454429 | Z19: 0.041569389 | AA19: 0.040741982 | AB19: 0.039966149 | AC19: 0.039233924 | AD19: 0.038540291 | AE19: 0.037879595 | AG19: egy.mit.rp.res.ecy.2 | AH19: 0.061135555 | AI19: 0.053218541 | AJ19: 0.045128065 | AK19: 0.043974813 | AL19: 0.043984458 | AM19: 0.05363388 | AN19: 0.053578425 | AO19: 0.055133487 | AP19: 0.054395535 | AQ19: 0.054794228 | AR19: 0.053041335 | AS19: 0.051740034 | AT19: 0.050368468 | AU19: 0.049104981 | AV19: 0.047944449 | AW19: 0.046866885 | AX19: 0.045860166 | AY19: 0.044917232 | AZ19: 0.044028885 | BA19: 0.043189636
A20: rpn | B20: coa | C20: ind | D20: 1 | H20: Retail price incl. new taxes and subsidies (fuel-use weighted average of the after-tax prices atp of the subsectors priced by the block; rpb where they use none) | Industry | Coal | I20: USD/GJ real | J20: Mitigation section 19a | K20: egy.mit.rpn.ind.coa.1 | L20: 11.251347 | M20: 8.7773563 | N20: 7.5715284 | O20: 6.8162015 | P20: 7.2323827 | Q20: 7.3262627 | R20: 7.2817484 | S20: 7.234012 | T20: 7.1829218 | U20: 7.1336176 | V20: 7.1336176 | W20: 7.1336176 | X20: 7.1336176 | Y20: 7.1336176 | Z20: 7.1336176 | AA20: 7.1336176 | AB20: 7.1336176 | AC20: 7.1336176 | AD20: 7.1336176 | AE20: 7.1336176 | AG20: egy.mit.rpn.ind.coa.2 | AH20: 11.251347 | AI20: 8.7773563 | AJ20: 7.5715284 | AK20: 6.8162015 | AL20: 7.2323827 | AM20: 9.3173436 | AN20: 9.2728292 | AO20: 9.2250929 | AP20: 9.1740026 | AQ20: 9.1246984 | AR20: 9.1246984 | AS20: 9.1246984 | AT20: 9.1246984 | AU20: 9.1246984 | AV20: 9.1246984 | AW20: 9.1246984 | AX20: 9.1246984 | AY20: 9.1246984 | AZ20: 9.1246984 | BA20: 9.1246984
A21: rpn | B21: nga | C21: ind | D21: 1 | H21: Retail price incl. new taxes and subsidies (fuel-use weighted average of the after-tax prices atp of the subsectors priced by the block; rpb where they use none) | Industry | Natural gas | I21: USD/GJ real | J21: Mitigation section 19a | K21: egy.mit.rpn.ind.nga.1 | L21: 4.899795 | M21: 5.1184551 | N21: 4.8850072 | O21: 4.8850072 | P21: 4.8850072 | Q21: 4.8850072 | R21: 4.8850072 | S21: 4.8850072 | T21: 4.8850072 | U21: 4.8850072 | V21: 4.8850072 | W21: 4.8850072 | X21: 4.8850072 | Y21: 4.8850072 | Z21: 4.8850072 | AA21: 4.8850072 | AB21: 4.8850072 | AC21: 4.8850072 | AD21: 4.8850072 | AE21: 4.8850072 | AG21: egy.mit.rpn.ind.nga.2 | AH21: 4.899795 | AI21: 5.1184551 | AJ21: 4.8850072 | AK21: 4.8850072 | AL21: 4.8850072 | AM21: 5.9960304 | AN21: 5.9960304 | AO21: 5.9960304 | AP21: 5.9960304 | AQ21: 5.9960304 | AR21: 5.9960304 | AS21: 5.9960304 | AT21: 5.9960304 | AU21: 5.9960304 | AV21: 5.9960304 | AW21: 5.9960304 | AX21: 5.9960304 | AY21: 5.9960304 | AZ21: 5.9960304 | BA21: 5.9960304
A22: rpn | B22: oop | C22: all | D22: 1 | H22: Retail price incl. new taxes and subsidies (fuel-use weighted average of the after-tax prices atp of the subsectors priced by the block; rpb where they use none) | All sectors | Other oil products | I22: USD/GJ real | J22: Mitigation section 19a | K22: egy.mit.rpn.all.oop.1 | L22: 4.8634416 | M22: 4.3984443 | N22: 4.185618 | O22: 4.185618 | P22: 4.185618 | Q22: 4.185618 | R22: 4.185618 | S22: 4.185618 | T22: 4.185618 | U22: 4.185618 | V22: 4.185618 | W22: 4.185618 | X22: 4.185618 | Y22: 4.185618 | Z22: 4.185618 | AA22: 4.185618 | AB22: 4.185618 | AC22: 4.185618 | AD22: 4.185618 | AE22: 4.185618 | AG22: egy.mit.rpn.all.oop.2 | AH22: 4.8634416 | AI22: 4.3984443 | AJ22: 4.185618 | AK22: 4.185618 | AL22: 4.185618 | AM22: 5.6416126 | AN22: 5.641629 | AO22: 5.6416454 | AP22: 5.6416617 | AQ22: 5.641678 | AR22: 5.6416942 | AS22: 5.6417104 | AT22: 5.6417265 | AU22: 5.6417425 | AV22: 5.6417585 | AW22: 5.6417745 | AX22: 5.6417903 | AY22: 5.6418062 | AZ22: 5.641822 | BA22: 5.6418377
A23: rpn | B23: gso | C23: all | D23: 1 | H23: Retail price incl. new taxes and subsidies (fuel-use weighted average of the after-tax prices atp of the subsectors priced by the block; rpb where they use none) | All sectors | Gasoline | I23: USD/GJ real | J23: Mitigation section 19a | K23: egy.mit.rpn.all.gso.1 | L23: 18.107131 | M23: 11.328675 | N23: 9.1450408 | O23: 9.1450408 | P23: 9.1450408 | Q23: 9.1450408 | R23: 9.1450408 | S23: 9.1450408 | T23: 9.1450408 | U23: 9.1450408 | V23: 9.1450408 | W23: 9.1450408 | X23: 9.1450408 | Y23: 9.1450408 | Z23: 9.1450408 | AA23: 9.1450408 | AB23: 9.1450408 | AC23: 9.1450408 | AD23: 9.1450408 | AE23: 9.1450408 | AG23: egy.mit.rpn.all.gso.2 | AH23: 18.107131 | AI23: 11.328675 | AJ23: 9.1450408 | AK23: 9.1450408 | AL23: 9.1450408 | AM23: 10.462698 | AN23: 10.462698 | AO23: 10.462698 | AP23: 10.462698 | AQ23: 10.462698 | AR23: 10.462698 | AS23: 10.462698 | AT23: 10.462698 | AU23: 10.462698 | AV23: 10.462698 | AW23: 10.462698 | AX23: 10.462698 | AY23: 10.462698 | AZ23: 10.462698 | BA23: 10.462698
... A35: pav.sp | B35: ecy | C35: all | D35: 1 | H35: Spending on the fuel at after-tax prices (sum over subsectors of atp x fuel use; electricity: rp x consumption, USD m; all energy: USD m) | All sectors | Electricity | I35: USD/GJ x ktoe | J35: Mitigation section 19a | K35: egy.mit.pav.sp.all.ecy.1 | L35: 10352.346 | M35: 9688.0843 | N35: 9207.6753 | O35: 10169.533 | P35: 10668.489 | Q35: 11204.691 | R35: 11691.537 | S35: 12352.557 | T35: 12899.921 | U35: 13495.427 | V35: 13558.86 | W35: 13925.299 | X35: 14265.044 | Y35: 14631.423 | Z35: 15007.038 | AA35: 15392.654 | AB35: 15787.422 | AC35: 16189.964 | AD35: 16600.333 | AE35: 17017.566 | AG35: egy.mit.pav.sp.all.ecy.2 | AH35: 10352.346 | AI35: 9688.0843 | AJ35: 9207.6753 | AK35: 10169.859 | AL35: 10669.173 | AM35: 13304.559 | AN35: 12657.872 | AO35: 13570.577 | AP35: 13707.44 | AQ35: 14416.214 | AR35: 14449.952 | AS35: 14854.099 | AT35: 15199.545 | AU35: 15579.015 | AV35: 15976.923 | AW35: 16392.108 | AX35: 16809.821 | AY35: 17233.534 | AZ35: 17656.294 | BA35: 18084.759

Sheet Distribution
A1: Variable | B1: Item | C1: Sample | D1: Param 1 | E1: Param 2 | H1: Description | I1: Unit | J1: Source | K1: Scenario: output code | L1: 0 | M1: 1 | N1: 2 | O1: 3 | P1: 4 | Q1: 5 | R1: 6 | S1: 7 | T1: 8 | U1: 9 | V1: 10 | X1: Scenario: output code | Y1: 0 | Z1: 1 | AA1: 2 | AB1: 3 | AC1: 4 | AD1: 5 | AE1: 6 | AF1: 7 | AG1: 8 | AH1: 9 | AI1: 10
A2: Distribution - household incidence of the scenario in the analysis year (deciles across)
A3: 0 | B3: Scenario and analysis year
H4: Scenario name (from MTInputs) | L4: =INDEX(ScenarioDefinition!$J$6:$AZ$6,MATCH(L$5,ScenarioDefinition!$J$5:$AZ$5,0)) -> Baseline (no carbon price) | W4: =IF(X$5=K$5,MAX(MAX(W$16:W$969),-MIN(W$16:W$969)),"") | Y4: =INDEX(ScenarioDefinition!$J$6:$AZ$6,MATCH(Y$5,ScenarioDefinition!$J$5:$AZ$5,0)) -> Carbon price $20/tCO2 from 2027
H5: Scenario number (MTInputs column) | K5: =COUNTIF($K$1:K$1,"Scenario*") -> 1 | L5: =K5 -> 1 | M5: =L5 -> 1 | N5: =M5 -> 1 | O5: =N5 -> 1 | P5: =O5 -> 1 | Q5: =P5 -> 1 | R5: =Q5 -> 1 | S5: =R5 -> 1 | ... V5: =U5 -> 1 | X5: =COUNTIF($K$1:X$1,"Scenario*") -> 2 | Y5: =X5 -> 2 | Z5: =Y5 -> 2 | AA5: =Z5 -> 2 | AB5: =AA5 -> 2 | AC5: =AB5 -> 2 | AD5: =AC5 -> 2 | AE5: =AD5 -> 2 | AF5: =AE5 -> 2 | ... AI5: =AH5 -> 2
H6: Position of the column group (LAMBDA test group included) | L6: =COUNTIF($K$1:K$1,"*output code") -> 1 | M6: =L6 -> 1 | N6: =M6 -> 1 | O6: =N6 -> 1 | P6: =O6 -> 1 | Q6: =P6 -> 1 | R6: =Q6 -> 1 | S6: =R6 -> 1 | T6: =S6 -> 1 | ... V6: =U6 -> 1 | Y6: =COUNTIF($K$1:X$1,"*output code") -> 2 | Z6: =Y6 -> 2 | AA6: =Z6 -> 2 | AB6: =AA6 -> 2 | AC6: =AB6 -> 2 | AD6: =AC6 -> 2 | AE6: =AD6 -> 2 | AF6: =AE6 -> 2 | AG6: =AF6 -> 2 | ... AI6: =AH6 -> 2
H7: Mitigation column of the analysis year, scenario 1 (group 1) | L7: =MATCH(L$12,FromMitigation!$K$1:$AF$1,0) -> 10 | M7: =L7 -> 10 | N7: =M7 -> 10 | O7: =N7 -> 10 | P7: =O7 -> 10 | Q7: =P7 -> 10 | R7: =Q7 -> 10 | S7: =R7 -> 10 | T7: =S7 -> 10 | ... V7: =U7 -> 10 | Y7: =MATCH(Y$12,FromMitigation!$K$1:$AF$1,0) -> 10 | Z7: =Y7 -> 10 | AA7: =Z7 -> 10 | AB7: =AA7 -> 10 | AC7: =AB7 -> 10 | AD7: =AC7 -> 10 | AE7: =AD7 -> 10 | AF7: =AE7 -> 10 | AG7: =AF7 -> 10 | ... AI7: =AH7 -> 10
H8: Mitigation column of the analysis year, this scenario group | L8: =L$7+(L$6-1)*MitGW -> 10 | M8: =L8 -> 10 | N8: =M8 -> 10 | O8: =N8 -> 10 | P8: =O8 -> 10 | Q8: =P8 -> 10 | R8: =Q8 -> 10 | S8: =R8 -> 10 | T8: =S8 -> 10 | ... V8: =U8 -> 10 | Y8: =Y$7+(Y$6-1)*MitGW -> 32 | Z8: =Y8 -> 32 | AA8: =Z8 -> 32 | AB8: =AA8 -> 32 | AC8: =AB8 -> 32 | AD8: =AC8 -> 32 | AE8: =AD8 -> 32 | AF8: =AE8 -> 32 | AG8: =AF8 -> 32 | ... AI8: =AH8 -> 32
H9: Statistic of the household survey (MTInputs QuantilesStatistic) | L9: =L$17 -> mean | M9: =L9 -> mean | N9: =M9 -> mean | O9: =N9 -> mean | P9: =O9 -> mean | Q9: =P9 -> mean | R9: =Q9 -> mean | S9: =R9 -> mean | T9: =S9 -> mean | ... V9: =U9 -> mean | Y9: =Y$17 -> mean | Z9: =Y9 -> mean | AA9: =Z9 -> mean | AB9: =AA9 -> mean | AC9: =AB9 -> mean | AD9: =AC9 -> mean | AE9: =AD9 -> mean | AF9: =AE9 -> mean | AG9: =AF9 -> mean | ... AI9: =AH9 -> mean
H10: Survey code: basket or decile (legacy HHSurvey code part) | L10: =IF(L$1=0,"bkt.","dec.") -> bkt. | M10: =IF(M$1=0,"bkt.","dec.") -> dec. | N10: =IF(N$1=0,"bkt.","dec.") -> dec. | O10: =IF(O$1=0,"bkt.","dec.") -> dec. | P10: =IF(P$1=0,"bkt.","dec.") -> dec. | Q10: =IF(Q$1=0,"bkt.","dec.") -> dec. | R10: =IF(R$1=0,"bkt.","dec.") -> dec. | S10: =IF(S$1=0,"bkt.","dec.") -> dec. | ... V10: =IF(V$1=0,"bkt.","dec.") -> dec. | Y10: =IF(Y$1=0,"bkt.","dec.") -> bkt. | Z10: =IF(Z$1=0,"bkt.","dec.") -> dec. | AA10: =IF(AA$1=0,"bkt.","dec.") -> dec. | AB10: =IF(AB$1=0,"bkt.","dec.") -> dec. | AC10: =IF(AC$1=0,"bkt.","dec.") -> dec. | AD10: =IF(AD$1=0,"bkt.","dec.") -> dec. | AE10: =IF(AE$1=0,"bkt.","dec.") -> dec. | AF10: =IF(AF$1=0,"bkt.","dec.") -> dec. | ... AI10: =IF(AI$1=0,"bkt.","dec.") -> dec.
H11: Survey code: quantile (9999 = basket) | L11: ="."&IF(L$1=0,BasketQ,L$1) -> .9999 | M11: ="."&IF(M$1=0,BasketQ,M$1) -> .1 | N11: ="."&IF(N$1=0,BasketQ,N$1) -> .2 | O11: ="."&IF(O$1=0,BasketQ,O$1) -> .3 | P11: ="."&IF(P$1=0,BasketQ,P$1) -> .4 | Q11: ="."&IF(Q$1=0,BasketQ,Q$1) -> .5 | R11: ="."&IF(R$1=0,BasketQ,R$1) -> .6 | S11: ="."&IF(S$1=0,BasketQ,S$1) -> .7 | ... V11: ="."&IF(V$1=0,BasketQ,V$1) -> .10 | Y11: ="."&IF(Y$1=0,BasketQ,Y$1) -> .9999 | Z11: ="."&IF(Z$1=0,BasketQ,Z$1) -> .1 | AA11: ="."&IF(AA$1=0,BasketQ,AA$1) -> .2 | AB11: ="."&IF(AB$1=0,BasketQ,AB$1) -> .3 | AC11: ="."&IF(AC$1=0,BasketQ,AC$1) -> .4 | AD11: ="."&IF(AD$1=0,BasketQ,AD$1) -> .5 | AE11: ="."&IF(AE$1=0,BasketQ,AE$1) -> .6 | AF11: ="."&IF(AF$1=0,BasketQ,AF$1) -> .7 | ... AI11: ="."&IF(AI$1=0,BasketQ,AI$1) -> .10
H12: Analysis year (MTInputs YearDistn) | L12: =L$16 -> 2030 | M12: =L12 -> 2030 | N12: =M12 -> 2030 | O12: =N12 -> 2030 | P12: =O12 -> 2030 | Q12: =P12 -> 2030 | R12: =Q12 -> 2030 | S12: =R12 -> 2030 | T12: =S12 -> 2030 | ... V12: =U12 -> 2030 | Y12: =Y$16 -> 2030 | Z12: =Y12 -> 2030 | AA12: =Z12 -> 2030 | AB12: =AA12 -> 2030 | AC12: =AB12 -> 2030 | AD12: =AC12 -> 2030 | AE12: =AD12 -> 2030 | AF12: =AE12 -> 2030 | AG12: =AF12 -> 2030 | ... AI12: =AH12 -> 2030
A14: 1 | B14: Settings (MTInputs, distributional module assumptions)
A16: YearDistn | D16: =INDEX(MTRowNum,MATCH($A16&"||",MTRowKey,0)) -> 304 | H16: MTInputs: YearDistn | J16: ScenarioDefinition | K16: =LOWER(CtryCode)&".distn."&$A16&IF($B16="","","."&$B16)&IF($C16="","",".dec."&$C16)&"."&K$5 -> egy.distn.YearDistn.1 | L16: =INDEX(ScenarioDefinition!$J$1:$AZ$526,$D16,MATCH(L$5,ScenarioDefinition!$J$5:$AZ$5,0)) -> 2030 | M16: =L16 -> 2030 | N16: =M16 -> 2030 | O16: =N16 -> 2030 | P16: =O16 -> 2030 | Q16: =P16 -> 2030 | R16: =Q16 -> 2030 | S16: =R16 -> 2030 | T16: =S16 -> 2030 | ... V16: =U16 -> 2030 | W16: =IF(X$5=K$5,SUM(Y16:AI16)-SUM(L16:V16),"") | X16: =LOWER(CtryCode)&".distn."&$A16&IF($B16="","","."&$B16)&IF($C16="","",".dec."&$C16)&"."&X$5 -> egy.distn.YearDistn.2 | Y16: =INDEX(ScenarioDefinition!$J$1:$AZ$526,$D16,MATCH(Y$5,ScenarioDefinition!$J$5:$AZ$5,0)) -> 2030 | Z16: =Y16 -> 2030 | AA16: =Z16 -> 2030 | AB16: =AA16 -> 2030 | AC16: =AB16 -> 2030 | AD16: =AC16 -> 2030 | AE16: =AD16 -> 2030 | AF16: =AE16 -> 2030 | AG16: =AF16 -> 2030 | ... AI16: =AH16 -> 2030
A17: QuantilesStatistic | D17: =INDEX(MTRowNum,MATCH($A17&"||",MTRowKey,0)) -> 319 | H17: MTInputs: QuantilesStatistic | J17: ScenarioDefinition | K17: =LOWER(CtryCode)&".distn."&$A17&IF($B17="","","."&$B17)&IF($C17="","",".dec."&$C17)&"."&K$5 -> egy.distn.QuantilesStatistic.1 | L17: =INDEX(ScenarioDefinition!$J$1:$AZ$526,$D17,MATCH(L$5,ScenarioDefinition!$J$5:$AZ$5,0)) -> mean | M17: =L17 -> mean | N17: =M17 -> mean | O17: =N17 -> mean | P17: =O17 -> mean | Q17: =P17 -> mean | R17: =Q17 -> mean | S17: =R17 -> mean | T17: =S17 -> mean | ... V17: =U17 -> mean | W17: =IF(X$5=K$5,SUM(Y17:AI17)-SUM(L17:V17),"") | X17: =LOWER(CtryCode)&".distn."&$A17&IF($B17="","","."&$B17)&IF($C17="","",".dec."&$C17)&"."&X$5 -> egy.distn.QuantilesStatistic.2 | Y17: =INDEX(ScenarioDefinition!$J$1:$AZ$526,$D17,MATCH(Y$5,ScenarioDefinition!$J$5:$AZ$5,0)) -> mean | Z17: =Y17 -> mean | AA17: =Z17 -> mean | AB17: =AA17 -> mean | AC17: =AB17 -> mean | AD17: =AC17 -> mean | AE17: =AD17 -> mean | AF17: =AE17 -> mean | AG17: =AF17 -> mean | ... AI17: =AH17 -> mean
A18: PEDs | D18: =INDEX(MTRowNum,MATCH($A18&"||",MTRowKey,0)) -> 315 | H18: MTInputs: PEDs | J18: ScenarioDefinition | K18: =LOWER(CtryCode)&".distn."&$A18&IF($B18="","","."&$B18)&IF($C18="","",".dec."&$C18)&"."&K$5 -> egy.distn.PEDs.1 | L18: =INDEX(ScenarioDefinition!$J$1:$AZ$526,$D18,MATCH(L$5,ScenarioDefinition!$J$5:$AZ$5,0)) -> Yes | M18: =L18 -> Yes | N18: =M18 -> Yes | O18: =N18 -> Yes | P18: =O18 -> Yes | Q18: =P18 -> Yes | R18: =Q18 -> Yes | S18: =R18 -> Yes | T18: =S18 -> Yes | ... V18: =U18 -> Yes | W18: =IF(X$5=K$5,SUM(Y18:AI18)-SUM(L18:V18),"") | X18: =LOWER(CtryCode)&".distn."&$A18&IF($B18="","","."&$B18)&IF($C18="","",".dec."&$C18)&"."&X$5 -> egy.distn.PEDs.2 | Y18: =INDEX(ScenarioDefinition!$J$1:$AZ$526,$D18,MATCH(Y$5,ScenarioDefinition!$J$5:$AZ$5,0)) -> Yes | Z18: =Y18 -> Yes | AA18: =Z18 -> Yes | AB18: =AA18 -> Yes | AC18: =AB18 -> Yes | AD18: =AC18 -> Yes | AE18: =AD18 -> Yes | AF18: =AE18 -> Yes | AG18: =AF18 -> Yes | ... AI18: =AH18 -> Yes
A19: ScaleGTAP | D19: =INDEX(MTRowNum,MATCH($A19&"||",MTRowKey,0)) -> 316 | H19: MTInputs: ScaleGTAP | J19: ScenarioDefinition | K19: =LOWER(CtryCode)&".distn."&$A19&IF($B19="","","."&$B19)&IF($C19="","",".dec."&$C19)&"."&K$5 -> egy.distn.ScaleGTAP.1 | L19: =INDEX(ScenarioDefinition!$J$1:$AZ$526,$D19,MATCH(L$5,ScenarioDefinition!$J$5:$AZ$5,0)) -> Yes | M19: =L19 -> Yes | N19: =M19 -> Yes | O19: =N19 -> Yes | P19: =O19 -> Yes | Q19: =P19 -> Yes | R19: =Q19 -> Yes | S19: =R19 -> Yes | T19: =S19 -> Yes | ... V19: =U19 -> Yes | W19: =IF(X$5=K$5,SUM(Y19:AI19)-SUM(L19:V19),"") | X19: =LOWER(CtryCode)&".distn."&$A19&IF($B19="","","."&$B19)&IF($C19="","",".dec."&$C19)&"."&X$5 -> egy.distn.ScaleGTAP.2 | Y19: =INDEX(ScenarioDefinition!$J$1:$AZ$526,$D19,MATCH(Y$5,ScenarioDefinition!$J$5:$AZ$5,0)) -> Yes | Z19: =Y19 -> Yes | AA19: =Z19 -> Yes | AB19: =AA19 -> Yes | AC19: =AB19 -> Yes | AD19: =AC19 -> Yes | AE19: =AD19 -> Yes | AF19: =AE19 -> Yes | AG19: =AF19 -> Yes | ... AI19: =AH19 -> Yes
A20: InferredDist | D20: =INDEX(MTRowNum,MATCH($A20&"||",MTRowKey,0)) -> 314 | H20: MTInputs: InferredDist | J20: ScenarioDefinition | K20: =LOWER(CtryCode)&".distn."&$A20&IF($B20="","","."&$B20)&IF($C20="","",".dec."&$C20)&"."&K$5 -> egy.distn.InferredDist.1 | L20: =INDEX(ScenarioDefinition!$J$1:$AZ$526,$D20,MATCH(L$5,ScenarioDefinition!$J$5:$AZ$5,0)) -> No | M20: =L20 -> No | N20: =M20 -> No | O20: =N20 -> No | P20: =O20 -> No | Q20: =P20 -> No | R20: =Q20 -> No | S20: =R20 -> No | T20: =S20 -> No | ... V20: =U20 -> No | W20: =IF(X$5=K$5,SUM(Y20:AI20)-SUM(L20:V20),"") | X20: =LOWER(CtryCode)&".distn."&$A20&IF($B20="","","."&$B20)&IF($C20="","",".dec."&$C20)&"."&X$5 -> egy.distn.InferredDist.2 | Y20: =INDEX(ScenarioDefinition!$J$1:$AZ$526,$D20,MATCH(Y$5,ScenarioDefinition!$J$5:$AZ$5,0)) -> No | Z20: =Y20 -> No | AA20: =Z20 -> No | AB20: =AA20 -> No | AC20: =AB20 -> No | AD20: =AC20 -> No | AE20: =AD20 -> No | AF20: =AE20 -> No | AG20: =AF20 -> No | ... AI20: =AH20 -> No
A21: DWLs | D21: =INDEX(MTRowNum,MATCH($A21&"||",MTRowKey,0)) -> 317 | H21: MTInputs: DWLs | J21: ScenarioDefinition | K21: =LOWER(CtryCode)&".distn."&$A21&IF($B21="","","."&$B21)&IF($C21="","",".dec."&$C21)&"."&K$5 -> egy.distn.DWLs.1 | L21: =INDEX(ScenarioDefinition!$J$1:$AZ$526,$D21,MATCH(L$5,ScenarioDefinition!$J$5:$AZ$5,0)) -> No | M21: =L21 -> No | N21: =M21 -> No | O21: =N21 -> No | P21: =O21 -> No | Q21: =P21 -> No | R21: =Q21 -> No | S21: =R21 -> No | T21: =S21 -> No | ... V21: =U21 -> No | W21: =IF(X$5=K$5,SUM(Y21:AI21)-SUM(L21:V21),"") | X21: =LOWER(CtryCode)&".distn."&$A21&IF($B21="","","."&$B21)&IF($C21="","",".dec."&$C21)&"."&X$5 -> egy.distn.DWLs.2 | Y21: =INDEX(ScenarioDefinition!$J$1:$AZ$526,$D21,MATCH(Y$5,ScenarioDefinition!$J$5:$AZ$5,0)) -> No | Z21: =Y21 -> No | AA21: =Z21 -> No | AB21: =AA21 -> No | AC21: =AB21 -> No | AD21: =AC21 -> No | AE21: =AD21 -> No | AF21: =AE21 -> No | AG21: =AF21 -> No | ... AI21: =AH21 -> No
A22: ExemptMostCook | D22: =INDEX(MTRowNum,MATCH($A22&"||",MTRowKey,0)) -> 312 | H22: MTInputs: ExemptMostCook | J22: ScenarioDefinition | K22: =LOWER(CtryCode)&".distn."&$A22&IF($B22="","","."&$B22)&IF($C22="","",".dec."&$C22)&"."&K$5 -> egy.distn.ExemptMostCook.1 | L22: =INDEX(ScenarioDefinition!$J$1:$AZ$526,$D22,MATCH(L$5,ScenarioDefinition!$J$5:$AZ$5,0)) -> No | M22: =L22 -> No | N22: =M22 -> No | O22: =N22 -> No | P22: =O22 -> No | Q22: =P22 -> No | R22: =Q22 -> No | S22: =R22 -> No | T22: =S22 -> No | ... V22: =U22 -> No | W22: =IF(X$5=K$5,SUM(Y22:AI22)-SUM(L22:V22),"") | X22: =LOWER(CtryCode)&".distn."&$A22&IF($B22="","","."&$B22)&IF($C22="","",".dec."&$C22)&"."&X$5 -> egy.distn.ExemptMostCook.2 | Y22: =INDEX(ScenarioDefinition!$J$1:$AZ$526,$D22,MATCH(Y$5,ScenarioDefinition!$J$5:$AZ$5,0)) -> No | Z22: =Y22 -> No | AA22: =Z22 -> No | AB22: =AA22 -> No | AC22: =AB22 -> No | AD22: =AC22 -> No | AE22: =AD22 -> No | AF22: =AE22 -> No | AG22: =AF22 -> No | ... AI22: =AH22 -> No
A23: ExemptCookDeciles | D23: =INDEX(MTRowNum,MATCH($A23&"||",MTRowKey,0)) -> 313 | H23: MTInputs: ExemptCookDeciles | J23: ScenarioDefinition | K23: =LOWER(CtryCode)&".distn."&$A23&IF($B23="","","."&$B23)&IF($C23="","",".dec."&$C23)&"."&K$5 -> egy.distn.ExemptCookDeciles.1 | L23: =INDEX(ScenarioDefinition!$J$1:$AZ$526,$D23,MATCH(L$5,ScenarioDefinition!$J$5:$AZ$5,0)) -> 4 | M23: =L23 -> 4 | N23: =M23 -> 4 | O23: =N23 -> 4 | P23: =O23 -> 4 | Q23: =P23 -> 4 | R23: =Q23 -> 4 | S23: =R23 -> 4 | T23: =S23 -> 4 | ... V23: =U23 -> 4 | W23: =IF(X$5=K$5,SUM(Y23:AI23)-SUM(L23:V23),"") | X23: =LOWER(CtryCode)&".distn."&$A23&IF($B23="","","."&$B23)&IF($C23="","",".dec."&$C23)&"."&X$5 -> egy.distn.ExemptCookDeciles.2 | Y23: =INDEX(ScenarioDefinition!$J$1:$AZ$526,$D23,MATCH(Y$5,ScenarioDefinition!$J$5:$AZ$5,0)) -> 4 | Z23: =Y23 -> 4 | AA23: =Z23 -> 4 | AB23: =AA23 -> 4 | AC23: =AB23 -> 4 | AD23: =AC23 -> 4 | AE23: =AD23 -> 4 | AF23: =AE23 -> 4 | AG23: =AF23 -> 4 | ... AI23: =AH23 -> 4
A24: EXPLabortax | D24: =INDEX(MTRowNum,MATCH($A24&"||",MTRowKey,0)) -> 197 | H24: MTInputs: EXPLabortax | J24: ScenarioDefinition | K24: =LOWER(CtryCode)&".distn."&$A24&IF($B24="","","."&$B24)&IF($C24="","",".dec."&$C24)&"."&K$5 -> egy.distn.EXPLabortax.1 | L24: =INDEX(ScenarioDefinition!$J$1:$AZ$526,$D24,MATCH(L$5,ScenarioDefinition!$J$5:$AZ$5,0)) -> 30 | M24: =L24 -> 30 | N24: =M24 -> 30 | O24: =N24 -> 30 | P24: =O24 -> 30 | Q24: =P24 -> 30 | R24: =Q24 -> 30 | S24: =R24 -> 30 | T24: =S24 -> 30 | ... V24: =U24 -> 30 | W24: =IF(X$5=K$5,SUM(Y24:AI24)-SUM(L24:V24),"") | X24: =LOWER(CtryCode)&".distn."&$A24&IF($B24="","","."&$B24)&IF($C24="","",".dec."&$C24)&"."&X$5 -> egy.distn.EXPLabortax.2 | Y24: =INDEX(ScenarioDefinition!$J$1:$AZ$526,$D24,MATCH(Y$5,ScenarioDefinition!$J$5:$AZ$5,0)) -> 30 | Z24: =Y24 -> 30 | AA24: =Z24 -> 30 | AB24: =AA24 -> 30 | AC24: =AB24 -> 30 | AD24: =AC24 -> 30 | AE24: =AD24 -> 30 | AF24: =AE24 -> 30 | AG24: =AF24 -> 30 | ... AI24: =AH24 -> 30
A25: EXPCapex | D25: =INDEX(MTRowNum,MATCH($A25&"||",MTRowKey,0)) -> 199 | H25: MTInputs: EXPCapex | J25: ScenarioDefinition | K25: =LOWER(CtryCode)&".distn."&$A25&IF($B25="","","."&$B25)&IF($C25="","",".dec."&$C25)&"."&K$5 -> egy.distn.EXPCapex.1 | L25: =INDEX(ScenarioDefinition!$J$1:$AZ$526,$D25,MATCH(L$5,ScenarioDefinition!$J$5:$AZ$5,0)) -> 50 | M25: =L25 -> 50 | N25: =M25 -> 50 | O25: =N25 -> 50 | P25: =O25 -> 50 | Q25: =P25 -> 50 | R25: =Q25 -> 50 | S25: =R25 -> 50 | T25: =S25 -> 50 | ... V25: =U25 -> 50 | W25: =IF(X$5=K$5,SUM(Y25:AI25)-SUM(L25:V25),"") | X25: =LOWER(CtryCode)&".distn."&$A25&IF($B25="","","."&$B25)&IF($C25="","",".dec."&$C25)&"."&X$5 -> egy.distn.EXPCapex.2 | Y25: =INDEX(ScenarioDefinition!$J$1:$AZ$526,$D25,MATCH(Y$5,ScenarioDefinition!$J$5:$AZ$5,0)) -> 50 | Z25: =Y25 -> 50 | AA25: =Z25 -> 50 | AB25: =AA25 -> 50 | AC25: =AB25 -> 50 | AD25: =AC25 -> 50 | AE25: =AD25 -> 50 | AF25: =AE25 -> 50 | AG25: =AF25 -> 50 | ... AI25: =AH25 -> 50
A26: EXPGoodsandserv | D26: =INDEX(MTRowNum,MATCH($A26&"||",MTRowKey,0)) -> 200 | H26: MTInputs: EXPGoodsandserv | J26: ScenarioDefinition | K26: =LOWER(CtryCode)&".distn."&$A26&IF($B26="","","."&$B26)&IF($C26="","",".dec."&$C26)&"."&K$5 -> egy.distn.EXPGoodsandserv.1 | L26: =INDEX(ScenarioDefinition!$J$1:$AZ$526,$D26,MATCH(L$5,ScenarioDefinition!$J$5:$AZ$5,0)) -> 0 | M26: =L26 -> 0 | N26: =M26 -> 0 | O26: =N26 -> 0 | P26: =O26 -> 0 | Q26: =P26 -> 0 | R26: =Q26 -> 0 | S26: =R26 -> 0 | T26: =S26 -> 0 | ... V26: =U26 -> 0 | W26: =IF(X$5=K$5,SUM(Y26:AI26)-SUM(L26:V26),"") | X26: =LOWER(CtryCode)&".distn."&$A26&IF($B26="","","."&$B26)&IF($C26="","",".dec."&$C26)&"."&X$5 -> egy.distn.EXPGoodsandserv.2 | Y26: =INDEX(ScenarioDefinition!$J$1:$AZ$526,$D26,MATCH(Y$5,ScenarioDefinition!$J$5:$AZ$5,0)) -> 0 | Z26: =Y26 -> 0 | AA26: =Z26 -> 0 | AB26: =AA26 -> 0 | AC26: =AB26 -> 0 | AD26: =AC26 -> 0 | AE26: =AD26 -> 0 | AF26: =AE26 -> 0 | AG26: =AF26 -> 0 | ... AI26: =AH26 -> 0
A27: EXPTransfers | D27: =INDEX(MTRowNum,MATCH($A27&"||",MTRowKey,0)) -> 201 | H27: MTInputs: EXPTransfers | J27: ScenarioDefinition | K27: =LOWER(CtryCode)&".distn."&$A27&IF($B27="","","."&$B27)&IF($C27="","",".dec."&$C27)&"."&K$5 -> egy.distn.EXPTransfers.1 | L27: =INDEX(ScenarioDefinition!$J$1:$AZ$526,$D27,MATCH(L$5,ScenarioDefinition!$J$5:$AZ$5,0)) -> 20 | M27: =L27 -> 20 | N27: =M27 -> 20 | O27: =N27 -> 20 | P27: =O27 -> 20 | Q27: =P27 -> 20 | R27: =Q27 -> 20 | S27: =R27 -> 20 | T27: =S27 -> 20 | ... V27: =U27 -> 20 | W27: =IF(X$5=K$5,SUM(Y27:AI27)-SUM(L27:V27),"") | X27: =LOWER(CtryCode)&".distn."&$A27&IF($B27="","","."&$B27)&IF($C27="","",".dec."&$C27)&"."&X$5 -> egy.distn.EXPTransfers.2 | Y27: =INDEX(ScenarioDefinition!$J$1:$AZ$526,$D27,MATCH(Y$5,ScenarioDefinition!$J$5:$AZ$5,0)) -> 20 | Z27: =Y27 -> 20 | AA27: =Z27 -> 20 | AB27: =AA27 -> 20 | AC27: =AB27 -> 20 | AD27: =AC27 -> 20 | AE27: =AD27 -> 20 | AF27: =AE27 -> 20 | AG27: =AF27 -> 20 | ... AI27: =AH27 -> 20
... A39: QuantilesLCU | D39: =INDEX(MTRowNum,MATCH($A39&"||",MTRowKey,0)) -> 320 | H39: MTInputs: QuantilesLCU | J39: ScenarioDefinition | K39: =LOWER(CtryCode)&".distn."&$A39&IF($B39="","","."&$B39)&IF($C39="","",".dec."&$C39)&"."&K$5 -> egy.distn.QuantilesLCU.1 | L39: =INDEX(ScenarioDefinition!$J$1:$AZ$526,$D39,MATCH(L$5,ScenarioDefinition!$J$5:$AZ$5,0)) -> No | M39: =L39 -> No | N39: =M39 -> No | O39: =N39 -> No | P39: =O39 -> No | Q39: =P39 -> No | R39: =Q39 -> No | S39: =R39 -> No | T39: =S39 -> No | ... V39: =U39 -> No | W39: =IF(X$5=K$5,SUM(Y39:AI39)-SUM(L39:V39),"") | X39: =LOWER(CtryCode)&".distn."&$A39&IF($B39="","","."&$B39)&IF($C39="","",".dec."&$C39)&"."&X$5 -> egy.distn.QuantilesLCU.2 | Y39: =INDEX(ScenarioDefinition!$J$1:$AZ$526,$D39,MATCH(Y$5,ScenarioDefinition!$J$5:$AZ$5,0)) -> No | Z39: =Y39 -> No | AA39: =Z39 -> No | AB39: =AA39 -> No | AC39: =AB39 -> No | AD39: =AC39 -> No | AE39: =AD39 -> No | AF39: =AE39 -> No | AG39: =AF39 -> No | ... AI39: =AH39 -> No
A41: acsvar | H41: Infrastructure access variable of the public investment type | I41: variable | J41: DistMapping (legacy rows 184-189) | K41: =LOWER(CtryCode)&".distn."&$A41&IF($B41="","","."&$B41)&IF($C41="","",".dec."&$C41)&"."&K$5 -> egy.distn.acsvar.1 | L41: =INDEX(DProgCode,MATCH("infra|"&L$36,DProgKey,0)) -> all_acs_share | M41: =L41 -> all_acs_share | N41: =M41 -> all_acs_share | O41: =N41 -> all_acs_share | P41: =O41 -> all_acs_share | Q41: =P41 -> all_acs_share | R41: =Q41 -> all_acs_share | S41: =R41 -> all_acs_share | T41: =S41 -> all_acs_share | ... V41: =U41 -> all_acs_share | W41: =IF(X$5=K$5,SUM(Y41:AI41)-SUM(L41:V41),"") | X41: =LOWER(CtryCode)&".distn."&$A41&IF($B41="","","."&$B41)&IF($C41="","",".dec."&$C41)&"."&X$5 -> egy.distn.acsvar.2 | Y41: =INDEX(DProgCode,MATCH("infra|"&Y$36,DProgKey,0)) -> all_acs_share | Z41: =Y41 -> all_acs_share | AA41: =Z41 -> all_acs_share | AB41: =AA41 -> all_acs_share | AC41: =AB41 -> all_acs_share | AD41: =AC41 -> all_acs_share | AE41: =AD41 -> all_acs_share | AF41: =AE41 -> all_acs_share | AG41: =AF41 -> all_acs_share | ... AI41: =AH41 -> all_acs_share
A42: aspcode | H42: ASPIRE program of the current spending type | I42: program | J42: DistMapping (legacy rows 195-210) | K42: =LOWER(CtryCode)&".distn."&$A42&IF($B42="","","."&$B42)&IF($C42="","",".dec."&$C42)&"."&K$5 -> egy.distn.aspcode.1 | L42: =INDEX(DProgCode,MATCH("aspire|"&L$37,DProgKey,0)) -> per_allsp.avt_q | M42: =L42 -> per_allsp.avt_q | N42: =M42 -> per_allsp.avt_q | O42: =N42 -> per_allsp.avt_q | P42: =O42 -> per_allsp.avt_q | Q42: =P42 -> per_allsp.avt_q | R42: =Q42 -> per_allsp.avt_q | S42: =R42 -> per_allsp.avt_q | T42: =S42 -> per_allsp.avt_q | ... V42: =U42 -> per_allsp.avt_q | W42: =IF(X$5=K$5,SUM(Y42:AI42)-SUM(L42:V42),"") | X42: =LOWER(CtryCode)&".distn."&$A42&IF($B42="","","."&$B42)&IF($C42="","",".dec."&$C42)&"."&X$5 -> egy.distn.aspcode.2 | Y42: =INDEX(DProgCode,MATCH("aspire|"&Y$37,DProgKey,0)) -> per_allsp.avt_q | Z42: =Y42 -> per_allsp.avt_q | AA42: =Z42 -> per_allsp.avt_q | AB42: =AA42 -> per_allsp.avt_q | AC42: =AB42 -> per_allsp.avt_q | AD42: =AC42 -> per_allsp.avt_q | AE42: =AD42 -> per_allsp.avt_q | AF42: =AE42 -> per_allsp.avt_q | AG42: =AF42 -> per_allsp.avt_q | ... AI42: =AH42 -> per_allsp.avt_q
A43: exfuel | H43: Most-used cooking fuel (WHOCooking, overall) | I43: item | J43: WHOCooking (legacy row 226) | K43: =LOWER(CtryCode)&".distn."&$A43&IF($B43="","","."&$B43)&IF($C43="","",".dec."&$C43)&"."&K$5 -> egy.distn.exfuel.1 | L43: =INDEX(DCookFuel,MATCH(CtryCode&".distn.pcoff.ove",DCookKey,0)) -> lpg | M43: =L43 -> lpg | N43: =M43 -> lpg | O43: =N43 -> lpg | P43: =O43 -> lpg | Q43: =P43 -> lpg | R43: =Q43 -> lpg | S43: =R43 -> lpg | T43: =S43 -> lpg | ... V43: =U43 -> lpg | W43: =IF(X$5=K$5,SUM(Y43:AI43)-SUM(L43:V43),"") | X43: =LOWER(CtryCode)&".distn."&$A43&IF($B43="","","."&$B43)&IF($C43="","",".dec."&$C43)&"."&X$5 -> egy.distn.exfuel.2 | Y43: =INDEX(DCookFuel,MATCH(CtryCode&".distn.pcoff.ove",DCookKey,0)) -> lpg | Z43: =Y43 -> lpg | AA43: =Z43 -> lpg | AB43: =AA43 -> lpg | AC43: =AB43 -> lpg | AD43: =AC43 -> lpg | AE43: =AD43 -> lpg | AF43: =AE43 -> lpg | AG43: =AF43 -> lpg | ... AI43: =AH43 -> lpg
A44: exdec | H44: Exempt decile of the most-used cooking fuel (1 = exempt) | I44: flag | J44: MTInputs ExemptMostCook, ExemptCookDeciles (legacy row 1579) | K44: =LOWER(CtryCode)&".distn."&$A44&IF($B44="","","."&$B44)&IF($C44="","",".dec."&$C44)&"."&K$5 -> egy.distn.exdec.1 | L44: =IF(AND(LEFT(L$22,3)="Yes",L$1>0,L$1<=L$23),1,0) -> 0 | M44: =IF(AND(LEFT(M$22,3)="Yes",M$1>0,M$1<=M$23),1,0) -> 0 | N44: =IF(AND(LEFT(N$22,3)="Yes",N$1>0,N$1<=N$23),1,0) -> 0 | O44: =IF(AND(LEFT(O$22,3)="Yes",O$1>0,O$1<=O$23),1,0) -> 0 | P44: =IF(AND(LEFT(P$22,3)="Yes",P$1>0,P$1<=P$23),1,0) -> 0 | Q44: =IF(AND(LEFT(Q$22,3)="Yes",Q$1>0,Q$1<=Q$23),1,0) -> 0 | R44: =IF(AND(LEFT(R$22,3)="Yes",R$1>0,R$1<=R$23),1,0) -> 0 | S44: =IF(AND(LEFT(S$22,3)="Yes",S$1>0,S$1<=S$23),1,0) -> 0 | ... V44: =IF(AND(LEFT(V$22,3)="Yes",V$1>0,V$1<=V$23),1,0) -> 0 | W44: =IF(X$5=K$5,SUM(Y44:AI44)-SUM(L44:V44),"") | X44: =LOWER(CtryCode)&".distn."&$A44&IF($B44="","","."&$B44)&IF($C44="","",".dec."&$C44)&"."&X$5 -> egy.distn.exdec.2 | Y44: =IF(AND(LEFT(Y$22,3)="Yes",Y$1>0,Y$1<=Y$23),1,0) -> 0 | Z44: =IF(AND(LEFT(Z$22,3)="Yes",Z$1>0,Z$1<=Z$23),1,0) -> 0 | AA44: =IF(AND(LEFT(AA$22,3)="Yes",AA$1>0,AA$1<=AA$23),1,0) -> 0 | AB44: =IF(AND(LEFT(AB$22,3)="Yes",AB$1>0,AB$1<=AB$23),1,0) -> 0 | AC44: =IF(AND(LEFT(AC$22,3)="Yes",AC$1>0,AC$1<=AC$23),1,0) -> 0 | AD44: =IF(AND(LEFT(AD$22,3)="Yes",AD$1>0,AD$1<=AD$23),1,0) -> 0 | AE44: =IF(AND(LEFT(AE$22,3)="Yes",AE$1>0,AE$1<=AE$23),1,0) -> 0 | AF44: =IF(AND(LEFT(AF$22,3)="Yes",AF$1>0,AF$1<=AF$23),1,0) -> 0 | ... AI44: =IF(AND(LEFT(AI$22,3)="Yes",AI$1>0,AI$1<=AI$23),1,0) -> 0
A45: tgtcode | H45: ASPIRE program of the transfer type (Cash: cash transfer) | I45: program | J45: DistMapping (legacy I216; v0.6.0) | K45: =LOWER(CtryCode)&".distn."&$A45&IF($B45="","","."&$B45)&IF($C45="","",".dec."&$C45)&"."&K$5 -> egy.distn.tgtcode.1 | L45: =IFERROR(INDEX(DProgCode,MATCH("aspire|"&L$31,DProgKey,0)),"Cash") -> Cash | M45: =L45 -> Cash | N45: =M45 -> Cash | O45: =N45 -> Cash | P45: =O45 -> Cash | Q45: =P45 -> Cash | R45: =Q45 -> Cash | S45: =R45 -> Cash | T45: =S45 -> Cash | ... V45: =U45 -> Cash | W45: =IF(X$5=K$5,SUM(Y45:AI45)-SUM(L45:V45),"") | X45: =LOWER(CtryCode)&".distn."&$A45&IF($B45="","","."&$B45)&IF($C45="","",".dec."&$C45)&"."&X$5 -> egy.distn.tgtcode.2 | Y45: =IFERROR(INDEX(DProgCode,MATCH("aspire|"&Y$31,DProgKey,0)),"Cash") -> Cash | Z45: =Y45 -> Cash | AA45: =Z45 -> Cash | AB45: =AA45 -> Cash | AC45: =AB45 -> Cash | AD45: =AC45 -> Cash | AE45: =AD45 -> Cash | AF45: =AE45 -> Cash | AG45: =AF45 -> Cash | ... AI45: =AH45 -> Cash
A46: tgtdata | H46: ASPIRE data for the transfer program and the country (1 = yes) | I46: flag | J46: ASPIRE (legacy I213; v0.6.0) | K46: =LOWER(CtryCode)&".distn."&$A46&IF($B46="","","."&$B46)&IF($C46="","",".dec."&$C46)&"."&K$5 -> egy.distn.tgtdata.1 | L46: =IF(ISNUMBER(MATCH(CtryCode&"."&L$45&"1_preT_tot",DAspKey,0)),1,0) -> 0 | M46: =L46 -> 0 | N46: =M46 -> 0 | O46: =N46 -> 0 | P46: =O46 -> 0 | Q46: =P46 -> 0 | R46: =Q46 -> 0 | S46: =R46 -> 0 | T46: =S46 -> 0 | ... V46: =U46 -> 0 | W46: =IF(X$5=K$5,SUM(Y46:AI46)-SUM(L46:V46),"") | X46: =LOWER(CtryCode)&".distn."&$A46&IF($B46="","","."&$B46)&IF($C46="","",".dec."&$C46)&"."&X$5 -> egy.distn.tgtdata.2 | Y46: =IF(ISNUMBER(MATCH(CtryCode&"."&Y$45&"1_preT_tot",DAspKey,0)),1,0) -> 0 | Z46: =Y46 -> 0 | AA46: =Z46 -> 0 | AB46: =AA46 -> 0 | AC46: =AB46 -> 0 | AD46: =AC46 -> 0 | AE46: =AD46 -> 0 | AF46: =AE46 -> 0 | AG46: =AF46 -> 0 | ... AI46: =AH46 -> 0
A47: plvar | H47: Survey variable of the poverty line (TargetBelow; popw if none) | I47: variable | J47: HHSurvey pct_belowpl_* (legacy Q2551; v0.6.0) | K47: =LOWER(CtryCode)&".distn."&$A47&IF($B47="","","."&$B47)&IF($C47="","",".dec."&$C47)&"."&K$5 -> egy.distn.plvar.1 | L47: =IF(LEFT(L$32&"",2)="No","popw","pct_belowpl_"&SUBSTITUTE(L$32&"",".","")) -> popw | M47: =L47 -> popw | N47: =M47 -> popw | O47: =N47 -> popw | P47: =O47 -> popw | Q47: =P47 -> popw | R47: =Q47 -> popw | S47: =R47 -> popw | T47: =S47 -> popw | ... V47: =U47 -> popw | W47: =IF(X$5=K$5,SUM(Y47:AI47)-SUM(L47:V47),"") | X47: =LOWER(CtryCode)&".distn."&$A47&IF($B47="","","."&$B47)&IF($C47="","",".dec."&$C47)&"."&X$5 -> egy.distn.plvar.2 | Y47: =IF(LEFT(Y$32&"",2)="No","popw","pct_belowpl_"&SUBSTITUTE(Y$32&"",".","")) -> popw | Z47: =Y47 -> popw | AA47: =Z47 -> popw | AB47: =AA47 -> popw | AC47: =AB47 -> popw | AD47: =AC47 -> popw | AE47: =AD47 -> popw | AF47: =AE47 -> popw | AG47: =AF47 -> popw | ... AI47: =AH47 -> popw
A48: tgtmode | H48: Targeting of the transfer: Cash, ASPIRE (program incidence) or PL (poverty line, with Cash only) | I48: mode | J48: legacy Q2545, Q2550 (v0.6.0; no ASPIRE data: Cash, fix D11) | K48: =LOWER(CtryCode)&".distn."&$A48&IF($B48="","","."&$B48)&IF($C48="","",".dec."&$C48)&"."&K$5 -> egy.distn.tgtmode.1 | L48: =IF(L$45<>"Cash",IF(L$46=1,"ASPIRE","Cash"),IF(L$47="popw","Cash","PL")) -> Cash | M48: =L48 -> Cash | N48: =M48 -> Cash | O48: =N48 -> Cash | P48: =O48 -> Cash | Q48: =P48 -> Cash | R48: =Q48 -> Cash | S48: =R48 -> Cash | T48: =S48 -> Cash | ... V48: =U48 -> Cash | W48: =IF(X$5=K$5,SUM(Y48:AI48)-SUM(L48:V48),"") | X48: =LOWER(CtryCode)&".distn."&$A48&IF($B48="","","."&$B48)&IF($C48="","",".dec."&$C48)&"."&X$5 -> egy.distn.tgtmode.2 | Y48: =IF(Y$45<>"Cash",IF(Y$46=1,"ASPIRE","Cash"),IF(Y$47="popw","Cash","PL")) -> Cash | Z48: =Y48 -> Cash | AA48: =Z48 -> Cash | AB48: =AA48 -> Cash | AC48: =AB48 -> Cash | AD48: =AC48 -> Cash | AE48: =AD48 -> Cash | AF48: =AE48 -> Cash | AG48: =AF48 -> Cash | ... AI48: =AH48 -> Cash
A50: support | H50: Options check: OK, or the reason an option is not applied | I50: check | J50: Methods, chapter Distribution (v0.6.0: every legacy option modelled) | K50: =LOWER(CtryCode)&".distn."&$A50&IF($B50="","","."&$B50)&IF($C50="","",".dec."&$C50)&"."&K$5 -> egy.distn.support.1 | L50: =IF(AND(L$45<>"Cash",L$46=0),"TransferType: no ASPIRE data, cash used","OK") -> OK | M50: =L50 -> OK | N50: =M50 -> OK | O50: =N50 -> OK | P50: =O50 -> OK | Q50: =P50 -> OK | R50: =Q50 -> OK | S50: =R50 -> OK | T50: =S50 -> OK | ... V50: =U50 -> OK | W50: =IF(X$5=K$5,SUM(Y50:AI50)-SUM(L50:V50),"") | X50: =LOWER(CtryCode)&".distn."&$A50&IF($B50="","","."&$B50)&IF($C50="","",".dec."&$C50)&"."&X$5 -> egy.distn.support.2 | Y50: =IF(AND(Y$45<>"Cash",Y$46=0),"TransferType: no ASPIRE data, cash used","OK") -> OK | Z50: =Y50 -> OK | AA50: =Z50 -> OK | AB50: =AA50 -> OK | AC50: =AB50 -> OK | AD50: =AC50 -> OK | AE50: =AD50 -> OK | AF50: =AE50 -> OK | AG50: =AF50 -> OK | ... AI50: =AH50 -> OK
A52: 2 | B52: Inputs from Mitigation (analysis year, same scenario group; legacy B.II-B.III)
B54: Household fuel prices: change against scenario 1 (residential after-tax price; electricity: retail price)
A55: dpr | B55: coa.res | H55: Coal: household price change | I55: fraction | J55: Mitigation atp.res.coa | K55: =LOWER(CtryCode)&".distn."&$A55&IF($B55="","","."&$B55)&IF($C55="","",".dec."&$C55)&"."&K$5 -> egy.distn.dpr.coa.res.1 | L55: =INDEX(FromMitigation!$K$12:$IZ$12,L$8)/INDEX(FromMitigation!$K$12:$IZ$12,L$7)-1 -> 0 | M55: =L55 -> 0 | N55: =M55 -> 0 | O55: =N55 -> 0 | P55: =O55 -> 0 | Q55: =P55 -> 0 | R55: =Q55 -> 0 | S55: =R55 -> 0 | T55: =S55 -> 0 | ... V55: =U55 -> 0 | W55: =IF(X$5=K$5,SUM(Y55:AI55)-SUM(L55:V55),"") | X55: =LOWER(CtryCode)&".distn."&$A55&IF($B55="","","."&$B55)&IF($C55="","",".dec."&$C55)&"."&X$5 -> egy.distn.dpr.coa.res.2 | Y55: =DPCHG(INDEX(FromMitigation!$K$12:$IZ$12,Y$8),INDEX(FromMitigation!$K$12:$IZ$12,Y$7)) -> 0.15431137 | Z55: =Y55 -> 0.15431137 | AA55: =Z55 -> 0.15431137 | AB55: =AA55 -> 0.15431137 | AC55: =AB55 -> 0.15431137 | AD55: =AC55 -> 0.15431137 | AE55: =AD55 -> 0.15431137 | AF55: =AE55 -> 0.15431137 | AG55: =AF55 -> 0.15431137 | ... AI55: =AH55 -> 0.15431137
A56: dpr | B56: ely.res | H56: Electricity: household price change | I56: fraction | J56: Mitigation rp.res.ecy | K56: =LOWER(CtryCode)&".distn."&$A56&IF($B56="","","."&$B56)&IF($C56="","",".dec."&$C56)&"."&K$5 -> egy.distn.dpr.ely.res.1 | L56: =INDEX(FromMitigation!$K$19:$IZ$19,L$8)/INDEX(FromMitigation!$K$19:$IZ$19,L$7)-1 -> 0 | M56: =L56 -> 0 | N56: =M56 -> 0 | O56: =N56 -> 0 | P56: =O56 -> 0 | Q56: =P56 -> 0 | R56: =Q56 -> 0 | S56: =R56 -> 0 | T56: =S56 -> 0 | ... V56: =U56 -> 0 | W56: =IF(X$5=K$5,SUM(Y56:AI56)-SUM(L56:V56),"") | X56: =LOWER(CtryCode)&".distn."&$A56&IF($B56="","","."&$B56)&IF($C56="","",".dec."&$C56)&"."&X$5 -> egy.distn.dpr.ely.res.2 | Y56: =DPCHG(INDEX(FromMitigation!$K$19:$IZ$19,Y$8),INDEX(FromMitigation!$K$19:$IZ$19,Y$7)) -> 0.1844216 | Z56: =Y56 -> 0.1844216 | AA56: =Z56 -> 0.1844216 | AB56: =AA56 -> 0.1844216 | AC56: =AB56 -> 0.1844216 | AD56: =AC56 -> 0.1844216 | AE56: =AD56 -> 0.1844216 | AF56: =AE56 -> 0.1844216 | AG56: =AF56 -> 0.1844216 | ... AI56: =AH56 -> 0.1844216
A57: dpr | B57: nga.res | H57: Natural gas: household price change | I57: fraction | J57: Mitigation atp.res.nga | K57: =LOWER(CtryCode)&".distn."&$A57&IF($B57="","","."&$B57)&IF($C57="","",".dec."&$C57)&"."&K$5 -> egy.distn.dpr.nga.res.1 | L57: =INDEX(FromMitigation!$K$13:$IZ$13,L$8)/INDEX(FromMitigation!$K$13:$IZ$13,L$7)-1 -> 0 | M57: =L57 -> 0 | N57: =M57 -> 0 | O57: =N57 -> 0 | P57: =O57 -> 0 | Q57: =P57 -> 0 | R57: =Q57 -> 0 | S57: =R57 -> 0 | T57: =S57 -> 0 | ... V57: =U57 -> 0 | W57: =IF(X$5=K$5,SUM(Y57:AI57)-SUM(L57:V57),"") | X57: =LOWER(CtryCode)&".distn."&$A57&IF($B57="","","."&$B57)&IF($C57="","",".dec."&$C57)&"."&X$5 -> egy.distn.dpr.nga.res.2 | Y57: =DPCHG(INDEX(FromMitigation!$K$13:$IZ$13,Y$8),INDEX(FromMitigation!$K$13:$IZ$13,Y$7)) -> 0.61821042 | Z57: =Y57 -> 0.61821042 | AA57: =Z57 -> 0.61821042 | AB57: =AA57 -> 0.61821042 | AC57: =AB57 -> 0.61821042 | AD57: =AC57 -> 0.61821042 | AE57: =AD57 -> 0.61821042 | AF57: =AE57 -> 0.61821042 | AG57: =AF57 -> 0.61821042 | ... AI57: =AH57 -> 0.61821042
A58: dpr | B58: oop.res | H58: Other oil products: household price change | I58: fraction | J58: Mitigation atp.res.oop | K58: =LOWER(CtryCode)&".distn."&$A58&IF($B58="","","."&$B58)&IF($C58="","",".dec."&$C58)&"."&K$5 -> egy.distn.dpr.oop.res.1 | L58: =INDEX(FromMitigation!$K$14:$IZ$14,L$8)/INDEX(FromMitigation!$K$14:$IZ$14,L$7)-1 -> 0 | M58: =L58 -> 0 | N58: =M58 -> 0 | O58: =N58 -> 0 | P58: =O58 -> 0 | Q58: =P58 -> 0 | R58: =Q58 -> 0 | S58: =R58 -> 0 | T58: =S58 -> 0 | ... V58: =U58 -> 0 | W58: =IF(X$5=K$5,SUM(Y58:AI58)-SUM(L58:V58),"") | X58: =LOWER(CtryCode)&".distn."&$A58&IF($B58="","","."&$B58)&IF($C58="","",".dec."&$C58)&"."&X$5 -> egy.distn.dpr.oop.res.2 | Y58: =DPCHG(INDEX(FromMitigation!$K$14:$IZ$14,Y$8),INDEX(FromMitigation!$K$14:$IZ$14,Y$7)) -> 0.36485867 | Z58: =Y58 -> 0.36485867 | AA58: =Z58 -> 0.36485867 | AB58: =AA58 -> 0.36485867 | AC58: =AB58 -> 0.36485867 | AD58: =AC58 -> 0.36485867 | AE58: =AD58 -> 0.36485867 | AF58: =AE58 -> 0.36485867 | AG58: =AF58 -> 0.36485867 | ... AI58: =AH58 -> 0.36485867
A59: dpr | B59: gso.res | H59: Gasoline: household price change | I59: fraction | J59: Mitigation atp.res.gso | K59: =LOWER(CtryCode)&".distn."&$A59&IF($B59="","","."&$B59)&IF($C59="","",".dec."&$C59)&"."&K$5 -> egy.distn.dpr.gso.res.1 | L59: =INDEX(FromMitigation!$K$15:$IZ$15,L$8)/INDEX(FromMitigation!$K$15:$IZ$15,L$7)-1 -> 0 | M59: =L59 -> 0 | N59: =M59 -> 0 | O59: =N59 -> 0 | P59: =O59 -> 0 | Q59: =P59 -> 0 | R59: =Q59 -> 0 | S59: =R59 -> 0 | T59: =S59 -> 0 | ... V59: =U59 -> 0 | W59: =IF(X$5=K$5,SUM(Y59:AI59)-SUM(L59:V59),"") | X59: =LOWER(CtryCode)&".distn."&$A59&IF($B59="","","."&$B59)&IF($C59="","",".dec."&$C59)&"."&X$5 -> egy.distn.dpr.gso.res.2 | Y59: =DPCHG(INDEX(FromMitigation!$K$15:$IZ$15,Y$8),INDEX(FromMitigation!$K$15:$IZ$15,Y$7)) -> 0.14925964 | Z59: =Y59 -> 0.14925964 | AA59: =Z59 -> 0.14925964 | AB59: =AA59 -> 0.14925964 | AC59: =AB59 -> 0.14925964 | AD59: =AC59 -> 0.14925964 | AE59: =AD59 -> 0.14925964 | AF59: =AE59 -> 0.14925964 | AG59: =AF59 -> 0.14925964 | ... AI59: =AH59 -> 0.14925964
A60: dpr | B60: die.res | H60: Diesel: household price change | I60: fraction | J60: Mitigation atp.res.die | K60: =LOWER(CtryCode)&".distn."&$A60&IF($B60="","","."&$B60)&IF($C60="","",".dec."&$C60)&"."&K$5 -> egy.distn.dpr.die.res.1 | L60: =INDEX(FromMitigation!$K$16:$IZ$16,L$8)/INDEX(FromMitigation!$K$16:$IZ$16,L$7)-1 -> 0 | M60: =L60 -> 0 | N60: =M60 -> 0 | O60: =N60 -> 0 | P60: =O60 -> 0 | Q60: =P60 -> 0 | R60: =Q60 -> 0 | S60: =R60 -> 0 | T60: =S60 -> 0 | ... V60: =U60 -> 0 | W60: =IF(X$5=K$5,SUM(Y60:AI60)-SUM(L60:V60),"") | X60: =LOWER(CtryCode)&".distn."&$A60&IF($B60="","","."&$B60)&IF($C60="","",".dec."&$C60)&"."&X$5 -> egy.distn.dpr.die.res.2 | Y60: =DPCHG(INDEX(FromMitigation!$K$16:$IZ$16,Y$8),INDEX(FromMitigation!$K$16:$IZ$16,Y$7)) -> 0.21407937 | Z60: =Y60 -> 0.21407937 | AA60: =Z60 -> 0.21407937 | AB60: =AA60 -> 0.21407937 | AC60: =AB60 -> 0.21407937 | AD60: =AC60 -> 0.21407937 | AE60: =AD60 -> 0.21407937 | AF60: =AE60 -> 0.21407937 | AG60: =AF60 -> 0.21407937 | ... AI60: =AH60 -> 0.21407937
A61: dpr | B61: ker.res | H61: Kerosene: household price change | I61: fraction | J61: Mitigation atp.res.ker | K61: =LOWER(CtryCode)&".distn."&$A61&IF($B61="","","."&$B61)&IF($C61="","",".dec."&$C61)&"."&K$5 -> egy.distn.dpr.ker.res.1 | L61: =INDEX(FromMitigation!$K$17:$IZ$17,L$8)/INDEX(FromMitigation!$K$17:$IZ$17,L$7)-1 -> 0 | M61: =L61 -> 0 | N61: =M61 -> 0 | O61: =N61 -> 0 | P61: =O61 -> 0 | Q61: =P61 -> 0 | R61: =Q61 -> 0 | S61: =R61 -> 0 | T61: =S61 -> 0 | ... V61: =U61 -> 0 | W61: =IF(X$5=K$5,SUM(Y61:AI61)-SUM(L61:V61),"") | X61: =LOWER(CtryCode)&".distn."&$A61&IF($B61="","","."&$B61)&IF($C61="","",".dec."&$C61)&"."&X$5 -> egy.distn.dpr.ker.res.2 | Y61: =DPCHG(INDEX(FromMitigation!$K$17:$IZ$17,Y$8),INDEX(FromMitigation!$K$17:$IZ$17,Y$7)) -> 0.19289816 | Z61: =Y61 -> 0.19289816 | AA61: =Z61 -> 0.19289816 | AB61: =AA61 -> 0.19289816 | AC61: =AB61 -> 0.19289816 | AD61: =AC61 -> 0.19289816 | AE61: =AD61 -> 0.19289816 | AF61: =AE61 -> 0.19289816 | AG61: =AF61 -> 0.19289816 | ... AI61: =AH61 -> 0.19289816
A62: dpr | B62: lpg.res | H62: LPG: household price change | I62: fraction | J62: Mitigation atp.res.lpg | K62: =LOWER(CtryCode)&".distn."&$A62&IF($B62="","","."&$B62)&IF($C62="","",".dec."&$C62)&"."&K$5 -> egy.distn.dpr.lpg.res.1 | L62: =INDEX(FromMitigation!$K$18:$IZ$18,L$8)/INDEX(FromMitigation!$K$18:$IZ$18,L$7)-1 -> 0 | M62: =L62 -> 0 | N62: =M62 -> 0 | O62: =N62 -> 0 | P62: =O62 -> 0 | Q62: =P62 -> 0 | R62: =Q62 -> 0 | S62: =R62 -> 0 | T62: =S62 -> 0 | ... V62: =U62 -> 0 | W62: =IF(X$5=K$5,SUM(Y62:AI62)-SUM(L62:V62),"") | X62: =LOWER(CtryCode)&".distn."&$A62&IF($B62="","","."&$B62)&IF($C62="","",".dec."&$C62)&"."&X$5 -> egy.distn.dpr.lpg.res.2 | Y62: =DPCHG(INDEX(FromMitigation!$K$18:$IZ$18,Y$8),INDEX(FromMitigation!$K$18:$IZ$18,Y$7)) -> 0.33574025 | Z62: =Y62 -> 0.33574025 | AA62: =Z62 -> 0.33574025 | AB62: =AA62 -> 0.33574025 | AC62: =AB62 -> 0.33574025 | AD62: =AC62 -> 0.33574025 | AE62: =AD62 -> 0.33574025 | AF62: =AE62 -> 0.33574025 | AG62: =AF62 -> 0.33574025 | ... AI62: =AH62 -> 0.33574025
B64: Economy-wide fuel prices (industry or all sectors): change against scenario 1, and baseline spending
A65: dpa | B65: coa | D65: coa | H65: Coal: economy-wide price change | I65: fraction | J65: Mitigation rpn.ind.coa | K65: =LOWER(CtryCode)&".distn."&$A65&IF($B65="","","."&$B65)&IF($C65="","",".dec."&$C65)&"."&K$5 -> egy.distn.dpa.coa.1 | L65: =INDEX(FromMitigation!$K$20:$IZ$20,L$8)/INDEX(FromMitigation!$K$20:$IZ$20,L$7)-1 -> 0 | M65: =L65 -> 0 | N65: =M65 -> 0 | O65: =N65 -> 0 | P65: =O65 -> 0 | Q65: =P65 -> 0 | R65: =Q65 -> 0 | S65: =R65 -> 0 | T65: =S65 -> 0 | ... V65: =U65 -> 0 | W65: =IF(X$5=K$5,SUM(Y65:AI65)-SUM(L65:V65),"") | X65: =LOWER(CtryCode)&".distn."&$A65&IF($B65="","","."&$B65)&IF($C65="","",".dec."&$C65)&"."&X$5 -> egy.distn.dpa.coa.2 | Y65: =DPCHG(INDEX(FromMitigation!$K$20:$IZ$20,Y$8),INDEX(FromMitigation!$K$20:$IZ$20,Y$7)) -> 0.27719651 | Z65: =Y65 -> 0.27719651 | AA65: =Z65 -> 0.27719651 | AB65: =AA65 -> 0.27719651 | AC65: =AB65 -> 0.27719651 | AD65: =AC65 -> 0.27719651 | AE65: =AD65 -> 0.27719651 | AF65: =AE65 -> 0.27719651 | AG65: =AF65 -> 0.27719651 | ... AI65: =AH65 -> 0.27719651
A66: dpa | B66: nga | D66: nga | H66: Natural gas: economy-wide price change | I66: fraction | J66: Mitigation rpn.ind.nga | K66: =LOWER(CtryCode)&".distn."&$A66&IF($B66="","","."&$B66)&IF($C66="","",".dec."&$C66)&"."&K$5 -> egy.distn.dpa.nga.1 | L66: =INDEX(FromMitigation!$K$21:$IZ$21,L$8)/INDEX(FromMitigation!$K$21:$IZ$21,L$7)-1 -> 0 | M66: =L66 -> 0 | N66: =M66 -> 0 | O66: =N66 -> 0 | P66: =O66 -> 0 | Q66: =P66 -> 0 | R66: =Q66 -> 0 | S66: =R66 -> 0 | T66: =S66 -> 0 | ... V66: =U66 -> 0 | W66: =IF(X$5=K$5,SUM(Y66:AI66)-SUM(L66:V66),"") | X66: =LOWER(CtryCode)&".distn."&$A66&IF($B66="","","."&$B66)&IF($C66="","",".dec."&$C66)&"."&X$5 -> egy.distn.dpa.nga.2 | Y66: =DPCHG(INDEX(FromMitigation!$K$21:$IZ$21,Y$8),INDEX(FromMitigation!$K$21:$IZ$21,Y$7)) -> 0.22743531 | Z66: =Y66 -> 0.22743531 | AA66: =Z66 -> 0.22743531 | AB66: =AA66 -> 0.22743531 | AC66: =AB66 -> 0.22743531 | AD66: =AC66 -> 0.22743531 | AE66: =AD66 -> 0.22743531 | AF66: =AE66 -> 0.22743531 | AG66: =AF66 -> 0.22743531 | ... AI66: =AH66 -> 0.22743531
A67: dpa | B67: oop | D67: oil | H67: Other oil products: economy-wide price change | I67: fraction | J67: Mitigation rpn.all.oop | K67: =LOWER(CtryCode)&".distn."&$A67&IF($B67="","","."&$B67)&IF($C67="","",".dec."&$C67)&"."&K$5 -> egy.distn.dpa.oop.1 | L67: =INDEX(FromMitigation!$K$22:$IZ$22,L$8)/INDEX(FromMitigation!$K$22:$IZ$22,L$7)-1 -> 0 | M67: =L67 -> 0 | N67: =M67 -> 0 | O67: =N67 -> 0 | P67: =O67 -> 0 | Q67: =P67 -> 0 | R67: =Q67 -> 0 | S67: =R67 -> 0 | T67: =S67 -> 0 | ... V67: =U67 -> 0 | W67: =IF(X$5=K$5,SUM(Y67:AI67)-SUM(L67:V67),"") | X67: =LOWER(CtryCode)&".distn."&$A67&IF($B67="","","."&$B67)&IF($C67="","",".dec."&$C67)&"."&X$5 -> egy.distn.dpa.oop.2 | Y67: =DPCHG(INDEX(FromMitigation!$K$22:$IZ$22,Y$8),INDEX(FromMitigation!$K$22:$IZ$22,Y$7)) -> 0.34786826 | Z67: =Y67 -> 0.34786826 | AA67: =Z67 -> 0.34786826 | AB67: =AA67 -> 0.34786826 | AC67: =AB67 -> 0.34786826 | AD67: =AC67 -> 0.34786826 | AE67: =AD67 -> 0.34786826 | AF67: =AE67 -> 0.34786826 | AG67: =AF67 -> 0.34786826 | ... AI67: =AH67 -> 0.34786826
A68: dpa | B68: gso | D68: p_c | H68: Gasoline: economy-wide price change | I68: fraction | J68: Mitigation rpn.all.gso | K68: =LOWER(CtryCode)&".distn."&$A68&IF($B68="","","."&$B68)&IF($C68="","",".dec."&$C68)&"."&K$5 -> egy.distn.dpa.gso.1 | L68: =INDEX(FromMitigation!$K$23:$IZ$23,L$8)/INDEX(FromMitigation!$K$23:$IZ$23,L$7)-1 -> 0 | M68: =L68 -> 0 | N68: =M68 -> 0 | O68: =N68 -> 0 | P68: =O68 -> 0 | Q68: =P68 -> 0 | R68: =Q68 -> 0 | S68: =R68 -> 0 | T68: =S68 -> 0 | ... V68: =U68 -> 0 | W68: =IF(X$5=K$5,SUM(Y68:AI68)-SUM(L68:V68),"") | X68: =LOWER(CtryCode)&".distn."&$A68&IF($B68="","","."&$B68)&IF($C68="","",".dec."&$C68)&"."&X$5 -> egy.distn.dpa.gso.2 | Y68: =DPCHG(INDEX(FromMitigation!$K$23:$IZ$23,Y$8),INDEX(FromMitigation!$K$23:$IZ$23,Y$7)) -> 0.14408438 | Z68: =Y68 -> 0.14408438 | AA68: =Z68 -> 0.14408438 | AB68: =AA68 -> 0.14408438 | AC68: =AB68 -> 0.14408438 | AD68: =AC68 -> 0.14408438 | AE68: =AD68 -> 0.14408438 | AF68: =AE68 -> 0.14408438 | AG68: =AF68 -> 0.14408438 | ... AI68: =AH68 -> 0.14408438
A69: dpa | B69: die | D69: p_c | H69: Diesel: economy-wide price change | I69: fraction | J69: Mitigation rpn.all.die | K69: =LOWER(CtryCode)&".distn."&$A69&IF($B69="","","."&$B69)&IF($C69="","",".dec."&$C69)&"."&K$5 -> egy.distn.dpa.die.1 | L69: =INDEX(FromMitigation!$K$24:$IZ$24,L$8)/INDEX(FromMitigation!$K$24:$IZ$24,L$7)-1 -> 0 | M69: =L69 -> 0 | N69: =M69 -> 0 | O69: =N69 -> 0 | P69: =O69 -> 0 | Q69: =P69 -> 0 | R69: =Q69 -> 0 | S69: =R69 -> 0 | T69: =S69 -> 0 | ... V69: =U69 -> 0 | W69: =IF(X$5=K$5,SUM(Y69:AI69)-SUM(L69:V69),"") | X69: =LOWER(CtryCode)&".distn."&$A69&IF($B69="","","."&$B69)&IF($C69="","",".dec."&$C69)&"."&X$5 -> egy.distn.dpa.die.2 | Y69: =DPCHG(INDEX(FromMitigation!$K$24:$IZ$24,Y$8),INDEX(FromMitigation!$K$24:$IZ$24,Y$7)) -> 0.20797133 | Z69: =Y69 -> 0.20797133 | AA69: =Z69 -> 0.20797133 | AB69: =AA69 -> 0.20797133 | AC69: =AB69 -> 0.20797133 | AD69: =AC69 -> 0.20797133 | AE69: =AD69 -> 0.20797133 | AF69: =AE69 -> 0.20797133 | AG69: =AF69 -> 0.20797133 | ... AI69: =AH69 -> 0.20797133
A70: dpa | B70: lpg | D70: p_c | H70: LPG: economy-wide price change | I70: fraction | J70: Mitigation rpn.all.lpg | K70: =LOWER(CtryCode)&".distn."&$A70&IF($B70="","","."&$B70)&IF($C70="","",".dec."&$C70)&"."&K$5 -> egy.distn.dpa.lpg.1 | L70: =INDEX(FromMitigation!$K$25:$IZ$25,L$8)/INDEX(FromMitigation!$K$25:$IZ$25,L$7)-1 -> 0 | M70: =L70 -> 0 | N70: =M70 -> 0 | O70: =N70 -> 0 | P70: =O70 -> 0 | Q70: =P70 -> 0 | R70: =Q70 -> 0 | S70: =R70 -> 0 | T70: =S70 -> 0 | ... V70: =U70 -> 0 | W70: =IF(X$5=K$5,SUM(Y70:AI70)-SUM(L70:V70),"") | X70: =LOWER(CtryCode)&".distn."&$A70&IF($B70="","","."&$B70)&IF($C70="","",".dec."&$C70)&"."&X$5 -> egy.distn.dpa.lpg.2 | Y70: =DPCHG(INDEX(FromMitigation!$K$25:$IZ$25,Y$8),INDEX(FromMitigation!$K$25:$IZ$25,Y$7)) -> 0.33574025 | Z70: =Y70 -> 0.33574025 | AA70: =Z70 -> 0.33574025 | AB70: =AA70 -> 0.33574025 | AC70: =AB70 -> 0.33574025 | AD70: =AC70 -> 0.33574025 | AE70: =AD70 -> 0.33574025 | AF70: =AE70 -> 0.33574025 | AG70: =AF70 -> 0.33574025 | ... AI70: =AH70 -> 0.33574025
A71: dpa | B71: ker | D71: p_c | H71: Kerosene: economy-wide price change | I71: fraction | J71: Mitigation rpn.all.ker | K71: =LOWER(CtryCode)&".distn."&$A71&IF($B71="","","."&$B71)&IF($C71="","",".dec."&$C71)&"."&K$5 -> egy.distn.dpa.ker.1 | L71: =INDEX(FromMitigation!$K$26:$IZ$26,L$8)/INDEX(FromMitigation!$K$26:$IZ$26,L$7)-1 -> 0 | M71: =L71 -> 0 | N71: =M71 -> 0 | O71: =N71 -> 0 | P71: =O71 -> 0 | Q71: =P71 -> 0 | R71: =Q71 -> 0 | S71: =R71 -> 0 | T71: =S71 -> 0 | ... V71: =U71 -> 0 | W71: =IF(X$5=K$5,SUM(Y71:AI71)-SUM(L71:V71),"") | X71: =LOWER(CtryCode)&".distn."&$A71&IF($B71="","","."&$B71)&IF($C71="","",".dec."&$C71)&"."&X$5 -> egy.distn.dpa.ker.2 | Y71: =DPCHG(INDEX(FromMitigation!$K$26:$IZ$26,Y$8),INDEX(FromMitigation!$K$26:$IZ$26,Y$7)) -> 0.20108132 | Z71: =Y71 -> 0.20108132 | AA71: =Z71 -> 0.20108132 | AB71: =AA71 -> 0.20108132 | AC71: =AB71 -> 0.20108132 | AD71: =AC71 -> 0.20108132 | AE71: =AD71 -> 0.20108132 | AF71: =AE71 -> 0.20108132 | AG71: =AF71 -> 0.20108132 | ... AI71: =AH71 -> 0.20108132
A72: dpa | B72: ecy | D72: ely | H72: Electricity: economy-wide price change | I72: fraction | J72: Mitigation rp.ind.ecy | K72: =LOWER(CtryCode)&".distn."&$A72&IF($B72="","","."&$B72)&IF($C72="","",".dec."&$C72)&"."&K$5 -> egy.distn.dpa.ecy.1 | L72: =INDEX(FromMitigation!$K$27:$IZ$27,L$8)/INDEX(FromMitigation!$K$27:$IZ$27,L$7)-1 -> 0 | M72: =L72 -> 0 | N72: =M72 -> 0 | O72: =N72 -> 0 | P72: =O72 -> 0 | Q72: =P72 -> 0 | R72: =Q72 -> 0 | S72: =R72 -> 0 | T72: =S72 -> 0 | ... V72: =U72 -> 0 | W72: =IF(X$5=K$5,SUM(Y72:AI72)-SUM(L72:V72),"") | X72: =LOWER(CtryCode)&".distn."&$A72&IF($B72="","","."&$B72)&IF($C72="","",".dec."&$C72)&"."&X$5 -> egy.distn.dpa.ecy.2 | Y72: =DPCHG(INDEX(FromMitigation!$K$27:$IZ$27,Y$8),INDEX(FromMitigation!$K$27:$IZ$27,Y$7)) -> 0.1570115 | Z72: =Y72 -> 0.1570115 | AA72: =Z72 -> 0.1570115 | AB72: =AA72 -> 0.1570115 | AC72: =AB72 -> 0.1570115 | AD72: =AC72 -> 0.1570115 | AE72: =AD72 -> 0.1570115 | AF72: =AE72 -> 0.1570115 | AG72: =AF72 -> 0.1570115 | ... AI72: =AH72 -> 0.1570115
A73: spend | B73: coa | D73: coa | H73: Coal: spending, scenario 1, base year (legacy exp.usd.1) | I73: USD m | J73: Mitigation pav.sp (fossil: $/GJ x ktoe x PJ/ktoe) | K73: =LOWER(CtryCode)&".distn."&$A73&IF($B73="","","."&$B73)&IF($C73="","",".dec."&$C73)&"."&K$5 -> egy.distn.spend.coa.1 | L73: =INDEX(FromMitigation!$K$28:$IZ$28,MATCH(BaseYr,FromMitigation!$K$1:$AF$1,0))*'Constants and Mappings'!$C$13 -> 778.18562 | M73: =L73 -> 778.18562 | N73: =M73 -> 778.18562 | O73: =N73 -> 778.18562 | P73: =O73 -> 778.18562 | Q73: =P73 -> 778.18562 | R73: =Q73 -> 778.18562 | S73: =R73 -> 778.18562 | T73: =S73 -> 778.18562 | ... V73: =U73 -> 778.18562 | W73: =IF(X$5=K$5,SUM(Y73:AI73)-SUM(L73:V73),"") | X73: =LOWER(CtryCode)&".distn."&$A73&IF($B73="","","."&$B73)&IF($C73="","",".dec."&$C73)&"."&X$5 -> egy.distn.spend.coa.2 | Y73: =INDEX(FromMitigation!$K$28:$IZ$28,MATCH(BaseYr,FromMitigation!$K$1:$AF$1,0))*'Constants and Mappings'!$C$13 -> 778.18562 | Z73: =Y73 -> 778.18562 | AA73: =Z73 -> 778.18562 | AB73: =AA73 -> 778.18562 | AC73: =AB73 -> 778.18562 | AD73: =AC73 -> 778.18562 | AE73: =AD73 -> 778.18562 | AF73: =AE73 -> 778.18562 | AG73: =AF73 -> 778.18562 | ... AI73: =AH73 -> 778.18562
A74: spend | B74: nga | D74: nga | H74: Natural gas: spending, scenario 1, base year (legacy exp.usd.1) | I74: USD m | J74: Mitigation pav.sp (fossil: $/GJ x ktoe x PJ/ktoe) | K74: =LOWER(CtryCode)&".distn."&$A74&IF($B74="","","."&$B74)&IF($C74="","",".dec."&$C74)&"."&K$5 -> egy.distn.spend.nga.1 | L74: =INDEX(FromMitigation!$K$29:$IZ$29,MATCH(BaseYr,FromMitigation!$K$1:$AF$1,0))*'Constants and Mappings'!$C$13 -> 2716.9838 | M74: =L74 -> 2716.9838 | N74: =M74 -> 2716.9838 | O74: =N74 -> 2716.9838 | P74: =O74 -> 2716.9838 | Q74: =P74 -> 2716.9838 | R74: =Q74 -> 2716.9838 | S74: =R74 -> 2716.9838 | T74: =S74 -> 2716.9838 | ... V74: =U74 -> 2716.9838 | W74: =IF(X$5=K$5,SUM(Y74:AI74)-SUM(L74:V74),"") | X74: =LOWER(CtryCode)&".distn."&$A74&IF($B74="","","."&$B74)&IF($C74="","",".dec."&$C74)&"."&X$5 -> egy.distn.spend.nga.2 | Y74: =INDEX(FromMitigation!$K$29:$IZ$29,MATCH(BaseYr,FromMitigation!$K$1:$AF$1,0))*'Constants and Mappings'!$C$13 -> 2716.9838 | Z74: =Y74 -> 2716.9838 | AA74: =Z74 -> 2716.9838 | AB74: =AA74 -> 2716.9838 | AC74: =AB74 -> 2716.9838 | AD74: =AC74 -> 2716.9838 | AE74: =AD74 -> 2716.9838 | AF74: =AE74 -> 2716.9838 | AG74: =AF74 -> 2716.9838 | ... AI74: =AH74 -> 2716.9838
A75: spend | B75: oop | D75: oil | H75: Other oil products: spending, scenario 1, base year (legacy exp.usd.1) | I75: USD m | J75: Mitigation pav.sp (fossil: $/GJ x ktoe x PJ/ktoe) | K75: =LOWER(CtryCode)&".distn."&$A75&IF($B75="","","."&$B75)&IF($C75="","",".dec."&$C75)&"."&K$5 -> egy.distn.spend.oop.1 | L75: =INDEX(FromMitigation!$K$30:$IZ$30,MATCH(BaseYr,FromMitigation!$K$1:$AF$1,0))*'Constants and Mappings'!$C$13 -> 595.23057 | M75: =L75 -> 595.23057 | N75: =M75 -> 595.23057 | O75: =N75 -> 595.23057 | P75: =O75 -> 595.23057 | Q75: =P75 -> 595.23057 | R75: =Q75 -> 595.23057 | S75: =R75 -> 595.23057 | T75: =S75 -> 595.23057 | ... V75: =U75 -> 595.23057 | W75: =IF(X$5=K$5,SUM(Y75:AI75)-SUM(L75:V75),"") | X75: =LOWER(CtryCode)&".distn."&$A75&IF($B75="","","."&$B75)&IF($C75="","",".dec."&$C75)&"."&X$5 -> egy.distn.spend.oop.2 | Y75: =INDEX(FromMitigation!$K$30:$IZ$30,MATCH(BaseYr,FromMitigation!$K$1:$AF$1,0))*'Constants and Mappings'!$C$13 -> 595.23057 | Z75: =Y75 -> 595.23057 | AA75: =Z75 -> 595.23057 | AB75: =AA75 -> 595.23057 | AC75: =AB75 -> 595.23057 | AD75: =AC75 -> 595.23057 | AE75: =AD75 -> 595.23057 | AF75: =AE75 -> 595.23057 | AG75: =AF75 -> 595.23057 | ... AI75: =AH75 -> 595.23057
A76: spend | B76: gso | D76: p_c | H76: Gasoline: spending, scenario 1, base year (legacy exp.usd.1) | I76: USD m | J76: Mitigation pav.sp (fossil: $/GJ x ktoe x PJ/ktoe) | K76: =LOWER(CtryCode)&".distn."&$A76&IF($B76="","","."&$B76)&IF($C76="","",".dec."&$C76)&"."&K$5 -> egy.distn.spend.gso.1 | L76: =INDEX(FromMitigation!$K$31:$IZ$31,MATCH(BaseYr,FromMitigation!$K$1:$AF$1,0))*'Constants and Mappings'!$C$13 -> 5556.1402 | M76: =L76 -> 5556.1402 | N76: =M76 -> 5556.1402 | O76: =N76 -> 5556.1402 | P76: =O76 -> 5556.1402 | Q76: =P76 -> 5556.1402 | R76: =Q76 -> 5556.1402 | S76: =R76 -> 5556.1402 | T76: =S76 -> 5556.1402 | ... V76: =U76 -> 5556.1402 | W76: =IF(X$5=K$5,SUM(Y76:AI76)-SUM(L76:V76),"") | X76: =LOWER(CtryCode)&".distn."&$A76&IF($B76="","","."&$B76)&IF($C76="","",".dec."&$C76)&"."&X$5 -> egy.distn.spend.gso.2 | Y76: =INDEX(FromMitigation!$K$31:$IZ$31,MATCH(BaseYr,FromMitigation!$K$1:$AF$1,0))*'Constants and Mappings'!$C$13 -> 5556.1402 | Z76: =Y76 -> 5556.1402 | AA76: =Z76 -> 5556.1402 | AB76: =AA76 -> 5556.1402 | AC76: =AB76 -> 5556.1402 | AD76: =AC76 -> 5556.1402 | AE76: =AD76 -> 5556.1402 | AF76: =AE76 -> 5556.1402 | AG76: =AF76 -> 5556.1402 | ... AI76: =AH76 -> 5556.1402
A77: spend | B77: die | D77: p_c | H77: Diesel: spending, scenario 1, base year (legacy exp.usd.1) | I77: USD m | J77: Mitigation pav.sp (fossil: $/GJ x ktoe x PJ/ktoe) | K77: =LOWER(CtryCode)&".distn."&$A77&IF($B77="","","."&$B77)&IF($C77="","",".dec."&$C77)&"."&K$5 -> egy.distn.spend.die.1 | L77: =INDEX(FromMitigation!$K$32:$IZ$32,MATCH(BaseYr,FromMitigation!$K$1:$AF$1,0))*'Constants and Mappings'!$C$13 -> 7224.2838 | M77: =L77 -> 7224.2838 | N77: =M77 -> 7224.2838 | O77: =N77 -> 7224.2838 | P77: =O77 -> 7224.2838 | Q77: =P77 -> 7224.2838 | R77: =Q77 -> 7224.2838 | S77: =R77 -> 7224.2838 | T77: =S77 -> 7224.2838 | ... V77: =U77 -> 7224.2838 | W77: =IF(X$5=K$5,SUM(Y77:AI77)-SUM(L77:V77),"") | X77: =LOWER(CtryCode)&".distn."&$A77&IF($B77="","","."&$B77)&IF($C77="","",".dec."&$C77)&"."&X$5 -> egy.distn.spend.die.2 | Y77: =INDEX(FromMitigation!$K$32:$IZ$32,MATCH(BaseYr,FromMitigation!$K$1:$AF$1,0))*'Constants and Mappings'!$C$13 -> 7224.2838 | Z77: =Y77 -> 7224.2838 | AA77: =Z77 -> 7224.2838 | AB77: =AA77 -> 7224.2838 | AC77: =AB77 -> 7224.2838 | AD77: =AC77 -> 7224.2838 | AE77: =AD77 -> 7224.2838 | AF77: =AE77 -> 7224.2838 | AG77: =AF77 -> 7224.2838 | ... AI77: =AH77 -> 7224.2838
A78: spend | B78: lpg | D78: p_c | H78: LPG: spending, scenario 1, base year (legacy exp.usd.1) | I78: USD m | J78: Mitigation pav.sp (fossil: $/GJ x ktoe x PJ/ktoe) | K78: =LOWER(CtryCode)&".distn."&$A78&IF($B78="","","."&$B78)&IF($C78="","",".dec."&$C78)&"."&K$5 -> egy.distn.spend.lpg.1 | L78: =INDEX(FromMitigation!$K$33:$IZ$33,MATCH(BaseYr,FromMitigation!$K$1:$AF$1,0))*'Constants and Mappings'!$C$13 -> 1307.6317 | M78: =L78 -> 1307.6317 | N78: =M78 -> 1307.6317 | O78: =N78 -> 1307.6317 | P78: =O78 -> 1307.6317 | Q78: =P78 -> 1307.6317 | R78: =Q78 -> 1307.6317 | S78: =R78 -> 1307.6317 | T78: =S78 -> 1307.6317 | ... V78: =U78 -> 1307.6317 | W78: =IF(X$5=K$5,SUM(Y78:AI78)-SUM(L78:V78),"") | X78: =LOWER(CtryCode)&".distn."&$A78&IF($B78="","","."&$B78)&IF($C78="","",".dec."&$C78)&"."&X$5 -> egy.distn.spend.lpg.2 | Y78: =INDEX(FromMitigation!$K$33:$IZ$33,MATCH(BaseYr,FromMitigation!$K$1:$AF$1,0))*'Constants and Mappings'!$C$13 -> 1307.6317 | Z78: =Y78 -> 1307.6317 | AA78: =Z78 -> 1307.6317 | AB78: =AA78 -> 1307.6317 | AC78: =AB78 -> 1307.6317 | AD78: =AC78 -> 1307.6317 | AE78: =AD78 -> 1307.6317 | AF78: =AE78 -> 1307.6317 | AG78: =AF78 -> 1307.6317 | ... AI78: =AH78 -> 1307.6317
A79: spend | B79: ker | D79: p_c | H79: Kerosene: spending, scenario 1, base year (legacy exp.usd.1) | I79: USD m | J79: Mitigation pav.sp (fossil: $/GJ x ktoe x PJ/ktoe) | K79: =LOWER(CtryCode)&".distn."&$A79&IF($B79="","","."&$B79)&IF($C79="","",".dec."&$C79)&"."&K$5 -> egy.distn.spend.ker.1 | L79: =INDEX(FromMitigation!$K$34:$IZ$34,MATCH(BaseYr,FromMitigation!$K$1:$AF$1,0))*'Constants and Mappings'!$C$13 -> 3.0489012 | M79: =L79 -> 3.0489012 | N79: =M79 -> 3.0489012 | O79: =N79 -> 3.0489012 | P79: =O79 -> 3.0489012 | Q79: =P79 -> 3.0489012 | R79: =Q79 -> 3.0489012 | S79: =R79 -> 3.0489012 | T79: =S79 -> 3.0489012 | ... V79: =U79 -> 3.0489012 | W79: =IF(X$5=K$5,SUM(Y79:AI79)-SUM(L79:V79),"") | X79: =LOWER(CtryCode)&".distn."&$A79&IF($B79="","","."&$B79)&IF($C79="","",".dec."&$C79)&"."&X$5 -> egy.distn.spend.ker.2 | Y79: =INDEX(FromMitigation!$K$34:$IZ$34,MATCH(BaseYr,FromMitigation!$K$1:$AF$1,0))*'Constants and Mappings'!$C$13 -> 3.0489012 | Z79: =Y79 -> 3.0489012 | AA79: =Z79 -> 3.0489012 | AB79: =AA79 -> 3.0489012 | AC79: =AB79 -> 3.0489012 | AD79: =AC79 -> 3.0489012 | AE79: =AD79 -> 3.0489012 | AF79: =AE79 -> 3.0489012 | AG79: =AF79 -> 3.0489012 | ... AI79: =AH79 -> 3.0489012
A80: spend | B80: ecy | D80: ely | H80: Electricity: spending, scenario 1, base year (legacy exp.usd.1) | I80: USD m | J80: Mitigation pav.sp (fossil: $/GJ x ktoe x PJ/ktoe) | K80: =LOWER(CtryCode)&".distn."&$A80&IF($B80="","","."&$B80)&IF($C80="","",".dec."&$C80)&"."&K$5 -> egy.distn.spend.ecy.1 | L80: =INDEX(FromMitigation!$K$35:$IZ$35,MATCH(BaseYr,FromMitigation!$K$1:$AF$1,0)) -> 10352.346 | M80: =L80 -> 10352.346 | N80: =M80 -> 10352.346 | O80: =N80 -> 10352.346 | P80: =O80 -> 10352.346 | Q80: =P80 -> 10352.346 | R80: =Q80 -> 10352.346 | S80: =R80 -> 10352.346 | T80: =S80 -> 10352.346 | ... V80: =U80 -> 10352.346 | W80: =IF(X$5=K$5,SUM(Y80:AI80)-SUM(L80:V80),"") | X80: =LOWER(CtryCode)&".distn."&$A80&IF($B80="","","."&$B80)&IF($C80="","",".dec."&$C80)&"."&X$5 -> egy.distn.spend.ecy.2 | Y80: =INDEX(FromMitigation!$K$35:$IZ$35,MATCH(BaseYr,FromMitigation!$K$1:$AF$1,0)) -> 10352.346 | Z80: =Y80 -> 10352.346 | AA80: =Z80 -> 10352.346 | AB80: =AA80 -> 10352.346 | AC80: =AB80 -> 10352.346 | AD80: =AC80 -> 10352.346 | AE80: =AD80 -> 10352.346 | AF80: =AE80 -> 10352.346 | AG80: =AF80 -> 10352.346 | ... AI80: =AH80 -> 10352.346
B82: Macro totals (local currency)
A83: gdp | H83: Real GDP, baseline (local currency) | I83: LCU bn | J83: Mitigation gdp.lcu (header row 12) | K83: =LOWER(CtryCode)&".distn."&$A83&IF($B83="","","."&$B83)&IF($C83="","",".dec."&$C83)&"."&K$5 -> egy.distn.gdp.1 | L83: =INDEX(FromMitigation!$K$8:$IZ$8,L$8)*FromMitigation!$D$8 -> 11066825114000 | M83: =L83 -> 11066825114000 | N83: =M83 -> 11066825114000 | O83: =N83 -> 11066825114000 | P83: =O83 -> 11066825114000 | Q83: =P83 -> 11066825114000 | R83: =Q83 -> 11066825114000 | S83: =R83 -> 11066825114000 | T83: =S83 -> 11066825114000 | ... V83: =U83 -> 11066825114000 | W83: =IF(X$5=K$5,SUM(Y83:AI83)-SUM(L83:V83),"") | X83: =LOWER(CtryCode)&".distn."&$A83&IF($B83="","","."&$B83)&IF($C83="","",".dec."&$C83)&"."&X$5 -> egy.distn.gdp.2 | Y83: =INDEX(FromMitigation!$K$8:$IZ$8,Y$8)*FromMitigation!$D$8 -> 11066825114000 | Z83: =Y83 -> 11066825114000 | AA83: =Z83 -> 11066825114000 | AB83: =AA83 -> 11066825114000 | AC83: =AB83 -> 11066825114000 | AD83: =AC83 -> 11066825114000 | AE83: =AD83 -> 11066825114000 | AF83: =AE83 -> 11066825114000 | AG83: =AF83 -> 11066825114000 | ... AI83: =AH83 -> 11066825114000
A84: pop | H84: Population | I84: persons m | J84: Mitigation pop | K84: =LOWER(CtryCode)&".distn."&$A84&IF($B84="","","."&$B84)&IF($C84="","",".dec."&$C84)&"."&K$5 -> egy.distn.pop.1 | L84: =INDEX(FromMitigation!$K$10:$IZ$10,L$8)*FromMitigation!$D$10 -> 127139321 | M84: =L84 -> 127139321 | N84: =M84 -> 127139321 | O84: =N84 -> 127139321 | P84: =O84 -> 127139321 | Q84: =P84 -> 127139321 | R84: =Q84 -> 127139321 | S84: =R84 -> 127139321 | T84: =S84 -> 127139321 | ... V84: =U84 -> 127139321 | W84: =IF(X$5=K$5,SUM(Y84:AI84)-SUM(L84:V84),"") | X84: =LOWER(CtryCode)&".distn."&$A84&IF($B84="","","."&$B84)&IF($C84="","",".dec."&$C84)&"."&X$5 -> egy.distn.pop.2 | Y84: =INDEX(FromMitigation!$K$10:$IZ$10,Y$8)*FromMitigation!$D$10 -> 127139321 | Z84: =Y84 -> 127139321 | AA84: =Z84 -> 127139321 | AB84: =AA84 -> 127139321 | AC84: =AB84 -> 127139321 | AD84: =AC84 -> 127139321 | AE84: =AD84 -> 127139321 | AF84: =AE84 -> 127139321 | AG84: =AF84 -> 127139321 | ... AI84: =AH84 -> 127139321
A86: rev | H86: Revenue from new policies (carbon pricing; legacy CP revenue) | I86: LCU | J86: Mitigation rnew x xr | K86: =LOWER(CtryCode)&".distn."&$A86&IF($B86="","","."&$B86)&IF($C86="","",".dec."&$C86)&"."&K$5 -> egy.distn.rev.1 | L86: =INDEX(FromMitigation!$K$11:$IZ$11,L$8)*FromMitigation!$D$11*INDEX(FromMitigation!$K$9:$IZ$9,L$8) -> 0 | M86: =L86 -> 0 | N86: =M86 -> 0 | O86: =N86 -> 0 | P86: =O86 -> 0 | Q86: =P86 -> 0 | R86: =Q86 -> 0 | S86: =R86 -> 0 | T86: =S86 -> 0 | ... V86: =U86 -> 0 | W86: =IF(X$5=K$5,SUM(Y86:AI86)-SUM(L86:V86),"") | X86: =LOWER(CtryCode)&".distn."&$A86&IF($B86="","","."&$B86)&IF($C86="","",".dec."&$C86)&"."&X$5 -> egy.distn.rev.2 | Y86: =INDEX(FromMitigation!$K$11:$IZ$11,Y$8)*FromMitigation!$D$11*INDEX(FromMitigation!$K$9:$IZ$9,Y$8) -> 7.4421168e+10 | Z86: =Y86 -> 7.4421168e+10 | AA86: =Z86 -> 7.4421168e+10 | AB86: =AA86 -> 7.4421168e+10 | AC86: =AB86 -> 7.4421168e+10 | AD86: =AC86 -> 7.4421168e+10 | AE86: =AD86 -> 7.4421168e+10 | AF86: =AE86 -> 7.4421168e+10 | AG86: =AF86 -> 7.4421168e+10 | ... AI86: =AH86 -> 7.4421168e+10
A88: 3 | B88: Indirect price changes of consumption categories (legacy C.I)
B90: Fuel groups of the input-output table: revenue (spending x price change), spending, total use, factor
A91: grev | B91: coa | H91: Coal: revenue at scenario-1 spending | I91: USD m | J91: legacy rows 549-556 | K91: =LOWER(CtryCode)&".distn."&$A91&IF($B91="","","."&$B91)&IF($C91="","",".dec."&$C91)&"."&K$5 -> egy.distn.grev.coa.1 | L91: =SUMPRODUCT(($D$73:$D$80=$B91)*L$73:L$80*L$65:L$72) -> 0 | M91: =L91 -> 0 | N91: =M91 -> 0 | O91: =N91 -> 0 | P91: =O91 -> 0 | Q91: =P91 -> 0 | R91: =Q91 -> 0 | S91: =R91 -> 0 | T91: =S91 -> 0 | ... V91: =U91 -> 0 | W91: =IF(X$5=K$5,SUM(Y91:AI91)-SUM(L91:V91),"") | X91: =LOWER(CtryCode)&".distn."&$A91&IF($B91="","","."&$B91)&IF($C91="","",".dec."&$C91)&"."&X$5 -> egy.distn.grev.coa.2 | Y91: =SUMPRODUCT(($D$73:$D$80=$B91)*Y$73:Y$80*Y$65:Y$72) -> 215.71034 | Z91: =Y91 -> 215.71034 | AA91: =Z91 -> 215.71034 | AB91: =AA91 -> 215.71034 | AC91: =AB91 -> 215.71034 | AD91: =AC91 -> 215.71034 | AE91: =AD91 -> 215.71034 | AF91: =AE91 -> 215.71034 | AG91: =AF91 -> 215.71034 | ... AI91: =AH91 -> 215.71034
A92: grev | B92: ely | H92: Electricity: revenue at scenario-1 spending | I92: USD m | J92: legacy rows 549-556 | K92: =LOWER(CtryCode)&".distn."&$A92&IF($B92="","","."&$B92)&IF($C92="","",".dec."&$C92)&"."&K$5 -> egy.distn.grev.ely.1 | L92: =SUMPRODUCT(($D$73:$D$80=$B92)*L$73:L$80*L$65:L$72) -> 0 | M92: =L92 -> 0 | N92: =M92 -> 0 | O92: =N92 -> 0 | P92: =O92 -> 0 | Q92: =P92 -> 0 | R92: =Q92 -> 0 | S92: =R92 -> 0 | T92: =S92 -> 0 | ... V92: =U92 -> 0 | W92: =IF(X$5=K$5,SUM(Y92:AI92)-SUM(L92:V92),"") | X92: =LOWER(CtryCode)&".distn."&$A92&IF($B92="","","."&$B92)&IF($C92="","",".dec."&$C92)&"."&X$5 -> egy.distn.grev.ely.2 | Y92: =SUMPRODUCT(($D$73:$D$80=$B92)*Y$73:Y$80*Y$65:Y$72) -> 1625.4373 | Z92: =Y92 -> 1625.4373 | AA92: =Z92 -> 1625.4373 | AB92: =AA92 -> 1625.4373 | AC92: =AB92 -> 1625.4373 | AD92: =AC92 -> 1625.4373 | AE92: =AD92 -> 1625.4373 | AF92: =AE92 -> 1625.4373 | AG92: =AF92 -> 1625.4373 | ... AI92: =AH92 -> 1625.4373
A93: grev | B93: nga | H93: Natural gas: revenue at scenario-1 spending | I93: USD m | J93: legacy rows 549-556 | K93: =LOWER(CtryCode)&".distn."&$A93&IF($B93="","","."&$B93)&IF($C93="","",".dec."&$C93)&"."&K$5 -> egy.distn.grev.nga.1 | L93: =SUMPRODUCT(($D$73:$D$80=$B93)*L$73:L$80*L$65:L$72) -> 0 | M93: =L93 -> 0 | N93: =M93 -> 0 | O93: =N93 -> 0 | P93: =O93 -> 0 | Q93: =P93 -> 0 | R93: =Q93 -> 0 | S93: =R93 -> 0 | T93: =S93 -> 0 | ... V93: =U93 -> 0 | W93: =IF(X$5=K$5,SUM(Y93:AI93)-SUM(L93:V93),"") | X93: =LOWER(CtryCode)&".distn."&$A93&IF($B93="","","."&$B93)&IF($C93="","",".dec."&$C93)&"."&X$5 -> egy.distn.grev.nga.2 | Y93: =SUMPRODUCT(($D$73:$D$80=$B93)*Y$73:Y$80*Y$65:Y$72) -> 617.93804 | Z93: =Y93 -> 617.93804 | AA93: =Z93 -> 617.93804 | AB93: =AA93 -> 617.93804 | AC93: =AB93 -> 617.93804 | AD93: =AC93 -> 617.93804 | AE93: =AD93 -> 617.93804 | AF93: =AE93 -> 617.93804 | AG93: =AF93 -> 617.93804 | ... AI93: =AH93 -> 617.93804
A94: grev | B94: oil | H94: Crude and other oil: revenue at scenario-1 spending | I94: USD m | J94: legacy rows 549-556 | K94: =LOWER(CtryCode)&".distn."&$A94&IF($B94="","","."&$B94)&IF($C94="","",".dec."&$C94)&"."&K$5 -> egy.distn.grev.oil.1 | L94: =SUMPRODUCT(($D$73:$D$80=$B94)*L$73:L$80*L$65:L$72) -> 0 | M94: =L94 -> 0 | N94: =M94 -> 0 | O94: =N94 -> 0 | P94: =O94 -> 0 | Q94: =P94 -> 0 | R94: =Q94 -> 0 | S94: =R94 -> 0 | T94: =S94 -> 0 | ... V94: =U94 -> 0 | W94: =IF(X$5=K$5,SUM(Y94:AI94)-SUM(L94:V94),"") | X94: =LOWER(CtryCode)&".distn."&$A94&IF($B94="","","."&$B94)&IF($C94="","",".dec."&$C94)&"."&X$5 -> egy.distn.grev.oil.2 | Y94: =SUMPRODUCT(($D$73:$D$80=$B94)*Y$73:Y$80*Y$65:Y$72) -> 207.06182 | Z94: =Y94 -> 207.06182 | AA94: =Z94 -> 207.06182 | AB94: =AA94 -> 207.06182 | AC94: =AB94 -> 207.06182 | AD94: =AC94 -> 207.06182 | AE94: =AD94 -> 207.06182 | AF94: =AE94 -> 207.06182 | AG94: =AF94 -> 207.06182 | ... AI94: =AH94 -> 207.06182
A95: grev | B95: p_c | H95: Refined products (gasoline, diesel, LPG, kerosene): revenue at scenario-1 spending | I95: USD m | J95: legacy rows 549-556 | K95: =LOWER(CtryCode)&".distn."&$A95&IF($B95="","","."&$B95)&IF($C95="","",".dec."&$C95)&"."&K$5 -> egy.distn.grev.p_c.1 | L95: =SUMPRODUCT(($D$73:$D$80=$B95)*L$73:L$80*L$65:L$72) -> 0 | M95: =L95 -> 0 | N95: =M95 -> 0 | O95: =N95 -> 0 | P95: =O95 -> 0 | Q95: =P95 -> 0 | R95: =Q95 -> 0 | S95: =R95 -> 0 | T95: =S95 -> 0 | ... V95: =U95 -> 0 | W95: =IF(X$5=K$5,SUM(Y95:AI95)-SUM(L95:V95),"") | X95: =LOWER(CtryCode)&".distn."&$A95&IF($B95="","","."&$B95)&IF($C95="","",".dec."&$C95)&"."&X$5 -> egy.distn.grev.p_c.2 | Y95: =SUMPRODUCT(($D$73:$D$80=$B95)*Y$73:Y$80*Y$65:Y$72) -> 2742.6346 | Z95: =Y95 -> 2742.6346 | AA95: =Z95 -> 2742.6346 | AB95: =AA95 -> 2742.6346 | AC95: =AB95 -> 2742.6346 | AD95: =AC95 -> 2742.6346 | AE95: =AD95 -> 2742.6346 | AF95: =AE95 -> 2742.6346 | AG95: =AF95 -> 2742.6346 | ... AI95: =AH95 -> 2742.6346
A96: gspend | B96: coa | H96: Coal: spending | I96: USD m | J96: legacy rows 528-535 | K96: =LOWER(CtryCode)&".distn."&$A96&IF($B96="","","."&$B96)&IF($C96="","",".dec."&$C96)&"."&K$5 -> egy.distn.gspend.coa.1 | L96: =SUMIF($D$73:$D$80,$B96,L$73:L$80) -> 778.18562 | M96: =L96 -> 778.18562 | N96: =M96 -> 778.18562 | O96: =N96 -> 778.18562 | P96: =O96 -> 778.18562 | Q96: =P96 -> 778.18562 | R96: =Q96 -> 778.18562 | S96: =R96 -> 778.18562 | T96: =S96 -> 778.18562 | ... V96: =U96 -> 778.18562 | W96: =IF(X$5=K$5,SUM(Y96:AI96)-SUM(L96:V96),"") | X96: =LOWER(CtryCode)&".distn."&$A96&IF($B96="","","."&$B96)&IF($C96="","",".dec."&$C96)&"."&X$5 -> egy.distn.gspend.coa.2 | Y96: =SUMIF($D$73:$D$80,$B96,Y$73:Y$80) -> 778.18562 | Z96: =Y96 -> 778.18562 | AA96: =Z96 -> 778.18562 | AB96: =AA96 -> 778.18562 | AC96: =AB96 -> 778.18562 | AD96: =AC96 -> 778.18562 | AE96: =AD96 -> 778.18562 | AF96: =AE96 -> 778.18562 | AG96: =AF96 -> 778.18562 | ... AI96: =AH96 -> 778.18562
A97: gspend | B97: ely | H97: Electricity: spending | I97: USD m | J97: legacy rows 528-535 | K97: =LOWER(CtryCode)&".distn."&$A97&IF($B97="","","."&$B97)&IF($C97="","",".dec."&$C97)&"."&K$5 -> egy.distn.gspend.ely.1 | L97: =SUMIF($D$73:$D$80,$B97,L$73:L$80) -> 10352.346 | M97: =L97 -> 10352.346 | N97: =M97 -> 10352.346 | O97: =N97 -> 10352.346 | P97: =O97 -> 10352.346 | Q97: =P97 -> 10352.346 | R97: =Q97 -> 10352.346 | S97: =R97 -> 10352.346 | T97: =S97 -> 10352.346 | ... V97: =U97 -> 10352.346 | W97: =IF(X$5=K$5,SUM(Y97:AI97)-SUM(L97:V97),"") | X97: =LOWER(CtryCode)&".distn."&$A97&IF($B97="","","."&$B97)&IF($C97="","",".dec."&$C97)&"."&X$5 -> egy.distn.gspend.ely.2 | Y97: =SUMIF($D$73:$D$80,$B97,Y$73:Y$80) -> 10352.346 | Z97: =Y97 -> 10352.346 | AA97: =Z97 -> 10352.346 | AB97: =AA97 -> 10352.346 | AC97: =AB97 -> 10352.346 | AD97: =AC97 -> 10352.346 | AE97: =AD97 -> 10352.346 | AF97: =AE97 -> 10352.346 | AG97: =AF97 -> 10352.346 | ... AI97: =AH97 -> 10352.346
A98: gspend | B98: nga | H98: Natural gas: spending | I98: USD m | J98: legacy rows 528-535 | K98: =LOWER(CtryCode)&".distn."&$A98&IF($B98="","","."&$B98)&IF($C98="","",".dec."&$C98)&"."&K$5 -> egy.distn.gspend.nga.1 | L98: =SUMIF($D$73:$D$80,$B98,L$73:L$80) -> 2716.9838 | M98: =L98 -> 2716.9838 | N98: =M98 -> 2716.9838 | O98: =N98 -> 2716.9838 | P98: =O98 -> 2716.9838 | Q98: =P98 -> 2716.9838 | R98: =Q98 -> 2716.9838 | S98: =R98 -> 2716.9838 | T98: =S98 -> 2716.9838 | ... V98: =U98 -> 2716.9838 | W98: =IF(X$5=K$5,SUM(Y98:AI98)-SUM(L98:V98),"") | X98: =LOWER(CtryCode)&".distn."&$A98&IF($B98="","","."&$B98)&IF($C98="","",".dec."&$C98)&"."&X$5 -> egy.distn.gspend.nga.2 | Y98: =SUMIF($D$73:$D$80,$B98,Y$73:Y$80) -> 2716.9838 | Z98: =Y98 -> 2716.9838 | AA98: =Z98 -> 2716.9838 | AB98: =AA98 -> 2716.9838 | AC98: =AB98 -> 2716.9838 | AD98: =AC98 -> 2716.9838 | AE98: =AD98 -> 2716.9838 | AF98: =AE98 -> 2716.9838 | AG98: =AF98 -> 2716.9838 | ... AI98: =AH98 -> 2716.9838
A99: gspend | B99: oil | H99: Crude and other oil: spending | I99: USD m | J99: legacy rows 528-535 | K99: =LOWER(CtryCode)&".distn."&$A99&IF($B99="","","."&$B99)&IF($C99="","",".dec."&$C99)&"."&K$5 -> egy.distn.gspend.oil.1 | L99: =SUMIF($D$73:$D$80,$B99,L$73:L$80) -> 595.23057 | M99: =L99 -> 595.23057 | N99: =M99 -> 595.23057 | O99: =N99 -> 595.23057 | P99: =O99 -> 595.23057 | Q99: =P99 -> 595.23057 | R99: =Q99 -> 595.23057 | S99: =R99 -> 595.23057 | T99: =S99 -> 595.23057 | ... V99: =U99 -> 595.23057 | W99: =IF(X$5=K$5,SUM(Y99:AI99)-SUM(L99:V99),"") | X99: =LOWER(CtryCode)&".distn."&$A99&IF($B99="","","."&$B99)&IF($C99="","",".dec."&$C99)&"."&X$5 -> egy.distn.gspend.oil.2 | Y99: =SUMIF($D$73:$D$80,$B99,Y$73:Y$80) -> 595.23057 | Z99: =Y99 -> 595.23057 | AA99: =Z99 -> 595.23057 | AB99: =AA99 -> 595.23057 | AC99: =AB99 -> 595.23057 | AD99: =AC99 -> 595.23057 | AE99: =AD99 -> 595.23057 | AF99: =AE99 -> 595.23057 | AG99: =AF99 -> 595.23057 | ... AI99: =AH99 -> 595.23057
A100: gspend | B100: p_c | H100: Refined products (gasoline, diesel, LPG, kerosene): spending | I100: USD m | J100: legacy rows 528-535 | K100: =LOWER(CtryCode)&".distn."&$A100&IF($B100="","","."&$B100)&IF($C100="","",".dec."&$C100)&"."&K$5 -> egy.distn.gspend.p_c.1 | L100: =SUMIF($D$73:$D$80,$B100,L$73:L$80) -> 14091.105 | M100: =L100 -> 14091.105 | N100: =M100 -> 14091.105 | O100: =N100 -> 14091.105 | P100: =O100 -> 14091.105 | Q100: =P100 -> 14091.105 | R100: =Q100 -> 14091.105 | S100: =R100 -> 14091.105 | T100: =S100 -> 14091.105 | ... V100: =U100 -> 14091.105 | W100: =IF(X$5=K$5,SUM(Y100:AI100)-SUM(L100:V100),"") | X100: =LOWER(CtryCode)&".distn."&$A100&IF($B100="","","."&$B100)&IF($C100="","",".dec."&$C100)&"."&X$5 -> egy.distn.gspend.p_c.2 | Y100: =SUMIF($D$73:$D$80,$B100,Y$73:Y$80) -> 14091.105 | Z100: =Y100 -> 14091.105 | AA100: =Z100 -> 14091.105 | AB100: =AA100 -> 14091.105 | AC100: =AB100 -> 14091.105 | AD100: =AC100 -> 14091.105 | AE100: =AD100 -> 14091.105 | AF100: =AE100 -> 14091.105 | AG100: =AF100 -> 14091.105 | ... AI100: =AH100 -> 14091.105
A101: gtot | B101: coa | H101: Coal: total use in the input-output table (embedded + own) | I101: USD m | J101: DistMapping, IO tables (legacy rows 588-600) | K101: =LOWER(CtryCode)&".distn."&$A101&IF($B101="","","."&$B101)&IF($C101="","",".dec."&$C101)&"."&K$5 -> egy.distn.gtot.coa.1 | L101: =INDEX(DIOTot,MATCH($B101,DIOTKey,0)) -> 4536.891 | M101: =L101 -> 4536.891 | N101: =M101 -> 4536.891 | O101: =N101 -> 4536.891 | P101: =O101 -> 4536.891 | Q101: =P101 -> 4536.891 | R101: =Q101 -> 4536.891 | S101: =R101 -> 4536.891 | T101: =S101 -> 4536.891 | ... V101: =U101 -> 4536.891 | W101: =IF(X$5=K$5,SUM(Y101:AI101)-SUM(L101:V101),"") | X101: =LOWER(CtryCode)&".distn."&$A101&IF($B101="","","."&$B101)&IF($C101="","",".dec."&$C101)&"."&X$5 -> egy.distn.gtot.coa.2 | Y101: =INDEX(DIOTot,MATCH($B101,DIOTKey,0)) -> 4536.891 | Z101: =Y101 -> 4536.891 | AA101: =Z101 -> 4536.891 | AB101: =AA101 -> 4536.891 | AC101: =AB101 -> 4536.891 | AD101: =AC101 -> 4536.891 | AE101: =AD101 -> 4536.891 | AF101: =AE101 -> 4536.891 | AG101: =AF101 -> 4536.891 | ... AI101: =AH101 -> 4536.891
A102: gtot | B102: ely | H102: Electricity: total use in the input-output table (embedded + own) | I102: USD m | J102: DistMapping, IO tables (legacy rows 588-600) | K102: =LOWER(CtryCode)&".distn."&$A102&IF($B102="","","."&$B102)&IF($C102="","",".dec."&$C102)&"."&K$5 -> egy.distn.gtot.ely.1 | L102: =INDEX(DIOTot,MATCH($B102,DIOTKey,0)) -> 33447.728 | M102: =L102 -> 33447.728 | N102: =M102 -> 33447.728 | O102: =N102 -> 33447.728 | P102: =O102 -> 33447.728 | Q102: =P102 -> 33447.728 | R102: =Q102 -> 33447.728 | S102: =R102 -> 33447.728 | T102: =S102 -> 33447.728 | ... V102: =U102 -> 33447.728 | W102: =IF(X$5=K$5,SUM(Y102:AI102)-SUM(L102:V102),"") | X102: =LOWER(CtryCode)&".distn."&$A102&IF($B102="","","."&$B102)&IF($C102="","",".dec."&$C102)&"."&X$5 -> egy.distn.gtot.ely.2 | Y102: =INDEX(DIOTot,MATCH($B102,DIOTKey,0)) -> 33447.728 | Z102: =Y102 -> 33447.728 | AA102: =Z102 -> 33447.728 | AB102: =AA102 -> 33447.728 | AC102: =AB102 -> 33447.728 | AD102: =AC102 -> 33447.728 | AE102: =AD102 -> 33447.728 | AF102: =AE102 -> 33447.728 | AG102: =AF102 -> 33447.728 | ... AI102: =AH102 -> 33447.728
A103: gtot | B103: nga | H103: Natural gas: total use in the input-output table (embedded + own) | I103: USD m | J103: DistMapping, IO tables (legacy rows 588-600) | K103: =LOWER(CtryCode)&".distn."&$A103&IF($B103="","","."&$B103)&IF($C103="","",".dec."&$C103)&"."&K$5 -> egy.distn.gtot.nga.1 | L103: =INDEX(DIOTot,MATCH($B103,DIOTKey,0)) -> 11798.434 | M103: =L103 -> 11798.434 | N103: =M103 -> 11798.434 | O103: =N103 -> 11798.434 | P103: =O103 -> 11798.434 | Q103: =P103 -> 11798.434 | R103: =Q103 -> 11798.434 | S103: =R103 -> 11798.434 | T103: =S103 -> 11798.434 | ... V103: =U103 -> 11798.434 | W103: =IF(X$5=K$5,SUM(Y103:AI103)-SUM(L103:V103),"") | X103: =LOWER(CtryCode)&".distn."&$A103&IF($B103="","","."&$B103)&IF($C103="","",".dec."&$C103)&"."&X$5 -> egy.distn.gtot.nga.2 | Y103: =INDEX(DIOTot,MATCH($B103,DIOTKey,0)) -> 11798.434 | Z103: =Y103 -> 11798.434 | AA103: =Z103 -> 11798.434 | AB103: =AA103 -> 11798.434 | AC103: =AB103 -> 11798.434 | AD103: =AC103 -> 11798.434 | AE103: =AD103 -> 11798.434 | AF103: =AE103 -> 11798.434 | AG103: =AF103 -> 11798.434 | ... AI103: =AH103 -> 11798.434
A104: gtot | B104: oil | H104: Crude and other oil: total use in the input-output table (embedded + own) | I104: USD m | J104: DistMapping, IO tables (legacy rows 588-600) | K104: =LOWER(CtryCode)&".distn."&$A104&IF($B104="","","."&$B104)&IF($C104="","",".dec."&$C104)&"."&K$5 -> egy.distn.gtot.oil.1 | L104: =INDEX(DIOTot,MATCH($B104,DIOTKey,0)) -> 74758.308 | M104: =L104 -> 74758.308 | N104: =M104 -> 74758.308 | O104: =N104 -> 74758.308 | P104: =O104 -> 74758.308 | Q104: =P104 -> 74758.308 | R104: =Q104 -> 74758.308 | S104: =R104 -> 74758.308 | T104: =S104 -> 74758.308 | ... V104: =U104 -> 74758.308 | W104: =IF(X$5=K$5,SUM(Y104:AI104)-SUM(L104:V104),"") | X104: =LOWER(CtryCode)&".distn."&$A104&IF($B104="","","."&$B104)&IF($C104="","",".dec."&$C104)&"."&X$5 -> egy.distn.gtot.oil.2 | Y104: =INDEX(DIOTot,MATCH($B104,DIOTKey,0)) -> 74758.308 | Z104: =Y104 -> 74758.308 | AA104: =Z104 -> 74758.308 | AB104: =AA104 -> 74758.308 | AC104: =AB104 -> 74758.308 | AD104: =AC104 -> 74758.308 | AE104: =AD104 -> 74758.308 | AF104: =AE104 -> 74758.308 | AG104: =AF104 -> 74758.308 | ... AI104: =AH104 -> 74758.308
A105: gtot | B105: p_c | H105: Refined products (gasoline, diesel, LPG, kerosene): total use in the input-output table (embedded + own) | I105: USD m | J105: DistMapping, IO tables (legacy rows 588-600) | K105: =LOWER(CtryCode)&".distn."&$A105&IF($B105="","","."&$B105)&IF($C105="","",".dec."&$C105)&"."&K$5 -> egy.distn.gtot.p_c.1 | L105: =INDEX(DIOTot,MATCH($B105,DIOTKey,0)) -> 137702.83 | M105: =L105 -> 137702.83 | N105: =M105 -> 137702.83 | O105: =N105 -> 137702.83 | P105: =O105 -> 137702.83 | Q105: =P105 -> 137702.83 | R105: =Q105 -> 137702.83 | S105: =R105 -> 137702.83 | T105: =S105 -> 137702.83 | ... V105: =U105 -> 137702.83 | W105: =IF(X$5=K$5,SUM(Y105:AI105)-SUM(L105:V105),"") | X105: =LOWER(CtryCode)&".distn."&$A105&IF($B105="","","."&$B105)&IF($C105="","",".dec."&$C105)&"."&X$5 -> egy.distn.gtot.p_c.2 | Y105: =INDEX(DIOTot,MATCH($B105,DIOTKey,0)) -> 137702.83 | Z105: =Y105 -> 137702.83 | AA105: =Z105 -> 137702.83 | AB105: =AA105 -> 137702.83 | AC105: =AB105 -> 137702.83 | AD105: =AC105 -> 137702.83 | AE105: =AD105 -> 137702.83 | AF105: =AE105 -> 137702.83 | AG105: =AF105 -> 137702.83 | ... AI105: =AH105 -> 137702.83
A106: gfac | B106: coa | H106: Coal: price factor (revenue / total use; ScaleGTAP = No: revenue / spending) | I106: fraction | J106: legacy rows 617-643 (k(s) cancels: method note) | K106: =LOWER(CtryCode)&".distn."&$A106&IF($B106="","","."&$B106)&IF($C106="","",".dec."&$C106)&"."&K$5 -> egy.distn.gfac.coa.1 | L106: =IF(LEFT(L$19,3)="Yes",L91/L101,IF(L96>0,L91/L96,0)) -> 0 | M106: =L106 -> 0 | N106: =M106 -> 0 | O106: =N106 -> 0 | P106: =O106 -> 0 | Q106: =P106 -> 0 | R106: =Q106 -> 0 | S106: =R106 -> 0 | T106: =S106 -> 0 | ... V106: =U106 -> 0 | W106: =IF(X$5=K$5,SUM(Y106:AI106)-SUM(L106:V106),"") | X106: =LOWER(CtryCode)&".distn."&$A106&IF($B106="","","."&$B106)&IF($C106="","",".dec."&$C106)&"."&X$5 -> egy.distn.gfac.coa.2 | Y106: =IF(LEFT(Y$19,3)="Yes",Y91/Y101,IF(Y96>0,Y91/Y96,0)) -> 0.04754585 | Z106: =Y106 -> 0.04754585 | AA106: =Z106 -> 0.04754585 | AB106: =AA106 -> 0.04754585 | AC106: =AB106 -> 0.04754585 | AD106: =AC106 -> 0.04754585 | AE106: =AD106 -> 0.04754585 | AF106: =AE106 -> 0.04754585 | AG106: =AF106 -> 0.04754585 | ... AI106: =AH106 -> 0.04754585
A107: gfac | B107: ely | H107: Electricity: price factor (revenue / total use; ScaleGTAP = No: revenue / spending) | I107: fraction | J107: legacy rows 617-643 (k(s) cancels: method note) | K107: =LOWER(CtryCode)&".distn."&$A107&IF($B107="","","."&$B107)&IF($C107="","",".dec."&$C107)&"."&K$5 -> egy.distn.gfac.ely.1 | L107: =IF(LEFT(L$19,3)="Yes",L92/L102,IF(L97>0,L92/L97,0)) -> 0 | M107: =L107 -> 0 | N107: =M107 -> 0 | O107: =N107 -> 0 | P107: =O107 -> 0 | Q107: =P107 -> 0 | R107: =Q107 -> 0 | S107: =R107 -> 0 | T107: =S107 -> 0 | ... V107: =U107 -> 0 | W107: =IF(X$5=K$5,SUM(Y107:AI107)-SUM(L107:V107),"") | X107: =LOWER(CtryCode)&".distn."&$A107&IF($B107="","","."&$B107)&IF($C107="","",".dec."&$C107)&"."&X$5 -> egy.distn.gfac.ely.2 | Y107: =IF(LEFT(Y$19,3)="Yes",Y92/Y102,IF(Y97>0,Y92/Y97,0)) -> 0.048596344 | Z107: =Y107 -> 0.048596344 | AA107: =Z107 -> 0.048596344 | AB107: =AA107 -> 0.048596344 | AC107: =AB107 -> 0.048596344 | AD107: =AC107 -> 0.048596344 | AE107: =AD107 -> 0.048596344 | AF107: =AE107 -> 0.048596344 | AG107: =AF107 -> 0.048596344 | ... AI107: =AH107 -> 0.048596344
A108: gfac | B108: nga | H108: Natural gas: price factor (revenue / total use; ScaleGTAP = No: revenue / spending) | I108: fraction | J108: legacy rows 617-643 (k(s) cancels: method note) | K108: =LOWER(CtryCode)&".distn."&$A108&IF($B108="","","."&$B108)&IF($C108="","",".dec."&$C108)&"."&K$5 -> egy.distn.gfac.nga.1 | L108: =IF(LEFT(L$19,3)="Yes",L93/L103,IF(L98>0,L93/L98,0)) -> 0 | M108: =L108 -> 0 | N108: =M108 -> 0 | O108: =N108 -> 0 | P108: =O108 -> 0 | Q108: =P108 -> 0 | R108: =Q108 -> 0 | S108: =R108 -> 0 | T108: =S108 -> 0 | ... V108: =U108 -> 0 | W108: =IF(X$5=K$5,SUM(Y108:AI108)-SUM(L108:V108),"") | X108: =LOWER(CtryCode)&".distn."&$A108&IF($B108="","","."&$B108)&IF($C108="","",".dec."&$C108)&"."&X$5 -> egy.distn.gfac.nga.2 | Y108: =IF(LEFT(Y$19,3)="Yes",Y93/Y103,IF(Y98>0,Y93/Y98,0)) -> 0.052374581 | Z108: =Y108 -> 0.052374581 | AA108: =Z108 -> 0.052374581 | AB108: =AA108 -> 0.052374581 | AC108: =AB108 -> 0.052374581 | AD108: =AC108 -> 0.052374581 | AE108: =AD108 -> 0.052374581 | AF108: =AE108 -> 0.052374581 | AG108: =AF108 -> 0.052374581 | ... AI108: =AH108 -> 0.052374581
A109: gfac | B109: oil | H109: Crude and other oil: price factor (revenue / total use; ScaleGTAP = No: revenue / spending) | I109: fraction | J109: legacy rows 617-643 (k(s) cancels: method note) | K109: =LOWER(CtryCode)&".distn."&$A109&IF($B109="","","."&$B109)&IF($C109="","",".dec."&$C109)&"."&K$5 -> egy.distn.gfac.oil.1 | L109: =IF(LEFT(L$19,3)="Yes",L94/L104,IF(L99>0,L94/L99,0)) -> 0 | M109: =L109 -> 0 | N109: =M109 -> 0 | O109: =N109 -> 0 | P109: =O109 -> 0 | Q109: =P109 -> 0 | R109: =Q109 -> 0 | S109: =R109 -> 0 | T109: =S109 -> 0 | ... V109: =U109 -> 0 | W109: =IF(X$5=K$5,SUM(Y109:AI109)-SUM(L109:V109),"") | X109: =LOWER(CtryCode)&".distn."&$A109&IF($B109="","","."&$B109)&IF($C109="","",".dec."&$C109)&"."&X$5 -> egy.distn.gfac.oil.2 | Y109: =IF(LEFT(Y$19,3)="Yes",Y94/Y104,IF(Y99>0,Y94/Y99,0)) -> 0.00276975 | Z109: =Y109 -> 0.00276975 | AA109: =Z109 -> 0.00276975 | AB109: =AA109 -> 0.00276975 | AC109: =AB109 -> 0.00276975 | AD109: =AC109 -> 0.00276975 | AE109: =AD109 -> 0.00276975 | AF109: =AE109 -> 0.00276975 | AG109: =AF109 -> 0.00276975 | ... AI109: =AH109 -> 0.00276975
A110: gfac | B110: p_c | H110: Refined products (gasoline, diesel, LPG, kerosene): price factor (revenue / total use; ScaleGTAP = No: revenue / spending) | I110: fraction | J110: legacy rows 617-643 (k(s) cancels: method note) | K110: =LOWER(CtryCode)&".distn."&$A110&IF($B110="","","."&$B110)&IF($C110="","",".dec."&$C110)&"."&K$5 -> egy.distn.gfac.p_c.1 | L110: =IF(LEFT(L$19,3)="Yes",L95/L105,IF(L100>0,L95/L100,0)) -> 0 | M110: =L110 -> 0 | N110: =M110 -> 0 | O110: =N110 -> 0 | P110: =O110 -> 0 | Q110: =P110 -> 0 | R110: =Q110 -> 0 | S110: =R110 -> 0 | T110: =S110 -> 0 | ... V110: =U110 -> 0 | W110: =IF(X$5=K$5,SUM(Y110:AI110)-SUM(L110:V110),"") | X110: =LOWER(CtryCode)&".distn."&$A110&IF($B110="","","."&$B110)&IF($C110="","",".dec."&$C110)&"."&X$5 -> egy.distn.gfac.p_c.2 | Y110: =IF(LEFT(Y$19,3)="Yes",Y95/Y105,IF(Y100>0,Y95/Y100,0)) -> 0.019917053 | Z110: =Y110 -> 0.019917053 | AA110: =Z110 -> 0.019917053 | AB110: =AA110 -> 0.019917053 | AC110: =AB110 -> 0.019917053 | AD110: =AC110 -> 0.019917053 | AE110: =AD110 -> 0.019917053 | AF110: =AE110 -> 0.019917053 | AG110: =AF110 -> 0.019917053 | ... AI110: =AH110 -> 0.019917053
B112: Consumption categories: household-demand weighted Leontief coefficients x fuel-group factors
A113: dpr | B113: app | H113: Appliances: price change | I113: fraction | J113: DistMapping, IO tables (legacy rows 668-736) | K113: =LOWER(CtryCode)&".distn."&$A113&IF($B113="","","."&$B113)&IF($C113="","",".dec."&$C113)&"."&K$5 -> egy.distn.dpr.app.1 | L113: =MMULT(INDEX(DLcat,MATCH($B113,DLcatKey,0),0),L$106:L$110) -> 0 | M113: =L113 -> 0 | N113: =M113 -> 0 | O113: =N113 -> 0 | P113: =O113 -> 0 | Q113: =P113 -> 0 | R113: =Q113 -> 0 | S113: =R113 -> 0 | T113: =S113 -> 0 | ... V113: =U113 -> 0 | W113: =IF(X$5=K$5,SUM(Y113:AI113)-SUM(L113:V113),"") | X113: =LOWER(CtryCode)&".distn."&$A113&IF($B113="","","."&$B113)&IF($C113="","",".dec."&$C113)&"."&X$5 -> egy.distn.dpr.app.2 | Y113: =MMULT(INDEX(DLcat,MATCH($B113,DLcatKey,0),0),Y$106:Y$110) -> 0.0027655371 | Z113: =Y113 -> 0.0027655371 | AA113: =Z113 -> 0.0027655371 | AB113: =AA113 -> 0.0027655371 | AC113: =AB113 -> 0.0027655371 | AD113: =AC113 -> 0.0027655371 | AE113: =AD113 -> 0.0027655371 | AF113: =AE113 -> 0.0027655371 | AG113: =AF113 -> 0.0027655371 | ... AI113: =AH113 -> 0.0027655371
A114: dpr | B114: che | H114: Chemicals: price change | I114: fraction | J114: DistMapping, IO tables (legacy rows 668-736) | K114: =LOWER(CtryCode)&".distn."&$A114&IF($B114="","","."&$B114)&IF($C114="","",".dec."&$C114)&"."&K$5 -> egy.distn.dpr.che.1 | L114: =MMULT(INDEX(DLcat,MATCH($B114,DLcatKey,0),0),L$106:L$110) -> 0 | M114: =L114 -> 0 | N114: =M114 -> 0 | O114: =N114 -> 0 | P114: =O114 -> 0 | Q114: =P114 -> 0 | R114: =Q114 -> 0 | S114: =R114 -> 0 | T114: =S114 -> 0 | ... V114: =U114 -> 0 | W114: =IF(X$5=K$5,SUM(Y114:AI114)-SUM(L114:V114),"") | X114: =LOWER(CtryCode)&".distn."&$A114&IF($B114="","","."&$B114)&IF($C114="","",".dec."&$C114)&"."&X$5 -> egy.distn.dpr.che.2 | Y114: =MMULT(INDEX(DLcat,MATCH($B114,DLcatKey,0),0),Y$106:Y$110) -> 0.0060375139 | Z114: =Y114 -> 0.0060375139 | AA114: =Z114 -> 0.0060375139 | AB114: =AA114 -> 0.0060375139 | AC114: =AB114 -> 0.0060375139 | AD114: =AC114 -> 0.0060375139 | AE114: =AD114 -> 0.0060375139 | AF114: =AE114 -> 0.0060375139 | AG114: =AF114 -> 0.0060375139 | ... AI114: =AH114 -> 0.0060375139
A115: dpr | B115: clo | H115: Clothing: price change | I115: fraction | J115: DistMapping, IO tables (legacy rows 668-736) | K115: =LOWER(CtryCode)&".distn."&$A115&IF($B115="","","."&$B115)&IF($C115="","",".dec."&$C115)&"."&K$5 -> egy.distn.dpr.clo.1 | L115: =MMULT(INDEX(DLcat,MATCH($B115,DLcatKey,0),0),L$106:L$110) -> 0 | M115: =L115 -> 0 | N115: =M115 -> 0 | O115: =N115 -> 0 | P115: =O115 -> 0 | Q115: =P115 -> 0 | R115: =Q115 -> 0 | S115: =R115 -> 0 | T115: =S115 -> 0 | ... V115: =U115 -> 0 | W115: =IF(X$5=K$5,SUM(Y115:AI115)-SUM(L115:V115),"") | X115: =LOWER(CtryCode)&".distn."&$A115&IF($B115="","","."&$B115)&IF($C115="","",".dec."&$C115)&"."&X$5 -> egy.distn.dpr.clo.2 | Y115: =MMULT(INDEX(DLcat,MATCH($B115,DLcatKey,0),0),Y$106:Y$110) -> 0.0011270396 | Z115: =Y115 -> 0.0011270396 | AA115: =Z115 -> 0.0011270396 | AB115: =AA115 -> 0.0011270396 | AC115: =AB115 -> 0.0011270396 | AD115: =AC115 -> 0.0011270396 | AE115: =AD115 -> 0.0011270396 | AF115: =AE115 -> 0.0011270396 | AG115: =AF115 -> 0.0011270396 | ... AI115: =AH115 -> 0.0011270396
A116: dpr | B116: com | H116: Communications: price change | I116: fraction | J116: DistMapping, IO tables (legacy rows 668-736) | K116: =LOWER(CtryCode)&".distn."&$A116&IF($B116="","","."&$B116)&IF($C116="","",".dec."&$C116)&"."&K$5 -> egy.distn.dpr.com.1 | L116: =MMULT(INDEX(DLcat,MATCH($B116,DLcatKey,0),0),L$106:L$110) -> 0 | M116: =L116 -> 0 | N116: =M116 -> 0 | O116: =N116 -> 0 | P116: =O116 -> 0 | Q116: =P116 -> 0 | R116: =Q116 -> 0 | S116: =R116 -> 0 | T116: =S116 -> 0 | ... V116: =U116 -> 0 | W116: =IF(X$5=K$5,SUM(Y116:AI116)-SUM(L116:V116),"") | X116: =LOWER(CtryCode)&".distn."&$A116&IF($B116="","","."&$B116)&IF($C116="","",".dec."&$C116)&"."&X$5 -> egy.distn.dpr.com.2 | Y116: =MMULT(INDEX(DLcat,MATCH($B116,DLcatKey,0),0),Y$106:Y$110) -> 0.00042590043 | Z116: =Y116 -> 0.00042590043 | AA116: =Z116 -> 0.00042590043 | AB116: =AA116 -> 0.00042590043 | AC116: =AB116 -> 0.00042590043 | AD116: =AC116 -> 0.00042590043 | AE116: =AD116 -> 0.00042590043 | AF116: =AE116 -> 0.00042590043 | AG116: =AF116 -> 0.00042590043 | ... AI116: =AH116 -> 0.00042590043
A117: dpr | B117: edu | H117: Education: price change | I117: fraction | J117: DistMapping, IO tables (legacy rows 668-736) | K117: =LOWER(CtryCode)&".distn."&$A117&IF($B117="","","."&$B117)&IF($C117="","",".dec."&$C117)&"."&K$5 -> egy.distn.dpr.edu.1 | L117: =MMULT(INDEX(DLcat,MATCH($B117,DLcatKey,0),0),L$106:L$110) -> 0 | M117: =L117 -> 0 | N117: =M117 -> 0 | O117: =N117 -> 0 | P117: =O117 -> 0 | Q117: =P117 -> 0 | R117: =Q117 -> 0 | S117: =R117 -> 0 | T117: =S117 -> 0 | ... V117: =U117 -> 0 | W117: =IF(X$5=K$5,SUM(Y117:AI117)-SUM(L117:V117),"") | X117: =LOWER(CtryCode)&".distn."&$A117&IF($B117="","","."&$B117)&IF($C117="","",".dec."&$C117)&"."&X$5 -> egy.distn.dpr.edu.2 | Y117: =MMULT(INDEX(DLcat,MATCH($B117,DLcatKey,0),0),Y$106:Y$110) -> 0.0010212791 | Z117: =Y117 -> 0.0010212791 | AA117: =Z117 -> 0.0010212791 | AB117: =AA117 -> 0.0010212791 | AC117: =AB117 -> 0.0010212791 | AD117: =AC117 -> 0.0010212791 | AE117: =AD117 -> 0.0010212791 | AF117: =AE117 -> 0.0010212791 | AG117: =AF117 -> 0.0010212791 | ... AI117: =AH117 -> 0.0010212791
A118: dpr | B118: food | H118: Food: price change | I118: fraction | J118: DistMapping, IO tables (legacy rows 668-736) | K118: =LOWER(CtryCode)&".distn."&$A118&IF($B118="","","."&$B118)&IF($C118="","",".dec."&$C118)&"."&K$5 -> egy.distn.dpr.food.1 | L118: =MMULT(INDEX(DLcat,MATCH($B118,DLcatKey,0),0),L$106:L$110) -> 0 | M118: =L118 -> 0 | N118: =M118 -> 0 | O118: =N118 -> 0 | P118: =O118 -> 0 | Q118: =P118 -> 0 | R118: =Q118 -> 0 | S118: =R118 -> 0 | T118: =S118 -> 0 | ... V118: =U118 -> 0 | W118: =IF(X$5=K$5,SUM(Y118:AI118)-SUM(L118:V118),"") | X118: =LOWER(CtryCode)&".distn."&$A118&IF($B118="","","."&$B118)&IF($C118="","",".dec."&$C118)&"."&X$5 -> egy.distn.dpr.food.2 | Y118: =MMULT(INDEX(DLcat,MATCH($B118,DLcatKey,0),0),Y$106:Y$110) -> 0.0011484804 | Z118: =Y118 -> 0.0011484804 | AA118: =Z118 -> 0.0011484804 | AB118: =AA118 -> 0.0011484804 | AC118: =AB118 -> 0.0011484804 | AD118: =AC118 -> 0.0011484804 | AE118: =AD118 -> 0.0011484804 | AF118: =AE118 -> 0.0011484804 | AG118: =AF118 -> 0.0011484804 | ... AI118: =AH118 -> 0.0011484804
A119: dpr | B119: hea | H119: Health services: price change | I119: fraction | J119: DistMapping, IO tables (legacy rows 668-736) | K119: =LOWER(CtryCode)&".distn."&$A119&IF($B119="","","."&$B119)&IF($C119="","",".dec."&$C119)&"."&K$5 -> egy.distn.dpr.hea.1 | L119: =MMULT(INDEX(DLcat,MATCH($B119,DLcatKey,0),0),L$106:L$110) -> 0 | M119: =L119 -> 0 | N119: =M119 -> 0 | O119: =N119 -> 0 | P119: =O119 -> 0 | Q119: =P119 -> 0 | R119: =Q119 -> 0 | S119: =R119 -> 0 | T119: =S119 -> 0 | ... V119: =U119 -> 0 | W119: =IF(X$5=K$5,SUM(Y119:AI119)-SUM(L119:V119),"") | X119: =LOWER(CtryCode)&".distn."&$A119&IF($B119="","","."&$B119)&IF($C119="","",".dec."&$C119)&"."&X$5 -> egy.distn.dpr.hea.2 | Y119: =MMULT(INDEX(DLcat,MATCH($B119,DLcatKey,0),0),Y$106:Y$110) -> 0.0012177198 | Z119: =Y119 -> 0.0012177198 | AA119: =Z119 -> 0.0012177198 | AB119: =AA119 -> 0.0012177198 | AC119: =AB119 -> 0.0012177198 | AD119: =AC119 -> 0.0012177198 | AE119: =AD119 -> 0.0012177198 | AF119: =AE119 -> 0.0012177198 | AG119: =AF119 -> 0.0012177198 | ... AI119: =AH119 -> 0.0012177198
A120: dpr | B120: hou | H120: Housing: price change | I120: fraction | J120: DistMapping, IO tables (legacy rows 668-736) | K120: =LOWER(CtryCode)&".distn."&$A120&IF($B120="","","."&$B120)&IF($C120="","",".dec."&$C120)&"."&K$5 -> egy.distn.dpr.hou.1 | L120: =MMULT(INDEX(DLcat,MATCH($B120,DLcatKey,0),0),L$106:L$110) -> 0 | M120: =L120 -> 0 | N120: =M120 -> 0 | O120: =N120 -> 0 | P120: =O120 -> 0 | Q120: =P120 -> 0 | R120: =Q120 -> 0 | S120: =R120 -> 0 | T120: =S120 -> 0 | ... V120: =U120 -> 0 | W120: =IF(X$5=K$5,SUM(Y120:AI120)-SUM(L120:V120),"") | X120: =LOWER(CtryCode)&".distn."&$A120&IF($B120="","","."&$B120)&IF($C120="","",".dec."&$C120)&"."&X$5 -> egy.distn.dpr.hou.2 | Y120: =MMULT(INDEX(DLcat,MATCH($B120,DLcatKey,0),0),Y$106:Y$110) -> 0.00094878775 | Z120: =Y120 -> 0.00094878775 | AA120: =Z120 -> 0.00094878775 | AB120: =AA120 -> 0.00094878775 | AC120: =AB120 -> 0.00094878775 | AD120: =AC120 -> 0.00094878775 | AE120: =AD120 -> 0.00094878775 | AF120: =AE120 -> 0.00094878775 | AG120: =AF120 -> 0.00094878775 | ... AI120: =AH120 -> 0.00094878775
A121: dpr | B121: oth | H121: Other: price change | I121: fraction | J121: DistMapping, IO tables (legacy rows 668-736) | K121: =LOWER(CtryCode)&".distn."&$A121&IF($B121="","","."&$B121)&IF($C121="","",".dec."&$C121)&"."&K$5 -> egy.distn.dpr.oth.1 | L121: =MMULT(INDEX(DLcat,MATCH($B121,DLcatKey,0),0),L$106:L$110) -> 0 | M121: =L121 -> 0 | N121: =M121 -> 0 | O121: =N121 -> 0 | P121: =O121 -> 0 | Q121: =P121 -> 0 | R121: =Q121 -> 0 | S121: =R121 -> 0 | T121: =S121 -> 0 | ... V121: =U121 -> 0 | W121: =IF(X$5=K$5,SUM(Y121:AI121)-SUM(L121:V121),"") | X121: =LOWER(CtryCode)&".distn."&$A121&IF($B121="","","."&$B121)&IF($C121="","",".dec."&$C121)&"."&X$5 -> egy.distn.dpr.oth.2 | Y121: =MMULT(INDEX(DLcat,MATCH($B121,DLcatKey,0),0),Y$106:Y$110) -> 0.00050612789 | Z121: =Y121 -> 0.00050612789 | AA121: =Z121 -> 0.00050612789 | AB121: =AA121 -> 0.00050612789 | AC121: =AB121 -> 0.00050612789 | AD121: =AC121 -> 0.00050612789 | AE121: =AD121 -> 0.00050612789 | AF121: =AE121 -> 0.00050612789 | AG121: =AF121 -> 0.00050612789 | ... AI121: =AH121 -> 0.00050612789
A122: dpr | B122: pap | H122: Paper: price change | I122: fraction | J122: DistMapping, IO tables (legacy rows 668-736) | K122: =LOWER(CtryCode)&".distn."&$A122&IF($B122="","","."&$B122)&IF($C122="","",".dec."&$C122)&"."&K$5 -> egy.distn.dpr.pap.1 | L122: =MMULT(INDEX(DLcat,MATCH($B122,DLcatKey,0),0),L$106:L$110) -> 0 | M122: =L122 -> 0 | N122: =M122 -> 0 | O122: =N122 -> 0 | P122: =O122 -> 0 | Q122: =P122 -> 0 | R122: =Q122 -> 0 | S122: =R122 -> 0 | T122: =S122 -> 0 | ... V122: =U122 -> 0 | W122: =IF(X$5=K$5,SUM(Y122:AI122)-SUM(L122:V122),"") | X122: =LOWER(CtryCode)&".distn."&$A122&IF($B122="","","."&$B122)&IF($C122="","",".dec."&$C122)&"."&X$5 -> egy.distn.dpr.pap.2 | Y122: =MMULT(INDEX(DLcat,MATCH($B122,DLcatKey,0),0),Y$106:Y$110) -> 0.0020276717 | Z122: =Y122 -> 0.0020276717 | AA122: =Z122 -> 0.0020276717 | AB122: =AA122 -> 0.0020276717 | AC122: =AB122 -> 0.0020276717 | AD122: =AC122 -> 0.0020276717 | AE122: =AD122 -> 0.0020276717 | AF122: =AE122 -> 0.0020276717 | AG122: =AF122 -> 0.0020276717 | ... AI122: =AH122 -> 0.0020276717
A123: dpr | B123: pha | H123: Pharmaceuticals: price change | I123: fraction | J123: DistMapping, IO tables (legacy rows 668-736) | K123: =LOWER(CtryCode)&".distn."&$A123&IF($B123="","","."&$B123)&IF($C123="","",".dec."&$C123)&"."&K$5 -> egy.distn.dpr.pha.1 | L123: =MMULT(INDEX(DLcat,MATCH($B123,DLcatKey,0),0),L$106:L$110) -> 0 | M123: =L123 -> 0 | N123: =M123 -> 0 | O123: =N123 -> 0 | P123: =O123 -> 0 | Q123: =P123 -> 0 | R123: =Q123 -> 0 | S123: =R123 -> 0 | T123: =S123 -> 0 | ... V123: =U123 -> 0 | W123: =IF(X$5=K$5,SUM(Y123:AI123)-SUM(L123:V123),"") | X123: =LOWER(CtryCode)&".distn."&$A123&IF($B123="","","."&$B123)&IF($C123="","",".dec."&$C123)&"."&X$5 -> egy.distn.dpr.pha.2 | Y123: =MMULT(INDEX(DLcat,MATCH($B123,DLcatKey,0),0),Y$106:Y$110) -> 0.0022039386 | Z123: =Y123 -> 0.0022039386 | AA123: =Z123 -> 0.0022039386 | AB123: =AA123 -> 0.0022039386 | AC123: =AB123 -> 0.0022039386 | AD123: =AC123 -> 0.0022039386 | AE123: =AD123 -> 0.0022039386 | AF123: =AE123 -> 0.0022039386 | AG123: =AF123 -> 0.0022039386 | ... AI123: =AH123 -> 0.0022039386
...

Sheet Constants and Mappings
A2: Constants and Mappings: global settings (from MTInputs), named constants, mappings, the data step (every lookup Mitigation reads)
A3: Global settings (inputs: MTInputs, Model settings)
B4: Country code | C4: =ScenarioDefinition!$J$531 -> EGY
B5: Country name | C5: Egypt
B6: Income group (selects elasticities) | C6: LMIC
B7: Base year | C7: =ScenarioDefinition!$J$532 -> 2022
B8: Results in real USD of year (MTInputs ResultsYear, scenario 1) | C8: =INDEX(SDBase,MATCH("ResultsYear",SDParam,0)) -> 2026
B9: Government energy price controls (MTInputs GovPriceControls, scenario 1) | C9: =INDEX(SDBase,MATCH("GovPriceControls",SDParam,0)) -> Bucketed*
B10: Last historical price year (IMF price dataset) | C10: =ScenarioDefinition!$J$533 -> 2024
B11: Gas market (Prices_int regional assumptions, by country name) | C11: Global
B12: Gas price commodity key (Prices_int) | C12: =IF($C$11="LNG","lng",IF($C$11="Europe","eus",IF($C$11="North Am","nam","glo"))) -> glo
B13: PJ per ktoe (ktoe x PJ/ktoe x $/GJ = USD million; x tCO2/GJ = MtCO2) | C13: 0.041868
B14: ETS: relative effectiveness of output-based allocation (fast estimate; auctioned = 1; legacy hardcoded) | C14: =ScenarioDefinition!$J$534 -> 0.5
B15: ETS: convergence exponent of the next-price proposal (legacy convergence factor, row 1966) | C15: =ScenarioDefinition!$J$535 -> 0.5
B16: ETS volatility table (sheet ETS+LTS rows 5-7; MTInputs labels ETSVolatility, ETSVolImpact) | C16: Medium | D16: High | E16: Low | F16: Zero
B17: Assumed annual price volatility of the ETS | C17: 0.42 | D17: 0.63 | E17: 0.28 | F17: 0
B18: Abatement cost increase per unit of volatility (impact) | C18: 0.5 | D18: 0.75 | E18: 0.33333333 | F18: 0
B19: Fuel use and power demand: apply the legacy 2023-2024 energy demand shock (1 = yes, as legacy; legacy rows 2439 and 483, data PowerPaths shock) | C19: =ScenarioDefinition!$J$536 -> 1
B20: Output code prefix (country.mit.; defined name CodePrefix) | C20: =LOWER($C$4)&".mit." -> egy.mit.
B21: Power: use spot fuel prices (Yes / No; legacy option; No = centred 5-year moving average of the price before new policies, as legacy A18; defined name SpotPow) | C21: =ScenarioDefinition!$J$542 -> No
B22: US CPI of ResultsYear (WEO USA|pcpi; CPIRes, base of the real-price index) | C22: =INDEX(WEOVal,MATCH("USA|pcpi",WEOKey,0),MATCH($C$8,WEOYear,0)) -> 332.66286
B23: US GDP deflator of ResultsYear (WEO USA|ngdp_d; DeflRes) | C23: =INDEX(WEOVal,MATCH("USA|ngdp_d",WEOKey,0),MATCH($C$8,WEOYear,0)) -> 132.68145
B24: Prices_dom row of the country and base year (PDomBase) | C24: 4
B25: Prices_dom row of the country and last historical price year (PDomLast) | C25: 6
B26: Last GHG inventory year of the country (sheet GHGs; GHGYear) | C26: 2024
B27: Calibrate energy CO2 to the GHG inventory (Yes / No; v0.4.11: Yes, as legacy EFsAdjustmentAnnexI and NonAnnexI, both Yes*; uses the country's scenario-1 CO2 with uncalibrated EFs on sheet BaselineCO2, row country|raw, refreshed by the build) | C27: =IF(LEFT(D27,1)="Y","Yes","No") -> Yes | D27: =INDEX(SDBase,MATCH("EFsAdjustmentAnnexI",SDParam,0)) -> Yes*
B28: Energy CO2 of the inventory in the year before the base year (Mt CO2; sheet GHGs, enr.co2; as legacy row 839, v0.4.11) | C28: 211.05354
B29: CO2 calibration factor (EFCalib): C28 / C30 if C27 = Yes, else 1; every CO2 EF is multiplied by it | C29: =IF(LEFT($C$27,3)="Yes",IFERROR($C$28/$C$30,1),1) -> 0.99554043
B30: Scenario-1 energy CO2 with uncalibrated EFs in the base year (Mt CO2; sheet BaselineCO2 row raw; as legacy row 623: the base-year energy balance, v0.4.11) | C30: 211.99896
B31: Base-year fuel use and power demand from: Balances (legacy default) or EnergyCons (MTInputs BalancesOrConsumption, scenario 1; BalOpt) | C31: =INDEX(SDBase,MATCH("BalancesOrConsumption",SDParam,0)) -> Balances
B32: Social cost of carbon (section 18; legacy Mitigation rows 17671-17677)
B33: Target-consistent carbon price (USD per tCO2 real; SCCTgt) | C33: =INDEX(SDBase,MATCH("SCCTargetConsistentCP",SDParam,0)) -> 75
B34: Year of the target-consistent price (SCCTgtYr) | C34: =ScenarioDefinition!$J$537 -> 2030
B35: SCC: real growth a year (SCCGr) | C35: =INDEX(SDBase,MATCH("SCCRise",SDParam,0)) -> 0.04
B36: Source of the national SCC: Target, Ricke, Manual or EPA (NSCCSrc; legacy Target*) | C36: =INDEX(SDBase,MATCH("NSCCSource",SDParam,0)) -> Target*
B37: Source of the global SCC: Target, Ricke, Manual or EPA (GSCCSrc; legacy Target*) | C37: =INDEX(SDBase,MATCH("GSCCSource",SDParam,0)) -> Target*
B38: Ricke et al. (2018): pure rate of time preference, 1 or 2 (%) | C38: =INDEX(SDBase,MATCH("NSCCDiscountRate",SDParam,0)) -> 2%*
B39: Ricke et al. (2018): elasticity of marginal utility, 0p7 or 1p5 | C39: =INDEX(SDBase,MATCH("NSCCMargUtilofCons",SDParam,0)) -> 1.5%*
B40: US EPA SCC (2.5% discount rate) in the base year (USD per tCO2 real; SCCEpa) | C40: =ScenarioDefinition!$J$538 -> 62
B41: Key of the national Ricke value (sheet SCC; RickeN) | C41: =LOWER($C$4)&"."&LEFT($C$38,1)&"."&SUBSTITUTE(LEFT($C$39,FIND("%",$C$39&"%")-1),".","p") -> egy.2.1p5
B42: Key of the global Ricke value (sheet SCC; RickeG) | C42: ="wld."&LEFT($C$38,1)&"."&SUBSTITUTE(LEFT($C$39,FIND("%",$C$39&"%")-1),".","p") -> wld.2.1p5
B43: World Bank region of the country, lower case (Countries; CtryReg: regional IIASA CO2 emission factors, sheet EF_GHG) | C43: mea
B44: Key prefix of the Balances information flows info_agrc, info_fish, info_food, info_wood (BalInfo: food share of food & forestry, legacy rows 1666-1673; v0.4.11) | C44: =$C$4&"|info_" -> EGY|info_
B45: Power: the investment deficit left after the second round goes to gas (Yes / No; legacy typed switch E4248, default No; PwDeficitGas; v0.5.4) | C45: =ScenarioDefinition!$J$540 -> No
B46: Methane fee applies to (Yes / No; inputs on sheet Manual inputs J196:J200, the legacy addresses; shown here; v0.5.2)
B47: Methane fee applies to biomass (MFeeBio = Manual inputs J196) | C47: No
B48: Methane fee applies to downstream gas (MFeeDG = Manual inputs J197) | C48: Yes
B49: Methane fee applies to fossil fuel production (oil, gas and coal) (MFeeFF = Manual inputs J198) | C49: Yes
B50: Methane fee applies to agriculture (livestock, rice) (MFeeAgr = Manual inputs J199) | C50: Yes
B51: Methane fee applies to waste (MFeeWst = Manual inputs J200) | C51: Yes
B53: Biomass is a normal good: residential biomass grows with income (Yes / No; MTInputs BiomassNormal, scenario 1; BioNormal; legacy row 5567; v0.4.13, I24) | C53: =INDEX(SDBase,MATCH("BiomassNormal",SDParam,0)) -> No
B54: Average price change reported (Legacy* / Laspeyres; PavMethod): Legacy* = legacy F5b-c (coal and gas over power, residential and industry at scenario-1 quantities; electricity own quantities; oil products the single price); Laspeyres = all final uses at scenario-1 quantities (v0.4.15, I31) | C54: =ScenarioDefinition!$J$539 -> Legacy*
B55: Multiplier group of each MTInputs MultipliersSource (row 226; first three letters, column B; any other text: the income group; MultSrcKey, MultSrcVal; v0.4.15, LD56)
B56: Glo | C56: global
B57: Est | C57: est
B58: Man | C58: man
B59: Include leakage to biomass in the residential sector (Yes / No; MTInputs BiomassLeakage, scenario 1; BioLeak; legacy rows 1785, 5571-5593; section 6b, v0.5.1) | C59: =INDEX(SDBase,MATCH("BiomassLeakage",SDParam,0)) -> No
B60: Residential cookstove efficiency by fuel (MTInputs NatGasEff, LPGEff, KerEff, BioEff, scenario 1; CookEffKey, CookEffVal, CookEffBio; legacy C5578-C5593; v0.5.1)
B61: nga | C61: =INDEX(SDBase,MATCH("NatGasEff",SDParam,0)) -> 0.58
B62: lpg | C62: =INDEX(SDBase,MATCH("LPGEff",SDParam,0)) -> 0.56
B63: ker | C63: =INDEX(SDBase,MATCH("KerEff",SDParam,0)) -> 0.45
B64: bio | C64: =INDEX(SDBase,MATCH("BioEff",SDParam,0)) -> 0.2
B65: Most-used cooking fuel of the country (WHOCooking, overall sample; CookFuel: the fuel that leaks to biomass; legacy L1784; v0.5.1) | C65: =IFERROR(INDEX(DCookFuel,MATCH(CtryCode&".distn.pcoff.ove",DCookKey,0)),"lpg") -> lpg
B66: Power: the coal implicit cost enters generation costs and tariffs (Yes / No; legacy: Yes; PwCoalICTariff; v0.5.6, PowerFeatures_Plan P5, decision 6). It always enters dispatch and investment | C66: =ScenarioDefinition!$J$541 -> Yes
B68: Initially exempt residential demand (legacy rows 1784-1795, 5564-5570; v0.5.6, LegacyDiff 67): MTInputs ExemptMostCook and ExemptCookDeciles (scenario 1), and the share of the most-used cooking fuel spent by the exempt deciles (HHSurvey, overall mean: budget share x consumption per capita x weight)
C69: =INDEX(SDBase,MATCH("ExemptMostCook",SDParam,0)) -> No
C70: =INDEX(SDBase,MATCH("ExemptCookDeciles",SDParam,0)) -> 4
A71: Decile | B71: Budget share of the fuel | C71: Consumption per capita | D71: Exempt (1/0) | E71: HHSurvey row | F71: Population weight
A72: 1 | B72: =IFERROR(INDEX(DHHVal,$E72,MATCH(CookFuel&"_share",DHHVar,0)),0) -> 2.6948595 | C72: =IFERROR(INDEX(DHHVal,$E72,MATCH("cons_pc_acrent",DHHVar,0)),0) -> 5229.7958 | D72: =IF(AND(LEFT($C$69,1)="Y",$A72<=$C$70),1,0) -> 0 | E72: =MATCH(CtryCode&".distn.bsh.dec.ove.mean."&$A72,DHHKey,0) -> 1 | F72: =IFERROR(INDEX(DHHVal,$E72,MATCH("popw",DHHVar,0)),0) -> 10019634
A73: 2 | B73: =IFERROR(INDEX(DHHVal,$E73,MATCH(CookFuel&"_share",DHHVar,0)),0) -> 2.3273985 | C73: =IFERROR(INDEX(DHHVal,$E73,MATCH("cons_pc_acrent",DHHVar,0)),0) -> 6664.2194 | D73: =IF(AND(LEFT($C$69,1)="Y",$A73<=$C$70),1,0) -> 0 | E73: =MATCH(CtryCode&".distn.bsh.dec.ove.mean."&$A73,DHHKey,0) -> 2 | F73: =IFERROR(INDEX(DHHVal,$E73,MATCH("popw",DHHVar,0)),0) -> 9844693
A74: 3 | B74: =IFERROR(INDEX(DHHVal,$E74,MATCH(CookFuel&"_share",DHHVar,0)),0) -> 2.1304738 | C74: =IFERROR(INDEX(DHHVal,$E74,MATCH("cons_pc_acrent",DHHVar,0)),0) -> 8231.7709 | D74: =IF(AND(LEFT($C$69,1)="Y",$A74<=$C$70),1,0) -> 0 | E74: =MATCH(CtryCode&".distn.bsh.dec.ove.mean."&$A74,DHHKey,0) -> 3 | F74: =IFERROR(INDEX(DHHVal,$E74,MATCH("popw",DHHVar,0)),0) -> 11193191
A75: 4 | B75: =IFERROR(INDEX(DHHVal,$E75,MATCH(CookFuel&"_share",DHHVar,0)),0) -> 1.8326297 | C75: =IFERROR(INDEX(DHHVal,$E75,MATCH("cons_pc_acrent",DHHVar,0)),0) -> 9811.9494 | D75: =IF(AND(LEFT($C$69,1)="Y",$A75<=$C$70),1,0) -> 0 | E75: =MATCH(CtryCode&".distn.bsh.dec.ove.mean."&$A75,DHHKey,0) -> 4 | F75: =IFERROR(INDEX(DHHVal,$E75,MATCH("popw",DHHVar,0)),0) -> 10068726
A76: 5 | B76: =IFERROR(INDEX(DHHVal,$E76,MATCH(CookFuel&"_share",DHHVar,0)),0) -> 1.7256762 | C76: =IFERROR(INDEX(DHHVal,$E76,MATCH("cons_pc_acrent",DHHVar,0)),0) -> 10348.651 | D76: =IF(AND(LEFT($C$69,1)="Y",$A76<=$C$70),1,0) -> 0 | E76: =MATCH(CtryCode&".distn.bsh.dec.ove.mean."&$A76,DHHKey,0) -> 5 | F76: =IFERROR(INDEX(DHHVal,$E76,MATCH("popw",DHHVar,0)),0) -> 10271899
A77: 6 | B77: =IFERROR(INDEX(DHHVal,$E77,MATCH(CookFuel&"_share",DHHVar,0)),0) -> 1.6333041 | C77: =IFERROR(INDEX(DHHVal,$E77,MATCH("cons_pc_acrent",DHHVar,0)),0) -> 11013.48 | D77: =IF(AND(LEFT($C$69,1)="Y",$A77<=$C$70),1,0) -> 0 | E77: =MATCH(CtryCode&".distn.bsh.dec.ove.mean."&$A77,DHHKey,0) -> 6 | F77: =IFERROR(INDEX(DHHVal,$E77,MATCH("popw",DHHVar,0)),0) -> 11280763
A78: 7 | B78: =IFERROR(INDEX(DHHVal,$E78,MATCH(CookFuel&"_share",DHHVar,0)),0) -> 1.5772945 | C78: =IFERROR(INDEX(DHHVal,$E78,MATCH("cons_pc_acrent",DHHVar,0)),0) -> 13822.567 | D78: =IF(AND(LEFT($C$69,1)="Y",$A78<=$C$70),1,0) -> 0 | E78: =MATCH(CtryCode&".distn.bsh.dec.ove.mean."&$A78,DHHKey,0) -> 7 | F78: =IFERROR(INDEX(DHHVal,$E78,MATCH("popw",DHHVar,0)),0) -> 10490081
A79: 8 | B79: =IFERROR(INDEX(DHHVal,$E79,MATCH(CookFuel&"_share",DHHVar,0)),0) -> 1.394601 | C79: =IFERROR(INDEX(DHHVal,$E79,MATCH("cons_pc_acrent",DHHVar,0)),0) -> 15870.829 | D79: =IF(AND(LEFT($C$69,1)="Y",$A79<=$C$70),1,0) -> 0 | E79: =MATCH(CtryCode&".distn.bsh.dec.ove.mean."&$A79,DHHKey,0) -> 8 | F79: =IFERROR(INDEX(DHHVal,$E79,MATCH("popw",DHHVar,0)),0) -> 10973133
A80: 9 | B80: =IFERROR(INDEX(DHHVal,$E80,MATCH(CookFuel&"_share",DHHVar,0)),0) -> 1.2187101 | C80: =IFERROR(INDEX(DHHVal,$E80,MATCH("cons_pc_acrent",DHHVar,0)),0) -> 18901.246 | D80: =IF(AND(LEFT($C$69,1)="Y",$A80<=$C$70),1,0) -> 0 | E80: =MATCH(CtryCode&".distn.bsh.dec.ove.mean."&$A80,DHHKey,0) -> 9 | F80: =IFERROR(INDEX(DHHVal,$E80,MATCH("popw",DHHVar,0)),0) -> 10076191
A81: 10 | B81: =IFERROR(INDEX(DHHVal,$E81,MATCH(CookFuel&"_share",DHHVar,0)),0) -> 1.0422258 | C81: =IFERROR(INDEX(DHHVal,$E81,MATCH("cons_pc_acrent",DHHVar,0)),0) -> 26289.388 | D81: =IF(AND(LEFT($C$69,1)="Y",$A81<=$C$70),1,0) -> 0 | E81: =MATCH(CtryCode&".distn.bsh.dec.ove.mean."&$A81,DHHKey,0) -> 10 | F81: =IFERROR(INDEX(DHHVal,$E81,MATCH("popw",DHHVar,0)),0) -> 9724646.7
A82: Basket | B82: =IFERROR(INDEX(DHHVal,$E82,MATCH(CookFuel&"_share",DHHVar,0)),0) -> 1.8104895 | C82: =IFERROR(INDEX(DHHVal,$E82,MATCH("cons_pc_acrent",DHHVar,0)),0) -> 12360.821 | D82: =OR(CookFuel={"nga","lpg","ker"})*1 -> 1 | E82: =MATCH(CtryCode&".distn.bsh.bkt.ove.mean."&BasketQ,DHHKey,0) -> 11 | F82: =IFERROR(INDEX(DHHVal,$E82,MATCH("popw",DHHVar,0)),0) -> 1.1144465e+08
B83: Share of the most-used cooking fuel initially exempt (ExemptCookShare): spend of the exempt deciles / economy-wide spend of the basket row 82 (v0.9.0, R6.3, I136, as legacy K1795); 0 unless the fuel is gas, LPG or kerosene | C83: =IFERROR(SUMPRODUCT(B72:B81,C72:C81,F72:F81,D72:D81)/(B82*C82*F82)*D82,0) -> 0
B85: Manual inputs (v0.9.0, R8): domestic prices, elasticities (MTInputs DomPrTax, ElIncMainSrc, ElPrcMainSrc, scenario 1)
B86: Manual domestic prices in use (1 / 0; DomPrTax = Yes; ManPrOn; Manual inputs G59:N146, legacy rows 765-829) | C86: =IF(LEFT(INDEX(SDBase,MATCH("DomPrTax",SDParam,0)),1)="Y",1,0) -> 0
B87: Manual income elasticities (1 / 0; ElIncMainSrc = Manual; ElIncMan; Manual inputs K279:N286) | C87: =IF(INDEX(SDBase,MATCH("ElIncMainSrc",SDParam,0))="Manual",1,0) -> 0
B88: Manual price elasticities (1 / 0; ElPrcMainSrc = Manual; ElPrcMan; Manual inputs K291:N307, L319:L321) | C88: =IF(INDEX(SDBase,MATCH("ElPrcMainSrc",SDParam,0))="Manual",1,0) -> 0
B89: Substitution elasticity biomass / LPG of the leakage (ResBioSubst; Elasticities C131, or Manual inputs L319 if ElPrcMan = 1; blank: #N/A, I140; R8.5) | C89: 0.25
A94: Constants: named constants and policy assumptions without an MTInputs row (looked up by Mitigation)
A95: Rows with a defined name (column A) are used by name in formulas; the other rows are looked up by key = variable|fuel|sector (Mitigation columns A|B|C) or by the key in the row description.
A96: Key / defined name | B96: Value | C96: Unit | D96: Description | E96: Source
A97: ManCapOff | B97: 14 | C97: rows | D97: Manual inputs: rows from the scenario-1 to the other-scenario capacity block (349 -> 363) | E97: legacy Manual inputs rows 349-357, 363-371 (v0.5.6, P3)
A98: CoalICYr | B98: 2030 | C98: year | D98: Year the coal implicit cost reaches its long-term value | E98: legacy K88 (v0.5.6, P5)
A99: MethGJperKtoe | B99: 41868 | C99: GJ per ktoe | D99: Production of fuels for supply methane: GJ per ktoe | E99: legacy rows 6137-6144 (v0.6.0)
A100: MethGJperBbl | B100: 6.1408 | C100: GJ per barrel | D100: Crude oil: GJ per barrel (legacy unit of the oil price) | E100: legacy rows 6137-6144 (v0.6.0)
A101: MethGJperT | B101: 29.3076 | C101: GJ per tonne | D101: Coal: GJ per tonne (legacy unit of the coal price) | E101: legacy rows 6137-6144 (v0.6.0)
A102: MethGJperMMBtu | B102: 1.055056 | C102: GJ per MMBtu | D102: Natural gas: GJ per MMBtu (legacy unit of the gas price) | E102: legacy rows 6137-6144 (v0.6.0)
A103: PwAvgLag | B103: 4 | C103: years | D103: Fuel price for power: trailing average over this year and the 4 before | E103: v0.6.2 (legacy bug L126: legacy rows 3155-3163 average t-2 .. t+2)
A104: LitersPerKtoeOil | B104: 1108792 | C104: liters per ktoe | D104: Crude oil: liters per ktoe (spreads the oil producer subsidy) | E104: legacy _conv_ktoe_liter_oil, Mitigation O953 (v0.6.1, I49)
A105: LitersPerBbl | B105: 158.98729 | C105: liters per barrel | D105: Liters in a barrel (other oil products are priced per barrel) | E105: Definition (v0.6.1, I49; legacy bug L125)
A106: NDCYrCap | B106: 2035 | C106: year | D106: Latest NDC target year used (later targets are compared in this year) | E106: legacy Mitigation F18405 (v0.5.7)
A107: HoursYr | B107: 8760 | C107: hours per year | D107: Hours in a year | E107: Definition
A108: kWperMW | B108: 1000 | C108: kW per MW | D108: Kilowatts per megawatt | E108: Definition
...

Sheet DATA_DISTN->>
A2: Distribution data: the data tabs of legacy CPAT used by the distribution module (DATA_DISTN)
A3: The tabs of this group (following this divider). In legacy CPAT: Yes = the same tab, Partly = a tab with part of this content, No = new in this workbook.
A5: Tab | B5: Content | C5: In legacy CPAT | D5: Legacy tab
A6: DistMapping | B6: Recycling choices, IO fuel groups, Gini weights, input-output tables of the country (formulas), GDP deflator of all countries (bottom) | C6: Partly | D6: Mapping (position); legacy Distribution rows 184-210, C.I, C.IX; WEO NGDP_D rows
A7: IO_GTAP | B7: GTAP input-output data by series and sector (legacy table unchanged) | C7: Yes | D7: IO_GTAP (same layout)
A8: HHSurvey | B8: Household budget survey by decile, sample and statistic (legacy table unchanged) | C8: Yes | D8: HHSurvey (same layout)
A9: HH_Elast | B9: Own-price elasticities by decile, all countries (legacy table unchanged) | C9: Yes | D9: HH_Elast (same layout)
A10: ASPIRE | B10: Social protection benefits by quintile (legacy table unchanged) | C10: Yes | D10: ASPIRE (same layout)
A11: WHOCooking | B11: Main cooking fuel and its share (legacy table unchanged) | C11: Yes | D11: WHOCooking (same layout)
A12: GDPRatios | B12: WDI ratios to GDP, all countries (legacy table unchanged; key column right) | C12: Yes | D12: GDPRatios (same layout)

Sheet DistMapping
A1: Source: legacy Distribution rows 184-210 (choices), C.I (fuel groups, input-output tables of the selected country), C.IX (Lorenz fit); legacy WEO (GDP deflator, bottom); extract_distn.py
A2: DistMapping - recycling choices, IO fuel groups, Gini weights, input-output tables, GDP deflator
A3: key | B3: kind | C3: label | D3: code
A4: infra|All Infr. | B4: infra | C4: All Infr. | D4: all_acs_share
A5: infra|ICT Infr. | B5: infra | C5: ICT Infr. | D5: ICT_acs_share
A6: infra|Electricity Infr. | B6: infra | C6: Electricity Infr. | D6: ely_acs_share
A7: infra|Water Infr. | B7: infra | C7: Water Infr. | D7: wtr_acs_share
A8: infra|Sanitation Infr. | B8: infra | C8: Sanitation Infr. | D8: sani_acs_share
A9: infra|Public Transport Infr. | B9: infra | C9: Public Transport Infr. | D9: transp_pub_acs_share
A10: aspire|Active Labor Market | B10: aspire | C10: Active Labor Market | D10: per_lm_ac.avt_q
A11: aspire|All Labor Market | B11: aspire | C11: All Labor Market | D11: per_lm_alllm.avt_q
A12: aspire|All Social Assistance | B12: aspire | C12: All Social Assistance | D12: per_sa_allsa.avt_q
A13: aspire|All Social Insurance | B13: aspire | C13: All Social Insurance | D13: per_si_allsi.avt_q
A14: aspire|All Social Protection and Labor | B14: aspire | C14: All Social Protection and Labor | D14: per_allsp.avt_q
... A25: aspire|Social Pensions | B25: aspire | C25: Social Pensions | D25: per_sa_sp.avt_q
A27: IO fuel groups
A28: coa | B28: Coal
A29: ely | B29: Electricity
A30: nga | B30: Natural gas
A31: oil | B31: Crude and other oil
A32: p_c | B32: Refined products (gasoline, diesel, LPG, kerosene)
A34: Gini weights W_d by decile (legacy LINEST fit L = a x^2 + b x: Gini = 1 - sum of decile consumption shares x W_d)
B35: 1 | C35: 2 | D35: 3 | E35: 4 | F35: 5 | G35: 6 | H35: 7 | I35: 8 | J35: 9 | K35: 10
A36: DGiniW | B36: 1.7871486 | C36: 1.7090179 | D36: 1.5679688 | E36: 1.3792138 | F36: 1.1579652 | G36: 0.91943532 | H36: 0.67883656 | I36: 0.45138128 | J36: 0.25228185 | K36: 0.096750639
A38: Input-output data of the selected country (IO_GTAP; USD m, GTAP year) by GTAP sector
A39: Sector | B39: afs | C39: atp | D39: b_t | E39: bph | F39: c_b | G39: chm | H39: cmn | I39: cmt | J39: cns | K39: coa | L39: ctl | M39: dwe | N39: edu | O39: eeq | P39: ele | Q39: ely | R39: fmp | S39: frs | T39: fsh | U39: gro | V39: hht | W39: i_s | X39: ins | Y39: lea | Z39: lum | AA39: mil | AB39: mvh | AC39: nfm | AD39: nga | AE39: nmm | AF39: oap | AG39: obs | AH39: ocr | AI39: ofd | AJ39: ofi | AK39: oil | AL39: ome | AM39: omf | AN39: omt | AO39: osd | AP39: osg | AQ39: otn | AR39: otp | AS39: oxt | AT39: p_c | AU39: pcr | AV39: pdr | AW39: pfb | AX39: ppp | AY39: rmk | AZ39: ros | BA39: rpp | BB39: rsa | BC39: sgr | BD39: tex | BE39: trd | BF39: v_f | BG39: vol | BH39: wap | BI39: whs | BJ39: wht | BK39: wol | BL39: wtp | BM39: wtr
A40: Category (legacy rows 668-736) | B40: ret | C40: tpu | D40: food | E40: pha | F40: food | G40: che | H40: com | I40: food | J40: hou | K40: coa | L40: food | M40: hou | N40: edu | O40: app | P40: app | Q40: ely | R40: app | S40: hou | T40: food | U40: food | V40: hea | W40: hou | X40: oth | Y40: clo | Z40: pap | AA40: food | AB40: teq | AC40: app | AD40: nga | AE40: hou | AF40: food | AG40: oth | AH40: food | AI40: food | AJ40: oth | AK40: oil | AL40: app | AM40: hou | AN40: food | AO40: food | AP40: oth | AQ40: teq | AR40: tpu | AS40: app | AT40: p_c | AU40: food | AV40: food | AW40: food | AX40: pap | AY40: food | AZ40: ret | BA40: che | BB40: oth | BC40: food | BD40: clo | BE40: teq | BF40: food | BG40: food | BH40: clo | BI40: tpu | BJ40: food | BK40: clo | BL40: tpu | BM40: hou
A41: totd | B41: =INDEX(DIOVal,MATCH(LOWER(CtryCode)&"."&$A41,DIOKey,0),MATCH(B$39,DIOSec,0)) -> 10334.473 | C41: =INDEX(DIOVal,MATCH(LOWER(CtryCode)&"."&$A41,DIOKey,0),MATCH(C$39,DIOSec,0)) -> 1604.4644 | D41: =INDEX(DIOVal,MATCH(LOWER(CtryCode)&"."&$A41,DIOKey,0),MATCH(D$39,DIOSec,0)) -> 11183.141 | E41: =INDEX(DIOVal,MATCH(LOWER(CtryCode)&"."&$A41,DIOKey,0),MATCH(E$39,DIOSec,0)) -> 1525.6101 | F41: =INDEX(DIOVal,MATCH(LOWER(CtryCode)&"."&$A41,DIOKey,0),MATCH(F$39,DIOSec,0)) -> 1293.527 | G41: =INDEX(DIOVal,MATCH(LOWER(CtryCode)&"."&$A41,DIOKey,0),MATCH(G$39,DIOSec,0)) -> 3870.5221 | H41: =INDEX(DIOVal,MATCH(LOWER(CtryCode)&"."&$A41,DIOKey,0),MATCH(H$39,DIOSec,0)) -> 21649.418 | I41: =INDEX(DIOVal,MATCH(LOWER(CtryCode)&"."&$A41,DIOKey,0),MATCH(I$39,DIOSec,0)) -> 2404.5401 | ... BM41: =INDEX(DIOVal,MATCH(LOWER(CtryCode)&"."&$A41,DIOKey,0),MATCH(BM$39,DIOSec,0)) -> 1247.661
A42: exports | B42: =INDEX(DIOVal,MATCH(LOWER(CtryCode)&"."&$A42,DIOKey,0),MATCH(B$39,DIOSec,0)) -> 296.27189 | C42: =INDEX(DIOVal,MATCH(LOWER(CtryCode)&"."&$A42,DIOKey,0),MATCH(C$39,DIOSec,0)) -> 1457.2674 | D42: =INDEX(DIOVal,MATCH(LOWER(CtryCode)&"."&$A42,DIOKey,0),MATCH(D$39,DIOSec,0)) -> 284.05083 | E42: =INDEX(DIOVal,MATCH(LOWER(CtryCode)&"."&$A42,DIOKey,0),MATCH(E$39,DIOSec,0)) -> 413.7084 | F42: =INDEX(DIOVal,MATCH(LOWER(CtryCode)&"."&$A42,DIOKey,0),MATCH(F$39,DIOSec,0)) -> 7.2264121 | G42: =INDEX(DIOVal,MATCH(LOWER(CtryCode)&"."&$A42,DIOKey,0),MATCH(G$39,DIOSec,0)) -> 3762.3775 | H42: =INDEX(DIOVal,MATCH(LOWER(CtryCode)&"."&$A42,DIOKey,0),MATCH(H$39,DIOSec,0)) -> 1433.8865 | I42: =INDEX(DIOVal,MATCH(LOWER(CtryCode)&"."&$A42,DIOKey,0),MATCH(I$39,DIOSec,0)) -> 68.742577 | ... BM42: =INDEX(DIOVal,MATCH(LOWER(CtryCode)&"."&$A42,DIOKey,0),MATCH(BM$39,DIOSec,0)) -> 25.892218
A43: hhd | B43: =INDEX(DIOVal,MATCH(LOWER(CtryCode)&"."&$A43,DIOKey,0),MATCH(B$39,DIOSec,0)) -> 10287.596 | C43: =INDEX(DIOVal,MATCH(LOWER(CtryCode)&"."&$A43,DIOKey,0),MATCH(C$39,DIOSec,0)) -> 1403.0977 | D43: =INDEX(DIOVal,MATCH(LOWER(CtryCode)&"."&$A43,DIOKey,0),MATCH(D$39,DIOSec,0)) -> 11181.21 | E43: =INDEX(DIOVal,MATCH(LOWER(CtryCode)&"."&$A43,DIOKey,0),MATCH(E$39,DIOSec,0)) -> 1472.6394 | F43: =INDEX(DIOVal,MATCH(LOWER(CtryCode)&"."&$A43,DIOKey,0),MATCH(F$39,DIOSec,0)) -> 1287.6824 | G43: =INDEX(DIOVal,MATCH(LOWER(CtryCode)&"."&$A43,DIOKey,0),MATCH(G$39,DIOSec,0)) -> 3587.9498 | H43: =INDEX(DIOVal,MATCH(LOWER(CtryCode)&"."&$A43,DIOKey,0),MATCH(H$39,DIOSec,0)) -> 19221.393 | I43: =INDEX(DIOVal,MATCH(LOWER(CtryCode)&"."&$A43,DIOKey,0),MATCH(I$39,DIOSec,0)) -> 2385.9941 | ... BM43: =INDEX(DIOVal,MATCH(LOWER(CtryCode)&"."&$A43,DIOKey,0),MATCH(BM$39,DIOSec,0)) -> 956.77678
A44: coa.leontiefs | B44: =INDEX(DIOVal,MATCH(LOWER(CtryCode)&"."&$A44,DIOKey,0),MATCH(B$39,DIOSec,0)) -> 0.00071293776 | C44: =INDEX(DIOVal,MATCH(LOWER(CtryCode)&"."&$A44,DIOKey,0),MATCH(C$39,DIOSec,0)) -> 0.0040886057 | D44: =INDEX(DIOVal,MATCH(LOWER(CtryCode)&"."&$A44,DIOKey,0),MATCH(D$39,DIOSec,0)) -> 0.0015429125 | E44: =INDEX(DIOVal,MATCH(LOWER(CtryCode)&"."&$A44,DIOKey,0),MATCH(E$39,DIOSec,0)) -> 0.0023684092 | F44: =INDEX(DIOVal,MATCH(LOWER(CtryCode)&"."&$A44,DIOKey,0),MATCH(F$39,DIOSec,0)) -> 0.0010255824 | G44: =INDEX(DIOVal,MATCH(LOWER(CtryCode)&"."&$A44,DIOKey,0),MATCH(G$39,DIOSec,0)) -> 0.005287378 | H44: =INDEX(DIOVal,MATCH(LOWER(CtryCode)&"."&$A44,DIOKey,0),MATCH(H$39,DIOSec,0)) -> 0.00076123581 | I44: =INDEX(DIOVal,MATCH(LOWER(CtryCode)&"."&$A44,DIOKey,0),MATCH(I$39,DIOSec,0)) -> 0.00030083199 | ... BM44: =INDEX(DIOVal,MATCH(LOWER(CtryCode)&"."&$A44,DIOKey,0),MATCH(BM$39,DIOSec,0)) -> 0.0038588635
A45: ely.leontiefs | B45: =INDEX(DIOVal,MATCH(LOWER(CtryCode)&"."&$A45,DIOKey,0),MATCH(B$39,DIOSec,0)) -> 0.0051899006 | C45: =INDEX(DIOVal,MATCH(LOWER(CtryCode)&"."&$A45,DIOKey,0),MATCH(C$39,DIOSec,0)) -> 0.0024449047 | D45: =INDEX(DIOVal,MATCH(LOWER(CtryCode)&"."&$A45,DIOKey,0),MATCH(D$39,DIOSec,0)) -> 0.0017552918 | E45: =INDEX(DIOVal,MATCH(LOWER(CtryCode)&"."&$A45,DIOKey,0),MATCH(E$39,DIOSec,0)) -> 0.0035076868 | F45: =INDEX(DIOVal,MATCH(LOWER(CtryCode)&"."&$A45,DIOKey,0),MATCH(F$39,DIOSec,0)) -> 0.002020499 | G45: =INDEX(DIOVal,MATCH(LOWER(CtryCode)&"."&$A45,DIOKey,0),MATCH(G$39,DIOSec,0)) -> 0.0106773 | H45: =INDEX(DIOVal,MATCH(LOWER(CtryCode)&"."&$A45,DIOKey,0),MATCH(H$39,DIOSec,0)) -> 0.0014849727 | I45: =INDEX(DIOVal,MATCH(LOWER(CtryCode)&"."&$A45,DIOKey,0),MATCH(I$39,DIOSec,0)) -> 0.0015267666 | ... BM45: =INDEX(DIOVal,MATCH(LOWER(CtryCode)&"."&$A45,DIOKey,0),MATCH(BM$39,DIOSec,0)) -> 0.013165722
A46: nga.leontiefs | B46: =INDEX(DIOVal,MATCH(LOWER(CtryCode)&"."&$A46,DIOKey,0),MATCH(B$39,DIOSec,0)) -> 0.0028174112 | C46: =INDEX(DIOVal,MATCH(LOWER(CtryCode)&"."&$A46,DIOKey,0),MATCH(C$39,DIOSec,0)) -> 0.0098443475 | D46: =INDEX(DIOVal,MATCH(LOWER(CtryCode)&"."&$A46,DIOKey,0),MATCH(D$39,DIOSec,0)) -> 0.0022552544 | E46: =INDEX(DIOVal,MATCH(LOWER(CtryCode)&"."&$A46,DIOKey,0),MATCH(E$39,DIOSec,0)) -> 0.020527135 | F46: =INDEX(DIOVal,MATCH(LOWER(CtryCode)&"."&$A46,DIOKey,0),MATCH(F$39,DIOSec,0)) -> 0.0033915006 | G46: =INDEX(DIOVal,MATCH(LOWER(CtryCode)&"."&$A46,DIOKey,0),MATCH(G$39,DIOSec,0)) -> 0.036056683 | H46: =INDEX(DIOVal,MATCH(LOWER(CtryCode)&"."&$A46,DIOKey,0),MATCH(H$39,DIOSec,0)) -> 0.0013438412 | I46: =INDEX(DIOVal,MATCH(LOWER(CtryCode)&"."&$A46,DIOKey,0),MATCH(I$39,DIOSec,0)) -> 0.0012866749 | ... BM46: =INDEX(DIOVal,MATCH(LOWER(CtryCode)&"."&$A46,DIOKey,0),MATCH(BM$39,DIOSec,0)) -> 0.0087122558
A47: oil.leontiefs | B47: =INDEX(DIOVal,MATCH(LOWER(CtryCode)&"."&$A47,DIOKey,0),MATCH(B$39,DIOSec,0)) -> 0.010716541 | C47: =INDEX(DIOVal,MATCH(LOWER(CtryCode)&"."&$A47,DIOKey,0),MATCH(C$39,DIOSec,0)) -> 0.2196354 | D47: =INDEX(DIOVal,MATCH(LOWER(CtryCode)&"."&$A47,DIOKey,0),MATCH(D$39,DIOSec,0)) -> 0.011477364 | E47: =INDEX(DIOVal,MATCH(LOWER(CtryCode)&"."&$A47,DIOKey,0),MATCH(E$39,DIOSec,0)) -> 0.026425123 | F47: =INDEX(DIOVal,MATCH(LOWER(CtryCode)&"."&$A47,DIOKey,0),MATCH(F$39,DIOSec,0)) -> 0.034986379 | G47: =INDEX(DIOVal,MATCH(LOWER(CtryCode)&"."&$A47,DIOKey,0),MATCH(G$39,DIOSec,0)) -> 0.1376497 | H47: =INDEX(DIOVal,MATCH(LOWER(CtryCode)&"."&$A47,DIOKey,0),MATCH(H$39,DIOSec,0)) -> 0.0077011269 | I47: =INDEX(DIOVal,MATCH(LOWER(CtryCode)&"."&$A47,DIOKey,0),MATCH(I$39,DIOSec,0)) -> 0.0065115891 | ... BM47: =INDEX(DIOVal,MATCH(LOWER(CtryCode)&"."&$A47,DIOKey,0),MATCH(BM$39,DIOSec,0)) -> 0.040217747
A48: p_c.leontiefs | B48: =INDEX(DIOVal,MATCH(LOWER(CtryCode)&"."&$A48,DIOKey,0),MATCH(B$39,DIOSec,0)) -> 0.015123998 | C48: =INDEX(DIOVal,MATCH(LOWER(CtryCode)&"."&$A48,DIOKey,0),MATCH(C$39,DIOSec,0)) -> 0.30610357 | D48: =INDEX(DIOVal,MATCH(LOWER(CtryCode)&"."&$A48,DIOKey,0),MATCH(D$39,DIOSec,0)) -> 0.016911444 | E48: =INDEX(DIOVal,MATCH(LOWER(CtryCode)&"."&$A48,DIOKey,0),MATCH(E$39,DIOSec,0)) -> 0.038789812 | F48: =INDEX(DIOVal,MATCH(LOWER(CtryCode)&"."&$A48,DIOKey,0),MATCH(F$39,DIOSec,0)) -> 0.046877066 | G48: =INDEX(DIOVal,MATCH(LOWER(CtryCode)&"."&$A48,DIOKey,0),MATCH(G$39,DIOSec,0)) -> 0.1952503 | H48: =INDEX(DIOVal,MATCH(LOWER(CtryCode)&"."&$A48,DIOKey,0),MATCH(H$39,DIOSec,0)) -> 0.011338488 | I48: =INDEX(DIOVal,MATCH(LOWER(CtryCode)&"."&$A48,DIOKey,0),MATCH(I$39,DIOSec,0)) -> 0.0089119242 | ... BM48: =INDEX(DIOVal,MATCH(LOWER(CtryCode)&"."&$A48,DIOKey,0),MATCH(BM$39,DIOSec,0)) -> 0.05718286
A49: output | B49: =INDEX(DIOVal,MATCH(LOWER(CtryCode)&"."&$A49,DIOKey,0),MATCH(B$39,DIOSec,0)) -> 11251.681 | C49: =INDEX(DIOVal,MATCH(LOWER(CtryCode)&"."&$A49,DIOKey,0),MATCH(C$39,DIOSec,0)) -> 3638.6478 | D49: =INDEX(DIOVal,MATCH(LOWER(CtryCode)&"."&$A49,DIOKey,0),MATCH(D$39,DIOSec,0)) -> 12265.316 | E49: =INDEX(DIOVal,MATCH(LOWER(CtryCode)&"."&$A49,DIOKey,0),MATCH(E$39,DIOSec,0)) -> 2998.7299 | F49: =INDEX(DIOVal,MATCH(LOWER(CtryCode)&"."&$A49,DIOKey,0),MATCH(F$39,DIOSec,0)) -> 2622.1852 | G49: =INDEX(DIOVal,MATCH(LOWER(CtryCode)&"."&$A49,DIOKey,0),MATCH(G$39,DIOSec,0)) -> 11384.1 | H49: =INDEX(DIOVal,MATCH(LOWER(CtryCode)&"."&$A49,DIOKey,0),MATCH(H$39,DIOSec,0)) -> 26373.824 | I49: =INDEX(DIOVal,MATCH(LOWER(CtryCode)&"."&$A49,DIOKey,0),MATCH(I$39,DIOSec,0)) -> 3204.9236 | ... BM49: =INDEX(DIOVal,MATCH(LOWER(CtryCode)&"."&$A49,DIOKey,0),MATCH(BM$39,DIOSec,0)) -> 3724.0157
A50: Fuel sector (1: embedded use is 0) | B50: =IF(ISNUMBER(MATCH(B$40,DGroupKey,0)),1,0) -> 0 | C50: =IF(ISNUMBER(MATCH(C$40,DGroupKey,0)),1,0) -> 0 | D50: =IF(ISNUMBER(MATCH(D$40,DGroupKey,0)),1,0) -> 0 | E50: =IF(ISNUMBER(MATCH(E$40,DGroupKey,0)),1,0) -> 0 | F50: =IF(ISNUMBER(MATCH(F$40,DGroupKey,0)),1,0) -> 0 | G50: =IF(ISNUMBER(MATCH(G$40,DGroupKey,0)),1,0) -> 0 | H50: =IF(ISNUMBER(MATCH(H$40,DGroupKey,0)),1,0) -> 0 | I50: =IF(ISNUMBER(MATCH(I$40,DGroupKey,0)),1,0) -> 0 | ... BM50: =IF(ISNUMBER(MATCH(BM$40,DGroupKey,0)),1,0) -> 0
A51: Demand + exports, non-fuel sectors | B51: =(B41+B42)*(1-B50) -> 10630.745 | C51: =(C41+C42)*(1-C50) -> 3061.7318 | D51: =(D41+D42)*(1-D50) -> 11467.192 | E51: =(E41+E42)*(1-E50) -> 1939.3185 | F51: =(F41+F42)*(1-F50) -> 1300.7535 | G51: =(G41+G42)*(1-G50) -> 7632.8996 | H51: =(H41+H42)*(1-H50) -> 23083.304 | I51: =(I41+I42)*(1-I50) -> 2473.2827 | ... BM51: =(BM41+BM42)*(1-BM50) -> 1273.5532
A52: Household demand x Leontief coa | B52: =B43*B44 -> 7.3344159 | C52: =C43*C44 -> 5.7367131 | D52: =D43*D44 -> 17.251629 | E52: =E43*E44 -> 3.4878126 | F52: =F43*F44 -> 1.3206244 | G52: =G43*G44 -> 18.970847 | H52: =H43*H44 -> 14.632013 | I52: =I43*I44 -> 0.71778336 | ... BM52: =BM43*BM44 -> 3.692071
A53: Household demand x Leontief ely | B53: =B43*B45 -> 53.391602 | C53: =C43*C45 -> 3.4304401 | D53: =D43*D45 -> 19.626286 | E53: =E43*E45 -> 5.1655578 | F53: =F43*F45 -> 2.601761 | G53: =G43*G45 -> 38.309615 | H53: =H43*H45 -> 28.543243 | I53: =I43*I45 -> 3.6428562 | ... BM53: =BM43*BM45 -> 12.596657
A54: Household demand x Leontief nga | B54: =B43*B46 -> 28.984389 | C54: =C43*C46 -> 13.812581 | D54: =D43*D46 -> 25.216474 | E54: =E43*E46 -> 30.229068 | F54: =F43*F46 -> 4.3671755 | G54: =G43*G46 -> 129.36957 | H54: =H43*H46 -> 25.8305 | I54: =I43*I46 -> 3.0699987 | ... BM54: =BM43*BM46 -> 8.3356841
A55: Household demand x Leontief oil | B55: =B43*B47 -> 110.24744 | C55: =C43*C47 -> 308.16992 | D55: =D43*D47 -> 128.33082 | E55: =E43*E47 -> 38.914678 | F55: =F43*F47 -> 45.051344 | G55: =G43*G47 -> 493.88022 | H55: =H43*H47 -> 148.02639 | I55: =I43*I47 -> 15.536613 | ... BM55: =BM43*BM47 -> 38.479407
A56: Household demand x Leontief p_c | B56: =B43*B48 -> 155.58959 | C56: =C43*C48 -> 429.4932 | D56: =D43*D48 -> 189.09041 | E56: =E43*E48 -> 57.123405 | F56: =F43*F48 -> 60.362773 | G56: =G43*G48 -> 700.54829 | H56: =H43*H48 -> 217.94154 | I56: =I43*I48 -> 21.263799 | ... BM56: =BM43*BM48 -> 54.711233
A58: Deflator ratio (ResultsYear / GTAP year) | B58: =INDEX(DIOVal,MATCH(LOWER(CtryCode)&".hhd",DIOKey,0),MATCH("year",DIOSec,0)) -> 2014 | C58: =INDEX(DDeflVal,MATCH(CtryCode&".NGDP_D.A",DDeflKey,0),MATCH('Constants and Mappings'!$C$8,DDeflYear,0)) -> 234.71832 | D58: =INDEX(DDeflVal,MATCH(CtryCode&".NGDP_D.A",DDeflKey,0),MATCH($B58,DDeflYear,0)) -> 41.125541 | E58: =$C58/$D58 -> 5.7073614 | F58: B: GTAP year; C, D: GDP deflator of ResultsYear and of the GTAP year; E: ratio
A60: Total use of each fuel group (USD m, ref-year prices: embedded + own demand x deflator ratio; legacy rows 588-600)
A61: coa | B61: =$E$58*(SUMPRODUCT($B$51:$BM$51,$B$44:$BM$44)+INDEX($B$41:$BM$41,MATCH($A61,$B$39:$BM$39,0))) -> 4536.891
A62: ely | B62: =$E$58*(SUMPRODUCT($B$51:$BM$51,$B$45:$BM$45)+INDEX($B$41:$BM$41,MATCH($A62,$B$39:$BM$39,0))) -> 33447.728
A63: nga | B63: =$E$58*(SUMPRODUCT($B$51:$BM$51,$B$46:$BM$46)+INDEX($B$41:$BM$41,MATCH($A63,$B$39:$BM$39,0))) -> 11798.434
A64: oil | B64: =$E$58*(SUMPRODUCT($B$51:$BM$51,$B$47:$BM$47)+INDEX($B$41:$BM$41,MATCH($A64,$B$39:$BM$39,0))) -> 74758.308
A65: p_c | B65: =$E$58*(SUMPRODUCT($B$51:$BM$51,$B$48:$BM$48)+INDEX($B$41:$BM$41,MATCH($A65,$B$39:$BM$39,0))) -> 137702.83
A67: Household-demand weighted Leontief coefficients of the consumption categories (legacy rows 668-736)
A68: Category | B68: coa | C68: ely | D68: nga | E68: oil | F68: p_c
A69: app | B69: =SUMIF($B$40:$BM$40,$A69,$B$52:$BM$52)/SUMIF($B$40:$BM$40,$A69,$B$43:$BM$43) -> 0.0054029191 | C69: =SUMIF($B$40:$BM$40,$A69,$B$53:$BM$53)/SUMIF($B$40:$BM$40,$A69,$B$43:$BM$43) -> 0.010944523 | D69: =SUMIF($B$40:$BM$40,$A69,$B$54:$BM$54)/SUMIF($B$40:$BM$40,$A69,$B$43:$BM$43) -> 0.0096523225 | E69: =SUMIF($B$40:$BM$40,$A69,$B$55:$BM$55)/SUMIF($B$40:$BM$40,$A69,$B$43:$BM$43) -> 0.044482354 | F69: =SUMIF($B$40:$BM$40,$A69,$B$56:$BM$56)/SUMIF($B$40:$BM$40,$A69,$B$43:$BM$43) -> 0.067682984
A70: che | B70: =SUMIF($B$40:$BM$40,$A70,$B$52:$BM$52)/SUMIF($B$40:$BM$40,$A70,$B$43:$BM$43) -> 0.0052821962 | C70: =SUMIF($B$40:$BM$40,$A70,$B$53:$BM$53)/SUMIF($B$40:$BM$40,$A70,$B$43:$BM$43) -> 0.0097601776 | D70: =SUMIF($B$40:$BM$40,$A70,$B$54:$BM$54)/SUMIF($B$40:$BM$40,$A70,$B$43:$BM$43) -> 0.033725409 | E70: =SUMIF($B$40:$BM$40,$A70,$B$55:$BM$55)/SUMIF($B$40:$BM$40,$A70,$B$43:$BM$43) -> 0.11353961 | F70: =SUMIF($B$40:$BM$40,$A70,$B$56:$BM$56)/SUMIF($B$40:$BM$40,$A70,$B$43:$BM$43) -> 0.16223424
A71: clo | B71: =SUMIF($B$40:$BM$40,$A71,$B$52:$BM$52)/SUMIF($B$40:$BM$40,$A71,$B$43:$BM$43) -> 0.0018926847 | C71: =SUMIF($B$40:$BM$40,$A71,$B$53:$BM$53)/SUMIF($B$40:$BM$40,$A71,$B$43:$BM$43) -> 0.00293912 | D71: =SUMIF($B$40:$BM$40,$A71,$B$54:$BM$54)/SUMIF($B$40:$BM$40,$A71,$B$43:$BM$43) -> 0.00394937 | E71: =SUMIF($B$40:$BM$40,$A71,$B$55:$BM$55)/SUMIF($B$40:$BM$40,$A71,$B$43:$BM$43) -> 0.021579895 | F71: =SUMIF($B$40:$BM$40,$A71,$B$56:$BM$56)/SUMIF($B$40:$BM$40,$A71,$B$43:$BM$43) -> 0.0315108
A72: com | B72: =SUMIF($B$40:$BM$40,$A72,$B$52:$BM$52)/SUMIF($B$40:$BM$40,$A72,$B$43:$BM$43) -> 0.00076123581 | C72: =SUMIF($B$40:$BM$40,$A72,$B$53:$BM$53)/SUMIF($B$40:$BM$40,$A72,$B$43:$BM$43) -> 0.0014849727 | D72: =SUMIF($B$40:$BM$40,$A72,$B$54:$BM$54)/SUMIF($B$40:$BM$40,$A72,$B$43:$BM$43) -> 0.0013438412 | E72: =SUMIF($B$40:$BM$40,$A72,$B$55:$BM$55)/SUMIF($B$40:$BM$40,$A72,$B$43:$BM$43) -> 0.0077011269 | F72: =SUMIF($B$40:$BM$40,$A72,$B$56:$BM$56)/SUMIF($B$40:$BM$40,$A72,$B$43:$BM$43) -> 0.011338488
A73: edu | B73: =SUMIF($B$40:$BM$40,$A73,$B$52:$BM$52)/SUMIF($B$40:$BM$40,$A73,$B$43:$BM$43) -> 0.0010438748 | C73: =SUMIF($B$40:$BM$40,$A73,$B$53:$BM$53)/SUMIF($B$40:$BM$40,$A73,$B$43:$BM$43) -> 0.0058187357 | D73: =SUMIF($B$40:$BM$40,$A73,$B$54:$BM$54)/SUMIF($B$40:$BM$40,$A73,$B$43:$BM$43) -> 0.0036944388 | E73: =SUMIF($B$40:$BM$40,$A73,$B$55:$BM$55)/SUMIF($B$40:$BM$40,$A73,$B$43:$BM$43) -> 0.015895705 | F73: =SUMIF($B$40:$BM$40,$A73,$B$56:$BM$56)/SUMIF($B$40:$BM$40,$A73,$B$43:$BM$43) -> 0.022661792
A74: food | B74: =SUMIF($B$40:$BM$40,$A74,$B$52:$BM$52)/SUMIF($B$40:$BM$40,$A74,$B$43:$BM$43) -> 0.0013238571 | C74: =SUMIF($B$40:$BM$40,$A74,$B$53:$BM$53)/SUMIF($B$40:$BM$40,$A74,$B$43:$BM$43) -> 0.0023334079 | D74: =SUMIF($B$40:$BM$40,$A74,$B$54:$BM$54)/SUMIF($B$40:$BM$40,$A74,$B$43:$BM$43) -> 0.0033790384 | E74: =SUMIF($B$40:$BM$40,$A74,$B$55:$BM$55)/SUMIF($B$40:$BM$40,$A74,$B$43:$BM$43) -> 0.025531889 | F74: =SUMIF($B$40:$BM$40,$A74,$B$56:$BM$56)/SUMIF($B$40:$BM$40,$A74,$B$43:$BM$43) -> 0.03637329
A75: hea | B75: =SUMIF($B$40:$BM$40,$A75,$B$52:$BM$52)/SUMIF($B$40:$BM$40,$A75,$B$43:$BM$43) -> 0.0018874857 | C75: =SUMIF($B$40:$BM$40,$A75,$B$53:$BM$53)/SUMIF($B$40:$BM$40,$A75,$B$43:$BM$43) -> 0.0044259418 | D75: =SUMIF($B$40:$BM$40,$A75,$B$54:$BM$54)/SUMIF($B$40:$BM$40,$A75,$B$43:$BM$43) -> 0.0049420267 | E75: =SUMIF($B$40:$BM$40,$A75,$B$55:$BM$55)/SUMIF($B$40:$BM$40,$A75,$B$43:$BM$43) -> 0.020772998 | F75: =SUMIF($B$40:$BM$40,$A75,$B$56:$BM$56)/SUMIF($B$40:$BM$40,$A75,$B$43:$BM$43) -> 0.029950238
A76: hou | B76: =SUMIF($B$40:$BM$40,$A76,$B$52:$BM$52)/SUMIF($B$40:$BM$40,$A76,$B$43:$BM$43) -> 0.001623246 | C76: =SUMIF($B$40:$BM$40,$A76,$B$53:$BM$53)/SUMIF($B$40:$BM$40,$A76,$B$43:$BM$43) -> 0.0027924653 | D76: =SUMIF($B$40:$BM$40,$A76,$B$54:$BM$54)/SUMIF($B$40:$BM$40,$A76,$B$43:$BM$43) -> 0.0034704009 | E76: =SUMIF($B$40:$BM$40,$A76,$B$55:$BM$55)/SUMIF($B$40:$BM$40,$A76,$B$43:$BM$43) -> 0.01708751 | F76: =SUMIF($B$40:$BM$40,$A76,$B$56:$BM$56)/SUMIF($B$40:$BM$40,$A76,$B$43:$BM$43) -> 0.025446366
A77: oth | B77: =SUMIF($B$40:$BM$40,$A77,$B$52:$BM$52)/SUMIF($B$40:$BM$40,$A77,$B$43:$BM$43) -> 0.00059428197 | C77: =SUMIF($B$40:$BM$40,$A77,$B$53:$BM$53)/SUMIF($B$40:$BM$40,$A77,$B$43:$BM$43) -> 0.0022075202 | D77: =SUMIF($B$40:$BM$40,$A77,$B$54:$BM$54)/SUMIF($B$40:$BM$40,$A77,$B$43:$BM$43) -> 0.0014625411 | E77: =SUMIF($B$40:$BM$40,$A77,$B$55:$BM$55)/SUMIF($B$40:$BM$40,$A77,$B$43:$BM$43) -> 0.0091112601 | F77: =SUMIF($B$40:$BM$40,$A77,$B$56:$BM$56)/SUMIF($B$40:$BM$40,$A77,$B$43:$BM$43) -> 0.013493912
A78: pap | B78: =SUMIF($B$40:$BM$40,$A78,$B$52:$BM$52)/SUMIF($B$40:$BM$40,$A78,$B$43:$BM$43) -> 0.0033861693 | C78: =SUMIF($B$40:$BM$40,$A78,$B$53:$BM$53)/SUMIF($B$40:$BM$40,$A78,$B$43:$BM$43) -> 0.0053940044 | D78: =SUMIF($B$40:$BM$40,$A78,$B$54:$BM$54)/SUMIF($B$40:$BM$40,$A78,$B$43:$BM$43) -> 0.0070600155 | E78: =SUMIF($B$40:$BM$40,$A78,$B$55:$BM$55)/SUMIF($B$40:$BM$40,$A78,$B$43:$BM$43) -> 0.03780909 | F78: =SUMIF($B$40:$BM$40,$A78,$B$56:$BM$56)/SUMIF($B$40:$BM$40,$A78,$B$43:$BM$43) -> 0.056738185
A79: pha | B79: =SUMIF($B$40:$BM$40,$A79,$B$52:$BM$52)/SUMIF($B$40:$BM$40,$A79,$B$43:$BM$43) -> 0.0023684092 | C79: =SUMIF($B$40:$BM$40,$A79,$B$53:$BM$53)/SUMIF($B$40:$BM$40,$A79,$B$43:$BM$43) -> 0.0035076868 | D79: =SUMIF($B$40:$BM$40,$A79,$B$54:$BM$54)/SUMIF($B$40:$BM$40,$A79,$B$43:$BM$43) -> 0.020527135 | E79: =SUMIF($B$40:$BM$40,$A79,$B$55:$BM$55)/SUMIF($B$40:$BM$40,$A79,$B$43:$BM$43) -> 0.026425123 | F79: =SUMIF($B$40:$BM$40,$A79,$B$56:$BM$56)/SUMIF($B$40:$BM$40,$A79,$B$43:$BM$43) -> 0.038789812
A80: ret | B80: =SUMIF($B$40:$BM$40,$A80,$B$52:$BM$52)/SUMIF($B$40:$BM$40,$A80,$B$43:$BM$43) -> 0.00094942346 | C80: =SUMIF($B$40:$BM$40,$A80,$B$53:$BM$53)/SUMIF($B$40:$BM$40,$A80,$B$43:$BM$43) -> 0.0051380348 | D80: =SUMIF($B$40:$BM$40,$A80,$B$54:$BM$54)/SUMIF($B$40:$BM$40,$A80,$B$43:$BM$43) -> 0.0034843297 | E80: =SUMIF($B$40:$BM$40,$A80,$B$55:$BM$55)/SUMIF($B$40:$BM$40,$A80,$B$43:$BM$43) -> 0.013708587 | F80: =SUMIF($B$40:$BM$40,$A80,$B$56:$BM$56)/SUMIF($B$40:$BM$40,$A80,$B$43:$BM$43) -> 0.019922647
... A82: tpu | B82: =SUMIF($B$40:$BM$40,$A82,$B$52:$BM$52)/SUMIF($B$40:$BM$40,$A82,$B$43:$BM$43) -> 0.0030303018 | C82: =SUMIF($B$40:$BM$40,$A82,$B$53:$BM$53)/SUMIF($B$40:$BM$40,$A82,$B$43:$BM$43) -> 0.0027305084 | D82: =SUMIF($B$40:$BM$40,$A82,$B$54:$BM$54)/SUMIF($B$40:$BM$40,$A82,$B$43:$BM$43) -> 0.0072699534 | E82: =SUMIF($B$40:$BM$40,$A82,$B$55:$BM$55)/SUMIF($B$40:$BM$40,$A82,$B$43:$BM$43) -> 0.15589515 | F82: =SUMIF($B$40:$BM$40,$A82,$B$56:$BM$56)/SUMIF($B$40:$BM$40,$A82,$B$43:$BM$43) -> 0.20612157
A84: GTAP sectors (rows; legacy Distribution D.VI): code, name, CPAT sector (data/distn_gtapmap.csv), household demand, exports, output, fuel sector, Leontief coefficients
A85: Sector | B85: Name | C85: CPAT sector | D85: hhd | E85: exports | F85: output | G85: fuel | H85: coa | I85: ely | J85: nga | K85: oil | L85: p_c
A86: afs | B86: Hotels | C86: srv | D86: =B$43 -> 10287.596 | E86: =B$42 -> 296.27189 | F86: =B$49 -> 11251.681 | G86: =B$50 -> 0 | H86: =B$44 -> 0.00071293776 | I86: =B$45 -> 0.0051899006 | J86: =B$46 -> 0.0028174112 | K86: =B$47 -> 0.010716541 | L86: =B$48 -> 0.015123998
A87: atp | B87: Air transport | C87: avi | D87: =C$43 -> 1403.0977 | E87: =C$42 -> 1457.2674 | F87: =C$49 -> 3638.6478 | G87: =C$50 -> 0 | H87: =C$44 -> 0.0040886057 | I87: =C$45 -> 0.0024449047 | J87: =C$46 -> 0.0098443475 | K87: =C$47 -> 0.2196354 | L87: =C$48 -> 0.30610357
A88: b_t | B88: Beverages & Tobacco | C88: foo | D88: =D$43 -> 11181.21 | E88: =D$42 -> 284.05083 | F88: =D$49 -> 12265.316 | G88: =D$50 -> 0 | H88: =D$44 -> 0.0015429125 | I88: =D$45 -> 0.0017552918 | J88: =D$46 -> 0.0022552544 | K88: =D$47 -> 0.011477364 | L88: =D$48 -> 0.016911444
A89: bph | B89: Pharmaceuticals | C89: mch | D89: =E$43 -> 1472.6394 | E89: =E$42 -> 413.7084 | F89: =E$49 -> 2998.7299 | G89: =E$50 -> 0 | H89: =E$44 -> 0.0023684092 | I89: =E$45 -> 0.0035076868 | J89: =E$46 -> 0.020527135 | K89: =E$47 -> 0.026425123 | L89: =E$48 -> 0.038789812
A90: c_b | B90: Cane & Beet | C90: foo | D90: =F$43 -> 1287.6824 | E90: =F$42 -> 7.2264121 | F90: =F$49 -> 2622.1852 | G90: =F$50 -> 0 | H90: =F$44 -> 0.0010255824 | I90: =F$45 -> 0.002020499 | J90: =F$46 -> 0.0033915006 | K90: =F$47 -> 0.034986379 | L90: =F$48 -> 0.046877066
A91: chm | B91: Chemicals | C91: mch | D91: =G$43 -> 3587.9498 | E91: =G$42 -> 3762.3775 | F91: =G$49 -> 11384.1 | G91: =G$50 -> 0 | H91: =G$44 -> 0.005287378 | I91: =G$45 -> 0.0106773 | J91: =G$46 -> 0.036056683 | K91: =G$47 -> 0.1376497 | L91: =G$48 -> 0.1952503
A92: cmn | B92: Telecomms | C92: srv | D92: =H$43 -> 19221.393 | E92: =H$42 -> 1433.8865 | F92: =H$49 -> 26373.824 | G92: =H$50 -> 0 | H92: =H$44 -> 0.00076123581 | I92: =H$45 -> 0.0014849727 | J92: =H$46 -> 0.0013438412 | K92: =H$47 -> 0.0077011269 | L92: =H$48 -> 0.011338488
A93: cmt | B93: Cattle Meat | C93: foo | D93: =I$43 -> 2385.9941 | E93: =I$42 -> 68.742577 | F93: =I$49 -> 3204.9236 | G93: =I$50 -> 0 | H93: =I$44 -> 0.00030083199 | I93: =I$45 -> 0.0015267666 | J93: =I$46 -> 0.0012866749 | K93: =I$47 -> 0.0065115891 | L93: =I$48 -> 0.0089119242
A94: cns | B94: Construction | C94: cst | D94: =J$43 -> 2714.0239 | E94: =J$42 -> 1094.0859 | F94: =J$49 -> 31827.381 | G94: =J$50 -> 0 | H94: =J$44 -> 0.0050366652 | I94: =J$45 -> 0.0045724546 | J94: =J$46 -> 0.006514764 | K94: =J$47 -> 0.033628891 | L94: =J$48 -> 0.05358302
A95: coa | B95: Coal | C95: foo | D95: =K$43 -> 6.6212974e-06 | E95: =K$42 -> 0.22515456 | F95: =K$49 -> 0.35861088 | G95: =K$50 -> 1 | H95: =K$44 -> 1.0461093 | I95: =K$45 -> 0.005488032 | J95: =K$46 -> 0.0058772465 | K95: =K$47 -> 0.038121162 | L95: =K$48 -> 0.055614507
A96: ctl | B96: Cattle | C96: foo | D96: =L$43 -> 1254.3427 | E96: =L$42 -> 9.7881259 | F96: =L$49 -> 1540.5761 | G96: =L$50 -> 0 | H96: =L$44 -> 0.0008754092 | I96: =L$45 -> 0.0018586777 | J96: =L$46 -> 0.0027867048 | K96: =L$47 -> 0.028143213 | L96: =L$48 -> 0.03742626
A97: dwe | B97: Housing rent | C97: srv | D97: =M$43 -> 14564.555 | E97: =M$42 -> 2.8602479e-18 | F97: =M$49 -> 15173.007 | G97: =M$50 -> 0 | H97: =M$44 -> 0.00032878451 | I97: =M$45 -> 0.0003987774 | J97: =M$46 -> 0.00055785463 | K97: =M$47 -> 0.0023724332 | L97: =M$48 -> 0.0036133173
A98: edu | B98: Education | C98: srv | D98: =N$43 -> 4618.192 | E98: =N$42 -> 510.42912 | F98: =N$49 -> 13904.614 | G98: =N$50 -> 0 | H98: =N$44 -> 0.0010438748 | I98: =N$45 -> 0.0058187357 | J98: =N$46 -> 0.0036944388 | K98: =N$47 -> 0.015895705 | L98: =N$48 -> 0.022661792
A99: eeq | B99: Electrical equipment | C99: mac | D99: =O$43 -> 25.197246 | E99: =O$42 -> 1546.3691 | F99: =O$49 -> 1736.8559 | G99: =O$50 -> 0 | H99: =O$44 -> 0.0062566465 | I99: =O$45 -> 0.0081245953 | J99: =O$46 -> 0.0080991921 | K99: =O$47 -> 0.036175723 | L99: =O$48 -> 0.057423271
A100: ele | B100: Computer equipment | C100: mac | D100: =P$43 -> 2621.2423 | E100: =P$42 -> 913.92471 | F100: =P$49 -> 7156.3886 | G100: =P$50 -> 0 | H100: =P$44 -> 0.0038283704 | I100: =P$45 -> 0.011121402 | J100: =P$46 -> 0.0078575836 | K100: =P$47 -> 0.030044833 | L100: =P$48 -> 0.04503134
A101: ely | B101: Electricity supply | C101: pow | D101: =Q$43 -> 4436.9535 | E101: =Q$42 -> 31.46303 | F101: =Q$49 -> 10759.242 | G101: =Q$50 -> 1 | H101: =Q$44 -> 0.0048748951 | I101: =Q$45 -> 0.99546625 | J101: =Q$46 -> 0.3346549 | K101: =Q$47 -> 0.47496993 | L101: =Q$48 -> 0.57686745
A102: fmp | B102: Fabricated metals | C102: mac | D102: =R$43 -> 638.43163 | E102: =R$42 -> 371.48624 | F102: =R$49 -> 7677.8275 | G102: =R$50 -> 0 | H102: =R$44 -> 0.0070818742 | I102: =R$45 -> 0.0067390269 | J102: =R$46 -> 0.011345328 | K102: =R$47 -> 0.050466724 | L102: =R$48 -> 0.079995265
A103: frs | B103: Forestry | C103: foo | D103: =S$43 -> 1.8587657 | E103: =S$42 -> 3.7266751 | F103: =S$49 -> 7.4160858 | G103: =S$50 -> 0 | H103: =S$44 -> 0.0018617365 | I103: =S$45 -> 0.0031751126 | J103: =S$46 -> 0.0031233113 | K103: =S$47 -> 0.041312036 | L103: =S$48 -> 0.05979155
A104: fsh | B104: Fishing | C104: foo | D104: =T$43 -> 3715.4607 | E104: =T$42 -> 109.75854 | F104: =T$49 -> 4995.6821 | G104: =T$50 -> 0 | H104: =T$44 -> 0.00062294927 | I104: =T$45 -> 0.0054874007 | J104: =T$46 -> 0.0031889198 | K104: =T$47 -> 0.021481993 | L104: =T$48 -> 0.028161882
A105: gro | B105: Other grains | C105: foo | D105: =U$43 -> 2245.3185 | E105: =U$42 -> 17.389537 | F105: =U$49 -> 5749.5416 | G105: =U$50 -> 0 | H105: =U$44 -> 0.00085694958 | I105: =U$45 -> 0.0018880788 | J105: =U$46 -> 0.003142747 | K105: =U$47 -> 0.030895442 | L105: =U$48 -> 0.043234725
A106: hht | B106: Human health & social work | C106: srv | D106: =V$43 -> 6187.3029 | E106: =V$42 -> 348.88055 | F106: =V$49 -> 23019.827 | G106: =V$50 -> 0 | H106: =V$44 -> 0.0018874857 | I106: =V$45 -> 0.0044259418 | J106: =V$46 -> 0.0049420267 | K106: =V$47 -> 0.020772998 | L106: =V$48 -> 0.029950238
A107: i_s | B107: Iron & Steel | C107: irn | D107: =W$43 -> 435.15471 | E107: =W$42 -> 918.89426 | F107: =W$49 -> 3363.1654 | G107: =W$50 -> 0 | H107: =W$44 -> 0.0091468307 | I107: =W$45 -> 0.021901742 | J107: =W$46 -> 0.02315565 | K107: =W$47 -> 0.087703373 | L107: =W$48 -> 0.13476849
A108: ins | B108: Insurance | C108: srv | D108: =X$43 -> 4775.9194 | E108: =X$42 -> 262.92697 | F108: =X$49 -> 6044.1936 | G108: =X$50 -> 0 | H108: =X$44 -> 0.00044422122 | I108: =X$45 -> 0.001384736 | J108: =X$46 -> 0.0010571833 | K108: =X$47 -> 0.0090933757 | L108: =X$48 -> 0.013149606
A109: lea | B109: Leather | C109: omn | D109: =Y$43 -> 140.61223 | E109: =Y$42 -> 227.6854 | F109: =Y$49 -> 1452.9146 | G109: =Y$50 -> 0 | H109: =Y$44 -> 0.0025655393 | I109: =Y$45 -> 0.0028095683 | J109: =Y$46 -> 0.0042126651 | K109: =Y$47 -> 0.02292075 | L109: =Y$48 -> 0.036219519
A110: lum | B110: Lumber | C110: foo | D110: =Z$43 -> 4263.2301 | E110: =Z$42 -> 178.95408 | F110: =Z$49 -> 5670.5042 | G110: =Z$50 -> 0 | H110: =Z$44 -> 0.0034932535 | I110: =Z$45 -> 0.0042283706 | J110: =Z$46 -> 0.0057045044 | K110: =Z$47 -> 0.034763749 | L110: =Z$48 -> 0.052494529
A111: mil | B111: Dairy | C111: foo | D111: =AA$43 -> 6020.7335 | E111: =AA$42 -> 475.28574 | F111: =AA$49 -> 8224.249 | G111: =AA$50 -> 0 | H111: =AA$44 -> 0.00069900296 | I111: =AA$45 -> 0.0016657201 | J111: =AA$46 -> 0.0021254598 | K111: =AA$47 -> 0.011373216 | L111: =AA$48 -> 0.016932996
A112: mvh | B112: Motor vehicles | C112: mac | D112: =AB$43 -> 4084.9142 | E112: =AB$42 -> 277.82057 | F112: =AB$49 -> 6465.03 | G112: =AB$50 -> 0 | H112: =AB$44 -> 0.005368925 | I112: =AB$45 -> 0.0061670023 | J112: =AB$46 -> 0.0070654794 | K112: =AB$47 -> 0.031647681 | L112: =AB$48 -> 0.04985246
A113: nfm | B113: Non-Ferrous Metals | C113: nfm | D113: =AC$43 -> 661.19846 | E113: =AC$42 -> 1692.9465 | F113: =AC$49 -> 5802.0599 | G113: =AC$50 -> 0 | H113: =AC$44 -> 0.010544773 | I113: =AC$45 -> 0.013390797 | J113: =AC$46 -> 0.014040655 | K113: =AC$47 -> 0.061171613 | L113: =AC$48 -> 0.10281369
A114: nga | B114: Natural gas | C114: pow | D114: =AD$43 -> 148.85538 | E114: =AD$42 -> 1034.6966 | F114: =AD$49 -> 4854.8623 | G114: =AD$50 -> 1 | H114: =AD$44 -> 0.0018594003 | I114: =AD$45 -> 0.00044616958 | J114: =AD$46 -> 1.0671175 | K114: =AD$47 -> 0.038080443 | L114: =AD$48 -> 0.046312795
A115: nmm | B115: Non-metallic minerals | C115: cem | D115: =AE$43 -> 4144.4997 | E115: =AE$42 -> 1426.5173 | F115: =AE$49 -> 12465.501 | G115: =AE$50 -> 0 | H115: =AE$44 -> 0.0021502812 | I115: =AE$45 -> 0.004706571 | J115: =AE$46 -> 0.007276738 | K115: =AE$47 -> 0.0411401 | L115: =AE$48 -> 0.058405776
A116: oap | B116: Other Animal Products | C116: foo | D116: =AF$43 -> 1410.3758 | E116: =AF$42 -> 42.223835 | F116: =AF$49 -> 1546.2349 | G116: =AF$50 -> 0 | H116: =AF$44 -> 0.00099421207 | I116: =AF$45 -> 0.001930288 | J116: =AF$46 -> 0.0030796279 | K116: =AF$47 -> 0.02903113 | L116: =AF$48 -> 0.040545559
A117: obs | B117: Other Business Services | C117: srv | D117: =AG$43 -> 625.80304 | E117: =AG$42 -> 1426.7389 | F117: =AG$49 -> 10184.889 | G117: =AG$50 -> 0 | H117: =AG$44 -> 0.0010622318 | I117: =AG$45 -> 0.0020638589 | J117: =AG$46 -> 0.0018703103 | K117: =AG$47 -> 0.013760912 | L117: =AG$48 -> 0.020787865
A118: ocr | B118: Other Crops | C118: foo | D118: =AH$43 -> 33.882782 | E118: =AH$42 -> 264.42946 | F118: =AH$49 -> 407.78382 | G118: =AH$50 -> 0 | H118: =AH$44 -> 0.00032408923 | I118: =AH$45 -> 0.00072598309 | J118: =AH$46 -> 0.0010937224 | K118: =AH$47 -> 0.010085771 | L118: =AH$48 -> 0.014751221
...

Sheet IO_GTAP
A1: Source: legacy sheet IO_GTAP, extract_legacy_tables.py. Legacy table unchanged: paste the legacy data rows (all countries) at A4
A2: IO_GTAP - GTAP input-output data by series (rows) and sector (columns), USD m, GTAP year
A3: dis | B3: iso3 | C3: year | D3: sector | E3: afs | F3: atp | G3: b_t | H3: bph | I3: c_b | J3: chm | K3: cmn | L3: cmt | M3: cns | N3: coa | O3: ctl | P3: dwe | Q3: edu | R3: eeq | S3: ele | T3: ely | U3: fmp | V3: frs | W3: fsh | X3: gro | Y3: hht | Z3: i_s | AA3: ins | AB3: lea | AC3: lum | AD3: mil | AE3: mvh | AF3: nfm | AG3: nga | AH3: nmm | AI3: oap | AJ3: obs | AK3: ocr | AL3: ofd | AM3: ofi | AN3: oil | AO3: ome | AP3: omf | AQ3: omt | AR3: osd | AS3: osg | AT3: otn | AU3: otp | AV3: oxt | AW3: p_c | AX3: pcr | AY3: pdr | AZ3: pfb | BA3: ppp | BB3: rmk | BC3: ros | BD3: rpp | BE3: rsa | BF3: sgr | BG3: tex | BH3: trd | BI3: v_f | BJ3: vol | BK3: wap | BL3: whs | BM3: wht | BN3: wol | BO3: wtp | BP3: wtr
A4: egy.domcons | B4: egy | C4: 2014 | D4: DOMCONS | N4: 58.942418 | T4: 6457.4468 | AG4: 4190.7192 | AN4: 13051.853 | AW4: 14681.134
A5: egy.exports | B5: egy | C5: 2014 | D5: Exports | E5: 296.27189 | F5: 1457.2674 | G5: 284.05083 | H5: 413.7084 | I5: 7.2264121 | J5: 3762.3775 | K5: 1433.8865 | L5: 68.742577 | M5: 1094.0859 | N5: 0.22515456 | O5: 9.7881259 | P5: 2.8602479e-18 | Q5: 510.42912 | R5: 1546.3691 | S5: 913.92471 | T5: 31.46303 | U5: 371.48624 | V5: 3.7266751 | W5: 109.75854 | X5: 17.389537 | Y5: 348.88055 | Z5: 918.89426 | AA5: 262.92697 | AB5: 227.6854 | AC5: 178.95408 | AD5: 475.28574 | AE5: 277.82057 | AF5: 1692.9465 | AG5: 1034.6966 | AH5: 1426.5173 | AI5: 42.223835 | AJ5: 1426.7389 | AK5: 264.42946 | AL5: 1862.4077 | AM5: 313.79325 | AN5: 6672.4185 | AO5: 195.62779 | AP5: 359.28264 | AQ5: 18.014632 | AR5: 85.837335 | AS5: 200.53698 | AT5: 51.488781 | AU5: 8063.0606 | AV5: 678.06361 | AW5: 2341.2344 | AX5: 79.68459 | AY5: 7.5990259 | AZ5: 156.82897 | BA5: 685.40819 | BB5: 7.1214344 | BC5: 1139.5659 | BD5: 852.8388 | BE5: 86.690104 | BF5: 372.49981 | BG5: 2097.8001 | BH5: 474.92094 | BI5: 2535.258 | BJ5: 192.31753 | BK5: 3137.7163 | BL5: 848.46913 | BM5: 17.804015 | BN5: 51.982812 | BO5: 215.08573 | BP5: 25.892218
A6: egy.hhd | B6: egy | C6: 2014 | D6: HHD | E6: 10287.596 | F6: 1403.0977 | G6: 11181.21 | H6: 1472.6394 | I6: 1287.6824 | J6: 3587.9498 | K6: 19221.393 | L6: 2385.9941 | M6: 2714.0239 | N6: 6.6212974e-06 | O6: 1254.3427 | P6: 14564.555 | Q6: 4618.192 | R6: 25.197246 | S6: 2621.2423 | T6: 4436.9535 | U6: 638.43163 | V6: 1.8587657 | W6: 3715.4607 | X6: 2245.3185 | Y6: 6187.3029 | Z6: 435.15471 | AA6: 4775.9194 | AB6: 140.61223 | AC6: 4263.2301 | AD6: 6020.7335 | AE6: 4084.9142 | AF6: 661.19846 | AG6: 148.85538 | AH6: 4144.4997 | AI6: 1410.3758 | AJ6: 625.80304 | AK6: 33.882782 | AL6: 19824.221 | AM6: 6924.0289 | AN6: 23.17207 | AO6: 65.319855 | AP6: 240.19232 | AQ6: 1059.291 | AR6: 1294.2561 | AS6: 1858.3682 | AT6: 622.55708 | AU6: 11277.546 | AV6: 220.95012 | AW6: 5525.5745 | AX6: 4325.0985 | AY6: 1342.6172 | AZ6: 1452.5228 | BA6: 1455.9426 | BB6: 1291.573 | BC6: 12627.793 | BD6: 1146.9271 | BE6: 2319.6482 | BF6: 1295.25 | BG6: 8534.4296 | BH6: 15650.207 | BI6: 11488.775 | BJ6: 50.182917 | BK6: 19933.478 | BL6: 2390.7453 | BM6: 3422.2317 | BN6: 11.966721 | BO6: 634.15063 | BP6: 956.77678
A7: egy.imports | B7: egy | C7: 2014 | D7: Imports | E7: 225.61329 | F7: 829.23707 | G7: 837.7744 | H7: 2301.0427 | I7: 23.461761 | J7: 7035.5018 | K7: 777.92462 | L7: 1477.5762 | M7: 378.6803 | N7: 58.800282 | O7: 115.28569 | P7: 2.8602479e-18 | Q7: 1471.3114 | R7: 2822.4417 | S7: 3639.9957 | T7: 14.784192 | U7: 1713.7511 | V7: 32.084459 | W7: 11.087817 | X7: 2000.8771 | Y7: 232.27855 | Z7: 5142.5775 | AA7: 1042.8937 | AB7: 649.08873 | AC7: 1823.7584 | AD7: 890.64634 | AE7: 5490.2455 | AF7: 2469.5864 | AG7: 4.1365608 | AH7: 1181.1967 | AI7: 121.63626 | AJ7: 3157.8458 | AK7: 567.27089 | AL7: 1899.5227 | AM7: 297.01096 | AN7: 1532.0358 | AO7: 5825.3697 | AP7: 1029.9517 | AQ7: 182.85033 | AR7: 1177.5713 | AS7: 176.10306 | AT7: 572.38338 | AU7: 988.46625 | AV7: 798.28199 | AW7: 6990.4434 | AX7: 26.833958 | AY7: 0.52623478 | AZ7: 186.71853 | BA7: 1651.0494 | BB7: 0.95473007 | BC7: 483.11712 | BD7: 2054.656 | BE7: 106.21343 | BF7: 665.69843 | BG7: 3453.1869 | BH7: 415.58942 | BI7: 1062.7491 | BJ7: 2582.34 | BK7: 1562.6764 | BL7: 155.53398 | BM7: 3184.1749 | BN7: 59.801258 | BO7: 72.854988 | BP7: 20.096428
A8: egy.output | B8: egy | C8: 2014 | D8: Output | E8: 11251.681 | F8: 3638.6478 | G8: 12265.316 | H8: 2998.7299 | I8: 2622.1852 | J8: 11384.1 | K8: 26373.824 | L8: 3204.9236 | M8: 31827.381 | N8: 0.35861088 | O8: 1540.5761 | P8: 15173.007 | Q8: 13904.614 | R8: 1736.8559 | S8: 7156.3886 | T8: 10759.242 | U8: 7677.8275 | V8: 7.4160858 | W8: 4995.6821 | X8: 5749.5416 | Y8: 23019.827 | Z8: 3363.1654 | AA8: 6044.1936 | AB8: 1452.9146 | AC8: 5670.5042 | AD8: 8224.249 | AE8: 6465.03 | AF8: 5802.0599 | AG8: 4854.8623 | AH8: 12465.501 | AI8: 1546.2349 | AJ8: 10184.889 | AK8: 407.78382 | AL8: 28583.222 | AM8: 11905.998 | AN8: 18104.194 | AO8: 689.59679 | AP8: 1999.5131 | AQ8: 1581.11 | AR8: 3310.2934 | AS8: 18195.878 | AT8: 1696.2999 | AU8: 22798.544 | AV8: 1202.8006 | AW8: 15290.736 | AX8: 4727.4207 | AY8: 6461.8145 | AZ8: 3961.0679 | BA8: 3318.324 | BB8: 1838.4017 | BC8: 14424.388 | BD8: 3505.4562 | BE8: 4463.3026 | BF8: 2135.3615 | BG8: 24709.356 | BH8: 26943.664 | BI8: 19834.287 | BJ8: 419.97162 | BK8: 26555.437 | BL8: 4387.9112 | BM8: 6070.169 | BN8: 46.669686 | BO8: 2031.7803 | BP8: 3724.0157
A9: egy.totd | B9: egy | C9: 2014 | D9: TOTD | E9: 10334.473 | F9: 1604.4644 | G9: 11183.141 | H9: 1525.6101 | I9: 1293.527 | J9: 3870.5221 | K9: 21649.418 | L9: 2404.5401 | M9: 28321.27 | N9: 6.6212974e-06 | O9: 1264.0684 | P9: 14576.248 | Q9: 10894.775 | R9: 66.503991 | S9: 2969.3719 | T9: 4436.9535 | U9: 2207.0358 | V9: 8.0047941 | W9: 3745.2363 | X9: 2253.9275 | Y9: 21377.289 | Z9: 495.05098 | AA9: 4782.6764 | AB9: 147.68165 | AC9: 4640.6231 | AD9: 6066.9782 | AE9: 5386.7613 | AF9: 836.27726 | AG9: 148.85538 | AH9: 4374.7629 | AI9: 1421.2703 | AJ9: 1185.3316 | AK9: 33.910588 | AL9: 19992.366 | AM9: 7357.7713 | AN9: 23.17207 | AO9: 210.05728 | AP9: 406.45276 | AQ9: 1067.39 | AR9: 1300.1278 | AS9: 17117.538 | AT9: 1003.6567 | AU9: 12145.913 | AV9: 223.13297 | AW9: 5525.5745 | AX9: 4363.2061 | AY9: 1348.7108 | AZ9: 1459.1092 | BA9: 1714.7955 | BB9: 1301.6431 | BC9: 12720.488 | BD9: 1340.6342 | BE9: 2518.3037 | BF9: 1306.5426 | BG9: 8595.5832 | BH9: 19036.617 | BI9: 11540.904 | BJ9: 50.557085 | BK9: 20142.764 | BL9: 2493.6555 | BM9: 3435.5495 | BN9: 15.243287 | BO9: 781.22828 | BP9: 1247.661
A10: egy.coa.leontiefs | B10: egy | C10: 2014 | D10: coa | E10: 0.00071293776 | F10: 0.0040886057 | G10: 0.0015429125 | H10: 0.0023684092 | I10: 0.0010255824 | J10: 0.005287378 | K10: 0.00076123581 | L10: 0.00030083199 | M10: 0.0050366652 | N10: 1.0461093 | O10: 0.0008754092 | P10: 0.00032878451 | Q10: 0.0010438748 | R10: 0.0062566465 | S10: 0.0038283704 | T10: 0.0048748951 | U10: 0.0070818742 | V10: 0.0018617365 | W10: 0.00062294927 | X10: 0.00085694958 | Y10: 0.0018874857 | Z10: 0.0091468307 | AA10: 0.00044422122 | AB10: 0.0025655393 | AC10: 0.0034932535 | AD10: 0.00069900296 | AE10: 0.005368925 | AF10: 0.010544773 | AG10: 0.0018594003 | AH10: 0.0021502812 | AI10: 0.00099421207 | AJ10: 0.0010622318 | AK10: 0.00032408923 | AL10: 0.00230913 | AM10: 0.00036130771 | AN10: 0.00042970216 | AO10: 0.007257185 | AP10: 0.0099145312 | AQ10: 0.00020450565 | AR10: 0.00061907041 | AS10: 0.002029651 | AT10: 0.0055131315 | AU10: 0.003006929 | AV10: 0.0031986102 | AW10: 0.0044482808 | AX10: 0.0011641153 | AY10: 0.00072906753 | AZ10: 0.0021508867 | BA10: 0.0030726098 | BB10: 0.00086932638 | BC10: 0.0011420834 | BD10: 0.0052659859 | BE10: 0.00032247781 | BF10: 0.001935427 | BG10: 0.0017398388 | BH10: 0.00069707851 | BI10: 0.00064205997 | BJ10: 0.00059416263 | BK10: 0.0019527509 | BL10: 0.0022581944 | BM10: 0.0011397737 | BN10: 0.0029381207 | BO10: 0.0040152374 | BP10: 0.0038588635
A11: egy.ely.leontiefs | B11: egy | C11: 2014 | D11: ely | E11: 0.0051899006 | F11: 0.0024449047 | G11: 0.0017552918 | H11: 0.0035076868 | I11: 0.002020499 | J11: 0.0106773 | K11: 0.0014849727 | L11: 0.0015267666 | M11: 0.0045724546 | N11: 0.005488032 | O11: 0.0018586777 | P11: 0.0003987774 | Q11: 0.0058187357 | R11: 0.0081245953 | S11: 0.011121402 | T11: 0.99546625 | U11: 0.0067390269 | V11: 0.0031751126 | W11: 0.0054874007 | X11: 0.0018880788 | Y11: 0.0044259418 | Z11: 0.021901742 | AA11: 0.001384736 | AB11: 0.0028095683 | AC11: 0.0042283706 | AD11: 0.0016657201 | AE11: 0.0061670023 | AF11: 0.013390797 | AG11: 0.00044616958 | AH11: 0.004706571 | AI11: 0.001930288 | AJ11: 0.0020638589 | AK11: 0.00072598309 | AL11: 0.0032060906 | AM11: 0.0015388885 | AN11: 0.00049414236 | AO11: 0.0082294156 | AP11: 0.018854431 | AQ11: 0.00082933911 | AR11: 0.0013144091 | AS11: 0.0045040225 | AT11: 0.0069754029 | AU11: 0.002510308 | AV11: 0.01480155 | AW11: 0.00065309808 | AX11: 0.002038649 | AY11: 0.0013699663 | AZ11: 0.0042390408 | BA11: 0.0088071642 | BB11: 0.0018513483 | BC11: 0.0050957808 | BD11: 0.0068911307 | BE11: 0.0040963127 | BF11: 0.0028719782 | BG11: 0.0032871279 | BH11: 0.0039921343 | BI11: 0.0013093981 | BJ11: 0.0013104148 | BK11: 0.0027905719 | BL11: 0.0039188154 | BM11: 0.0024691904 | BN11: 0.0037120385 | BO11: 0.0027984899 | BP11: 0.013165722
A12: egy.nga.leontiefs | B12: egy | C12: 2014 | D12: nga | E12: 0.0028174112 | F12: 0.0098443475 | G12: 0.0022552544 | H12: 0.020527135 | I12: 0.0033915006 | J12: 0.036056683 | K12: 0.0013438412 | L12: 0.0012866749 | M12: 0.006514764 | N12: 0.0058772465 | O12: 0.0027867048 | P12: 0.00055785463 | Q12: 0.0036944388 | R12: 0.0080991921 | S12: 0.0078575836 | T12: 0.3346549 | U12: 0.011345328 | V12: 0.0031233113 | W12: 0.0031889198 | X12: 0.003142747 | Y12: 0.0049420267 | Z12: 0.02315565 | AA12: 0.0010571833 | AB12: 0.0042126651 | AC12: 0.0057045044 | AD12: 0.0021254598 | AE12: 0.0070654794 | AF12: 0.014040655 | AG12: 1.0671175 | AH12: 0.007276738 | AI12: 0.0030796279 | AJ12: 0.0018703103 | AK12: 0.0010937224 | AL12: 0.0052675052 | AM12: 0.0010049524 | AN12: 0.0066262244 | AO12: 0.0080489506 | AP12: 0.02345994 | AQ12: 0.00077185126 | AR12: 0.0022400686 | AS12: 0.0035896431 | AT12: 0.0070657665 | AU12: 0.0075210638 | AV12: 0.013571239 | AW12: 0.011209994 | AX12: 0.003362761 | AY12: 0.0025275958 | AZ12: 0.0073488753 | BA12: 0.011029166 | BB12: 0.0029168923 | BC12: 0.0040276541 | BD12: 0.026432447 | BE12: 0.0018488888 | BF12: 0.0050162111 | BG12: 0.0038882112 | BH12: 0.0021638066 | BI12: 0.0022369686 | BJ12: 0.0022201566 | BK12: 0.003973374 | BL12: 0.0038267499 | BM12: 0.0038085701 | BN12: 0.0044883704 | BO12: 0.010089137 | BP12: 0.0087122558
A13: egy.oil.leontiefs | B13: egy | C13: 2014 | D13: oil | E13: 0.010716541 | F13: 0.2196354 | G13: 0.011477364 | H13: 0.026425123 | I13: 0.034986379 | J13: 0.1376497 | K13: 0.0077011269 | L13: 0.0065115891 | M13: 0.033628891 | N13: 0.038121162 | O13: 0.028143213 | P13: 0.0023724332 | Q13: 0.015895705 | R13: 0.036175723 | S13: 0.030044833 | T13: 0.47496993 | U13: 0.050466724 | V13: 0.041312036 | W13: 0.021481993 | X13: 0.030895442 | Y13: 0.020772998 | Z13: 0.087703373 | AA13: 0.0090933757 | AB13: 0.02292075 | AC13: 0.034763749 | AD13: 0.011373216 | AE13: 0.031647681 | AF13: 0.061171613 | AG13: 0.038080443 | AH13: 0.0411401 | AI13: 0.02903113 | AJ13: 0.013760912 | AK13: 0.010085771 | AL13: 0.035776979 | AM13: 0.0066732154 | AN13: 1.0207195 | AO13: 0.032826154 | AP13: 0.087175409 | AQ13: 0.0042949926 | AR13: 0.02201606 | AS13: 0.019401564 | AT13: 0.027868031 | AU13: 0.17610436 | AV13: 0.15292042 | AW13: 0.90839666 | AX13: 0.027938921 | AY13: 0.024083252 | AZ13: 0.072818957 | BA13: 0.04672633 | BB13: 0.027012961 | BC13: 0.016146144 | BD13: 0.03811564 | BE13: 0.0069271214 | BF13: 0.039756049 | BG13: 0.026203876 | BH13: 0.015403713 | BI13: 0.021201727 | BJ13: 0.021202304 | BK13: 0.019571944 | BL13: 0.016674708 | BM13: 0.039365021 | BN13: 0.052822039 | BO13: 0.18033187 | BP13: 0.040217747
A14: egy.p_c.leontiefs | B14: egy | C14: 2014 | D14: p_c | E14: 0.015123998 | F14: 0.30610357 | G14: 0.016911444 | H14: 0.038789812 | I14: 0.046877066 | J14: 0.1952503 | K14: 0.011338488 | L14: 0.0089119242 | M14: 0.05358302 | N14: 0.055614507 | O14: 0.03742626 | P14: 0.0036133173 | Q14: 0.022661792 | R14: 0.057423271 | S14: 0.04503134 | T14: 0.57686745 | U14: 0.079995265 | V14: 0.05979155 | W14: 0.028161882 | X14: 0.043234725 | Y14: 0.029950238 | Z14: 0.13476849 | AA14: 0.013149606 | AB14: 0.036219519 | AC14: 0.052494529 | AD14: 0.016932996 | AE14: 0.04985246 | AF14: 0.10281369 | AG14: 0.046312795 | AH14: 0.058405776 | AI14: 0.040545559 | AJ14: 0.020787865 | AK14: 0.014751221 | AL14: 0.051782047 | AM14: 0.0098920946 | AN14: 0.012404508 | AO14: 0.057454006 | AP14: 0.13795708 | AQ14: 0.0058634775 | AR14: 0.030243338 | AS14: 0.029784373 | AT14: 0.044757439 | AU14: 0.22862753 | AV14: 0.19989924 | AW14: 1.0457075 | AX14: 0.039811926 | AY14: 0.034471907 | AZ14: 0.10217539 | BA14: 0.069164281 | BB14: 0.038993376 | BC14: 0.023832004 | BD14: 0.05894958 | BE14: 0.0099352726 | BF14: 0.057076432 | BG14: 0.036634089 | BH14: 0.022591817 | BI14: 0.030404983 | BJ14: 0.028937268 | BK14: 0.02925885 | BL14: 0.025179403 | BM14: 0.054171184 | BN14: 0.073523937 | BO14: 0.26681712 | BP14: 0.05718286

Sheet HHSurvey
A1: Source: legacy sheet HHSurvey, extract_legacy_tables.py. Legacy table unchanged: paste the legacy data rows (all countries) at A4
A2: HHSurvey - household budget survey by sample, statistic and decile (shares in %, population, consumption)
A3: code | B3: iso3 | C3: year | D3: sample | E3: type | F3: stat_type | G3: quant_cons | H3: appliances_share | I3: ccl_share | J3: chemicals_share | K3: clothing_share | L3: coa_share | M3: communications_share | N3: die_share | O3: education_share | P3: ethanol_share | Q3: ely_share | R3: food_share | S3: fwd_share | T3: gso_share | U3: health_srv_share | V3: housing_share | W3: ker_share | X3: lpg_share | Y3: nga_share | Z3: oil_share | AA3: other_share | AB3: paper_share | AC3: pharma_share | AD3: rectourism_share | AE3: transp_eqt_share | AF3: transp_pub_share | AG3: dec_1_p1 | AH3: dec_1_p99 | AI3: dec_2_p1 | AJ3: dec_2_p99 | AK3: dec_3_p1 | AL3: dec_3_p99 | AM3: dec_4_p1 | AN3: dec_4_p99 | AO3: dec_5_p1 | AP3: dec_5_p99 | AQ3: dec_6_p1 | AR3: dec_6_p99 | AS3: dec_7_p1 | AT3: dec_7_p99 | AU3: dec_8_p1 | AV3: dec_8_p99 | AW3: dec_9_p1 | AX3: dec_9_p99 | AY3: dec_10_p1 | AZ3: dec_10_p99 | BA3: cons_pc_acrent | BB3: popw | BC3: cons_pct_acct | BD3: mean_cons_pct_acct | BE3: ely_acs_share | BF3: ICT_acs_share | BG3: sani_acs_share | BH3: wtr_acs_share | BI3: transp_pub_acs_share | BJ3: all_acs_share | BK3: pct_belowpl_215 | BL3: pct_belowpl_365 | BM3: pct_belowpl_685 | BN3: pit_share_region | BO3: pit_share_income | BP3: indv
A4: EGY.distn.bsh.dec.ove.mean.1 | B4: EGY | C4: 2017 | D4: Overall | E4: Deciles | F4: mean | G4: 1 | H4: 1.7660084 | I4: 0.0089722859 | J4: 4.3351574 | K4: 5.8943551 | L4: 0 | M4: 2.1577997 | N4: 0 | O4: 3.0112564 | P4: 0 | Q4: 3.7120453 | R4: 54.747041 | S4: 0.0005429776 | T4: 0.30729141 | U4: 3.1006242 | V4: 5.2782058 | W4: 2.0060849e-05 | X4: 2.6948595 | Y4: 0.28218716 | Z4: 0.097126146 | AA4: 0.013204305 | AB4: 2.3089435 | AC4: 4.987937 | AD4: 6.7300709 | AE4: 0.31983998 | AF4: 4.7279049 | AG4: 3284.8671 | AH4: 7041.9223 | AI4: 7290.6415 | AJ4: 8977.186 | AK4: 8805.5001 | AL4: 10197.236 | AM4: 9770.5707 | AN4: 10221.349 | AO4: 11592.96 | AP4: 12929.541 | AQ4: 12539.419 | AR4: 13935.293 | AS4: 13974.452 | AT4: 15280.874 | AU4: 15743.841 | AV4: 18052.785 | AW4: 19369.722 | AX4: 21950.235 | AY4: 22419.644 | AZ4: 62042.895 | BA4: 5229.7958 | BB4: 10019634 | BC4: 99.050586 | BD4: 99.255858 | BE4: 108.54317 | BF4: 33.730254 | BG4: 43.33268 | BH4: 98.103729 | BI4: 112.34322 | BJ4: 72.135154 | BK4: 0.17223852 | BL4: 2.9525464 | BM4: 10.042934 | BN4: 0.72535675 | BO4: 0.79716045 | BP4: 1.5541052
A5: EGY.distn.bsh.dec.ove.mean.2 | B5: EGY | C5: 2017 | D5: Overall | E5: Deciles | F5: mean | G5: 2 | H5: 1.687002 | I5: 0.0052755284 | J5: 3.9032876 | K5: 5.4717862 | L5: 0 | M5: 2.3558276 | N5: 0 | O5: 3.9577508 | P5: 0 | Q5: 3.3868689 | R5: 60.147961 | S5: 0.00026300327 | T5: 0.36343148 | U5: 3.1369988 | V5: 4.3916579 | W5: 2.3127734e-05 | X5: 2.3273985 | Y5: 0.27367429 | Z5: 0.10075626 | AA5: 0.0086808774 | AB5: 2.2875912 | AC5: 4.8897175 | AD5: 6.677071 | AE5: 0.30705763 | AF5: 4.2752158 | AG5: 3049.4171 | AH5: 7210.6993 | AI5: 6635.2072 | AJ5: 8561.6366 | AK5: 8722.0051 | AL5: 9005.0763 | AM5: 9616.3761 | AN5: 11677.673 | AO5: 11347.612 | AP5: 11766.322 | AQ5: 12624.153 | AR5: 14170.425 | AS5: 14544.584 | AT5: 15251.926 | AU5: 15388.248 | AV5: 17883.038 | AW5: 18174.78 | AX5: 23470.864 | AY5: 24406.326 | AZ5: 64433.558 | BA5: 6664.2194 | BB5: 9844693 | BC5: 106.14401 | BD5: 110.65442 | BE5: 106.88168 | BF5: 42.572126 | BG5: 59.360215 | BH5: 106.64412 | BI5: 113.28458 | BJ5: 79.161338 | BK5: 0.0097684183 | BL5: 0.011442196 | BM5: 10.963907 | BN5: 1.9374274 | BO5: 2.0971337 | BP5: 1.6507933
A6: EGY.distn.bsh.dec.ove.mean.3 | B6: EGY | C6: 2017 | D6: Overall | E6: Deciles | F6: mean | G6: 3 | H6: 1.6464771 | I6: 0.0055361033 | J6: 3.5477598 | K6: 6.5285495 | L6: 0 | M6: 2.3583571 | N6: 0 | O6: 4.1836152 | P6: 0 | Q6: 3.4977952 | R6: 54.888944 | S6: 0.0003015262 | T6: 0.43834922 | U6: 3.8631265 | V6: 4.9096157 | W6: 1.025383e-05 | X6: 2.1304738 | Y6: 0.29012724 | Z6: 0.1377628 | AA6: 0.0063969053 | AB6: 2.2232985 | AC6: 4.8673438 | AD6: 6.7337389 | AE6: 0.30826151 | AF6: 4.403088 | AG6: 3045.2636 | AH6: 7394.2191 | AI6: 7072.6927 | AJ6: 8942.0209 | AK6: 8390.8638 | AL6: 9057.5908 | AM6: 9943.365 | AN6: 11305.443 | AO6: 11287.313 | AP6: 12722.65 | AQ6: 12705.447 | AR6: 13307.217 | AS6: 14013.048 | AT6: 14463.29 | AU6: 14737.694 | AV6: 17205.948 | AW6: 19071.164 | AX6: 21505.828 | AY6: 23283.089 | AZ6: 61617.432 | BA6: 8231.7709 | BB6: 11193191 | BC6: 98.850116 | BD6: 106.75791 | BE6: 99.553979 | BF6: 50.112631 | BG6: 61.082464 | BH6: 104.01421 | BI6: 105.28867 | BJ6: 88.02387 | BK6: 0 | BL6: 0.0069918601 | BM6: 10.359791 | BN6: 3.1214459 | BO6: 2.7348698 | BP6: 1.607978
